Workbook

Sheet SE1000 (черный лист)
M1: Курс Eвро | N1: 72.57 | AE1: 0.95 | AH1: скидка
B2: Провенто | E2: УЗОЛА | H2: Rittal | O2: DKS (CE) | U2: DKS (ST) | AA2: IPEX
B3: Артикул | C3: Прайсовая цена, руб с НДС | D3: Цена со стандартной скидкой для щитовиков 25% | E3: Артикул | F3: Наименование | G3: Прайсовая цена, руб с НДС | H3: Артикул | I3: Наименование | J3: Прайсовая цена Rittal, евро с НДС | K3: Прайсовая цена Rittal, руб с НДС | L3: наличие в Казани | M3: цена ЭТМ со скидкой | N3: Прайс ЭТМ (розница) | O3: Артикул | P3: Наименование | Q3: Прайсовая цена ДКС, руб с НДС | R3: наличие в Казани | S3: цена ЭТМ со скидкой | T3: Прайс ЭТМ (розница) | U3: Артикул | V3: Наименование | W3: Прайсовая цена ДКС, руб с НДС | X3: наличие в Казани | Y3: цена ЭТМ со скидкой | Z3: Прайс ЭТМ (розница) | AA3: А, мм. | AB3: В, мм. | AC3: С, мм. | AD3: Артикул | AE3: цена со скидкой 5% от DKC (ST)-24 столб | AF3: Прайсовая цена | AH3: сумма со скидкой на объем складского запаса | AL3: Себестоимость
B4: MES 30.20.15 | C4: 3055 | D4: =C4*0.75 -> 2291.25 | E4: U7521302015 | F4: Корпус UC2 30.20.15 IP66 USOLA | G4: 2644 | H4: 1035500 | I4: AE Шкаф RAL7035, с МП, 200x300x155mm | J4: 46.49 | K4: =J4*$N$1 -> 3373.7793 | M4: 3,126.06 | N4: 3,866.00 | O4: R5CE0231 | P4: Навесной шкаф CE, 200 х 300 х 150мм, IP66 | Q4: 4682.79 | R4: 0 | S4: 3868.04 | T4: 5012 | U4: R5ST0231 | V4: Корпус сварной навесной серии ST с М/П Размер: 200 x 300 x 150 мм (В х Ш х Г) | W4: 2814.02 | X4: 19 | Y4: 2324.41 | Z4: 3012 | AA4: 300 | AB4: 200 | AC4: 150 | AD4: SЕ1001 | AE4: =Y4*$AE$1 -> 2208.1895 | AF4: =AE4/0.75 -> 2944.2527 | AG4: =ROUND(AF4,0) -> 2944 | AH4: =X47*AE4 -> 13249.137 | AI4: 1 | AJ4: =2*(AA4*AB4+AB4*AC4+AA4*AC4)/1000000 -> 0.27 | AK4: =AE4/AJ4 -> 8178.4796 | AL4: 3541.4
D5: =C5*0.75 -> 0 | K5: =J5*$N$1 -> 0 | O5: R5CE0391 | P5: Навесной шкаф CE, 300 x 250 x 150мм, IP66 | Q5: 4838.95 | R5: 0 | S5: 3997.03 | T5: 5179 | U5: R5ST0391 | V5: Корпус сварной навесной серии ST с М/П Размер: 300 x 250 x 150 мм (В х Ш х Г) | W5: 2899.45 | X5: 7 | Y5: 2394.98 | Z5: 3103 | AA5: 300 | AB5: 250 | AC5: 150 | AD5: SE1002 | AE5: =Y5*$AE$1 -> 2275.231 | AF5: =AE5/0.75 -> 3033.6413 | AG5: =ROUND(AF5,0) -> 3034 | AH5: =X4*AE5 -> 43229.389 | AI5: 1 | AJ5: =2*(AA5*AB5+AB5*AC5+AA5*AC5)/1000000 -> 0.315 | AK5: =AE5/AJ5 -> 7222.9556
B6: MES 30.30.15 | C6: 3433 | D6: =C6*0.75 -> 2574.75 | E6: U7521303015 | F6: Корпус UC2 30.30.15 IP66 USOLA | G6: 2970 | H6: 1036500 | I6: AE Шкаф RAL7035 с МП, 300x300x155mm | J6: 59.22 | K6: =J6*$N$1 -> 4297.5954 | M6: 3,983.30 | N6: 4,926.00 | O6: R5CE0331 | P6: Навесной шкаф CE, 300 x 300 x 150мм, IP66 | Q6: 5205.09 | R6: 0 | S6: 4299.47 | T6: 5571 | U6: R5ST0331 | V6: Корпус сварной навесной серии ST с М/П Размер: 300 x 300 x 150 мм (В х Ш х Г) | W6: 3080.11 | X6: 55 | Y6: 2544.21 | Z6: 3296 | AA6: 300 | AB6: 300 | AC6: 150 | AD6: SE1003 | AE6: =Y6*$AE$1 -> 2416.9995 | AF6: =AE6/0.75 -> 3222.666 | AG6: =ROUND(AF6,0) -> 3223 | AH6: =X5*AE6 -> 16918.997 | AI6: 1 | AJ6: =2*(AA6*AB6+AB6*AC6+AA6*AC6)/1000000 -> 0.36 | AK6: =AE6/AJ6 -> 6713.8875
B7: MES 30.40.15 | C7: 3487 | D7: =C7*0.75 -> 2615.25 | E7: U7521304015 | F7: Корпус UC2 30.40.15 IP66 USOLA | G7: 3264 | H7: 1030500 | I7: AE Шкаф RAL7035, с МП, 380x300x155mm | J7: 57 | K7: =J7*$N$1 -> 4136.49 | M7: 3,833.29 | N7: 4,741.00 | O7: R5CE0341 | P7: Навесной шкаф CE, 300 x 400 x 150мм, IP66 | Q7: 5393.08 | R7: 0 | S7: 4454.75 | T7: 5772 | U7: R5ST0341 | V7: Корпус сварной навесной серии ST с М/П Размер: 300 x 400 x 150 мм (В х Ш х Г) | W7: 3182.84 | X7: 12 | Y7: 2629.06 | Z7: 3406 | AA7: 300 | AB7: 400 | AC7: 150 | AD7: SE1004 | AE7: =Y7*$AE$1 -> 2497.607 | AF7: =AE7/0.75 -> 3330.1427 | AG7: =ROUND(AF7,0) -> 3330 | AH7: =X6*AE7 -> 137368.39 | AI7: 1 | AJ7: =2*(AA7*AB7+AB7*AC7+AA7*AC7)/1000000 -> 0.45 | AK7: =AE7/AJ7 -> 5550.2378
D8: =C8*0.75 -> 0 | E8: U7521304020 | F8: Корпус UC2 30.40.20 IP66 USOLA | G8: 3078 | H8: 1031500 | I8: AE Шкаф RAL7035 с МП, 380x300x210mm | J8: 62.34 | K8: =J8*$N$1 -> 4524.0138 | L8: 0 | M8: 4,192.61 | N8: 5,185.00 | O8: R5CE0342 | P8: Навесной шкаф CE, 300 х 400 х 200мм, IP66 | Q8: 5901.76 | R8: 0 | S8: 4874.92 | T8: 6316 | U8: R5ST0342 | V8: Корпус сварной навесной серии ST с М/П Размер: 300 x 400 x 200 мм (В х Ш х Г) | W8: 3116.51 | X8: 18 | Y8: 2574.28 | Z8: 3335 | AA8: 300 | AB8: 400 | AC8: 200 | AD8: SE1005 | AE8: =Y8*$AE$1 -> 2445.566 | AF8: =AE8/0.75 -> 3260.7547 | AG8: =ROUND(AF8,0) -> 3261 | AH8: =X7*AE8 -> 29346.792 | AI8: 1 | AJ8: =2*(AA8*AB8+AB8*AC8+AA8*AC8)/1000000 -> 0.52 | AK8: =AE8/AJ8 -> 4703.0115
B9: MES 40.30.15 | C9: 3552 | D9: =C9*0.75 -> 2664 | E9: U7521403015 | F9: Корпус UC2 40.30.15 IP66 USOLA | G9: 3049 | K9: =J9*$N$1 -> 0 | O9: R5CE0431 | P9: Навесной шкаф CE, 400 x 300 x 150мм, IP66 | Q9: 5867.24 | R9: 0 | S9: 4846.41 | T9: 6279 | U9: R5ST0431 | V9: Корпус сварной навесной серии ST с М/П Размер: 400 x 300 x 150 мм (В х Ш х Г) | W9: 3285.53 | X9: 14 | Y9: 2713.88 | Z9: 3516 | AA9: 400 | AB9: 300 | AC9: 150 | AD9: SE1006 | AE9: =Y9*$AE$1 -> 2578.186 | AF9: =AE9/0.75 -> 3437.5813 | AG9: =ROUND(AF9,0) -> 3438 | AH9: =X8*AE9 -> 46407.348 | AI9: 1 | AJ9: =2*(AA9*AB9+AB9*AC9+AA9*AC9)/1000000 -> 0.45 | AK9: =AE9/AJ9 -> 5729.3022
B10: MES 40.30.21 | C10: 4028 | D10: =C10*0.75 -> 3021 | E10: U7521403020 | F10: Корпус UC2 40.30.20 IP66 USOLA | G10: 3457 | H10: 1034500 | I10: AE Шкаф RAL7035, с МП, 300x400x210mm | J10: 66.36 | K10: =J10*$N$1 -> 4815.7452 | L10: 4 | M10: 4,462.64 | N10: 5,519.00 | O10: R5CE0432 | P10: Навесной шкаф CE, 400 x 300 x 200мм, IP66 | Q10: 6187.28 | R10: 0 | S10: 5110.77 | T10: 6622 | U10: R5ST0432 | V10: Корпус сварной навесной серии ST с М/П Размер: 400 x 300 x 200 мм (В х Ш х Г) | W10: 3664.86 | X10: 38 | Y10: 3027.22 | Z10: 3922 | AA10: 400 | AB10: 300 | AC10: 200 | AD10: SE1007 | AE10: =Y10*$AE$1 -> 2875.859 | AF10: =AE10/0.75 -> 3834.4787 | AG10: =ROUND(AF10,0) -> 3834 | AH10: =X9*AE10 -> 40262.026 | AI10: 1 | AJ10: =2*(AA10*AB10+AB10*AC10+AA10*AC10)/1000000 -> 0.52 | AK10: =AE10/AJ10 -> 5530.4981
B11: MES 40.40.21 | C11: 4417 | D11: =C11*0.75 -> 3312.75 | E11: U7521404020 | F11: Корпус UC2 40.40.20 IP66 USOLA | G11: 3791 | H11: 1380500 | I11: AE Шкаф RAL7035, с МП, 380x380x210mm | J11: 66.08 | K11: =J11*$N$1 -> 4795.4256 | L11: 5 | M11: 4,444.07 | N11: 5,496.00 | O11: R5CE0442 | P11: Навесной шкаф CE, 400 x 400 x 200мм, IP66 | Q11: 6329.86 | R11: 0 | S11: 5228.54 | T11: 6774 | U11: R5ST0442 | V11: Корпус сварной навесной серии ST с М/П Размер: 400 x 400 x 200 мм (В х Ш х Г) | W11: 3712.47 | Y11: 3066.55 | Z11: 3973 | AA11: 400 | AB11: 400 | AC11: 200 | AD11: SE1008 | AE11: =Y11*$AE$1 -> 2913.2225 | AF11: =AE11/0.75 -> 3884.2967 | AG11: =ROUND(AF11,0) -> 3884 | AH11: =X10*AE11 -> 110702.45 | AI11: 1 | AJ11: =2*(AA11*AB11+AB11*AC11+AA11*AC11)/1000000 -> 0.64 | AK11: =AE11/AJ11 -> 4551.9102
B12: MES 40.60.21 | C12: 5296 | D12: =C12*0.75 -> 3972 | E12: U7521406020 | F12: Корпус UC2 40.60.20 IP66 USOLA | G12: 4547 | H12: 1039500 | I12: AE Шкаф RAL7035, с МП, 600x380x210mm | J12: 87.29 | K12: =J12*$N$1 -> 6334.6353 | L12: 1 | M12: 5,870.65 | N12: 7,260.00 | O12: R5CE0462 | P12: Навесной шкаф CE, 400 x 600 x 200мм, IP65 | Q12: 8646.76 | R12: 0 | S12: 7142.33 | T12: 9254 | U12: R5ST0462 | V12: Корпус сварной навесной серии ST с М/П Размер: 400 x 600 x 200 мм (В х Ш х Г) | W12: 5353.26 | X12: 20 | Y12: 4421.86 | Z12: 5729 | AA12: 400 | AB12: 600 | AC12: 200 | AD12: SE1009 | AE12: =Y12*$AE$1 -> 4200.767 | AF12: =AE12/0.75 -> 5601.0227 | AG12: =ROUND(AF12,0) -> 5601 | AH12: =X11*AE12 -> 0 | AI12: 1 | AJ12: =2*(AA12*AB12+AB12*AC12+AA12*AC12)/1000000 -> 0.88 | AK12: =AE12/AJ12 -> 4773.5989
B13: MES 50.30.21 | C13: 4782 | D13: =C13*0.75 -> 3586.5 | E13: U7521503015 | F13: Корпус UC2 50.30.15 IP66 USOLA | G13: 4074 | K13: =J13*$N$1 -> 0 | O13: R5CE0531 | P13: Навесной шкаф CE, 500 x 300 x 150мм, IP66 | Q13: 7038.49 | R13: 0 | S13: 5813.87 | T13: 7533 | U13: R5ST0531 | V13: Корпус сварной навесной серии ST с М/П Размер: 500 x 300 x 150 мм (В х Ш х Г) | W13: 4205.05 | X13: 11 | Y13: 3473.42 | Z13: 4500 | AA13: 500 | AB13: 300 | AC13: 150 | AD13: SE1010 | AE13: =Y13*$AE$1 -> 3299.749 | AF13: =AE13/0.75 -> 4399.6653 | AG13: =ROUND(AF13,0) -> 4400 | AH13: =X12*AE13 -> 65994.98 | AI13: 1 | AJ13: =2*(AA13*AB13+AB13*AC13+AA13*AC13)/1000000 -> 0.54 | AK13: =AE13/AJ13 -> 6110.6463
D14: =C14*0.75 -> 0 | E14: U7521503020 | F14: Корпус UC2 50.30.20 IP66 USOLA | G14: 4106 | K14: =J14*$N$1 -> 0 | O14: R5CE0532 | P14: Навесной шкаф CE, 500 x 300 x 200мм, IP66 | Q14: 7258.41 | R14: 0 | S14: 5995.53 | T14: 7768 | U14: R5ST0532 | V14: Корпус сварной навесной серии ST с М/П Размер: 500 x 300 x 200 мм (В х Ш х Г) | W14: 4570.97 | X14: 10 | Y14: 3775.67 | Z14: 4892 | AA14: 500 | AB14: 300 | AC14: 200 | AD14: SE1011 | AE14: =Y14*$AE$1 -> 3586.8865 | AF14: =AE14/0.75 -> 4782.5153 | AG14: =ROUND(AF14,0) -> 4783 | AH14: =X13*AE14 -> 39455.751 | AI14: 1 | AJ14: =2*(AA14*AB14+AB14*AC14+AA14*AC14)/1000000 -> 0.62 | AK14: =AE14/AJ14 -> 5785.3008
B15: MES 50.40.21 | C15: 5078 | D15: =C15*0.75 -> 3808.5 | E15: U7521504020 | F15: Корпус UC2 50.40.20 IP66 USOLA | G15: 4360 | H15: 1045500 | I15: AE Шкаф RAL7035 с МП, 400x500x210mm | J15: 76.4 | K15: =J15*$N$1 -> 5544.348 | L15: 2 | M15: 5,138.43 | N15: 6,355.00 | O15: R5CE0542 | P15: Навесной шкаф CE, 500 x 400 x 200мм, IP66 | Q15: 7355.23 | R15: 0 | S15: 6075.5 | T15: 7872 | U15: R5ST0542 | V15: Корпус сварной навесной серии ST с М/П Размер: 500 x 400 x 200 мм (В х Ш х Г) | W15: 4645.98 | X15: 22 | Y15: 3837.63 | Z15: 4972 | AA15: 500 | AB15: 400 | AC15: 200 | AD15: SE1012 | AE15: =Y15*$AE$1 -> 3645.7485 | AF15: =AE15/0.75 -> 4860.998 | AG15: =ROUND(AF15,0) -> 4861 | AH15: =X14*AE15 -> 36457.485 | AI15: 1 | AJ15: =2*(AA15*AB15+AB15*AC15+AA15*AC15)/1000000 -> 0.76 | AK15: =AE15/AJ15 -> 4797.0375
B16: MES 50.50.21 | C16: 5625 | D16: =C16*0.75 -> 4218.75 | E16: U7521505020 | F16: Корпус UC2 50.50.20 IP66 USOLA | G16: 4829 | H16: 1050500 | I16: AE Шкаф RAL7035 с МП, 500x500x210mm | J16: 92.85 | K16: =J16*$N$1 -> 6738.1245 | L16: 0 | M16: 6,244.97 | N16: 7,723.00 | O16: R5CE0552 | P16: Навесной шкаф CE, 500 x 500 x 200мм, IP65 | Q16: 9198.97 | R16: 0 | S16: 7598.46 | T16: 9845 | U16: R5ST0552 | V16: Корпус сварной навесной серии ST с М/П Размер: 500 x 500 x 200 мм (В х Ш х Г) | W16: 5304.16 | X16: 63 | Y16: 4381.3 | Z16: 5677 | AA16: 500 | AB16: 500 | AC16: 200 | AD16: SE1013 | AE16: =Y16*$AE$1 -> 4162.235 | AF16: =AE16/0.75 -> 5549.6467 | AG16: =ROUND(AF16,0) -> 5550 | AH16: =X15*AE16 -> 91569.17 | AI16: 1 | AJ16: =2*(AA16*AB16+AB16*AC16+AA16*AC16)/1000000 -> 0.9 | AK16: =AE16/AJ16 -> 4624.7056
D17: =C17*0.75 -> 0 | K17: =J17*$N$1 -> 0 | O17: R5CE0562 | P17: Навесной шкаф CE, 500 х 600 х 200мм, IP65 | Q17: 10557.71 | R17: 0 | S17: 8720.79 | T17: 11299 | U17: R5ST0562 | V17: Корпус сварной навесной серии ST с М/П Размер: 500 x 600 x 200 мм (В х Ш х Г) | W17: 5760.19 | X17: 0 | Y17: 4757.98 | Z17: 6165 | AA17: 500 | AB17: 600 | AC17: 200 | AD17: SE1014 | AE17: =Y17*$AE$1 -> 4520.081 | AF17: =AE17/0.75 -> 6026.7747 | AG17: =ROUND(AF17,0) -> 6027 | AH17: =X16*AE17 -> 284765.1 | AI17: 1 | AJ17: =2*(AA17*AB17+AB17*AC17+AA17*AC17)/1000000 -> 1.04 | AK17: =AE17/AJ17 -> 4346.2317
B18: MES 50.40.25 | C18: 5543 | D18: =C18*0.75 -> 4157.25 | E18: U7521504025 | F18: Корпус UC2 50.40.25 IP66 USOLA | G18: 4759 | K18: =J18*$N$1 -> 0 | O18: R5CE0549 | P18: Навесной шкаф CE, 500 x 400 x 250мм, IP65 | Q18: 8320.79 | R18: 0 | S18: 6873.08 | T18: 8905 | U18: R5ST0549 | V18: Корпус сварной навесной серии ST с М/П Размер: 500 x 400 x 250 мм (В х Ш х Г) | W18: 5135.3 | X18: 15 | Y18: 4241.82 | Z18: 5496 | AA18: 500 | AB18: 400 | AC18: 250 | AD18: SE1015 | AE18: =Y18*$AE$1 -> 4029.729 | AF18: =AE18/0.75 -> 5372.972 | AG18: =ROUND(AF18,0) -> 5373 | AH18: =X17*AE18 -> 0 | AI18: 1 | AJ18: =2*(AA18*AB18+AB18*AC18+AA18*AC18)/1000000 -> 0.85 | AK18: =AE18/AJ18 -> 4740.8576
D19: =C19*0.75 -> 0 | H19: 1350500 | I19: AE Шкаф RAL7035, с МП, 500x500x300mm | J19: 128.55 | K19: =J19*$N$1 -> 9328.8735 | L19: 0 | M19: 8,645.97 | N19: 10,692.00 | O19: R5CE0553 | P19: Навесной шкаф CE, 500 х 500 х 300мм, IP65 | Q19: 11877.42 | R19: 0 | S19: 9810.89 | T19: 12711 | U19: R5ST0553 | V19: Корпус сварной навесной серии ST с М/П Размер: 500 x 500 x 300 мм (В х Ш х Г) | W19: 6895.38 | X19: 25 | Y19: 5695.67 | Z19: 7380 | AA19: 500 | AB19: 500 | AC19: 300 | AD19: SE1016 | AE19: =Y19*$AE$1 -> 5410.8865 | AF19: =AE19/0.75 -> 7214.5153 | AG19: =ROUND(AF19,0) -> 7215 | AH19: =X18*AE19 -> 81163.298 | AI19: 1 | AJ19: =2*(AA19*AB19+AB19*AC19+AA19*AC19)/1000000 -> 1.1 | AK19: =AE19/AJ19 -> 4918.9877
D20: =C20*0.75 -> 0 | K20: =J20*$N$1 -> 0 | O20: R5CE0563 | P20: Навесной шкаф CE, 500 х 600 х 300мм, IP65 | Q20: 12453.46 | R20: 0 | S20: 10286.71 | T20: 13328 | U20: R5ST0563 | V20: Корпус сварной навесной серии ST с М/П Размер: 500 x 600 x 300 мм (В х Ш х Г) | W20: 7488.24 | X20: 2 | Y20: 6185.37 | Z20: 8014 | AA20: 500 | AB20: 600 | AC20: 300 | AD20: SE1017 | AE20: =Y20*$AE$1 -> 5876.1015 | AF20: =AE20/0.75 -> 7834.802 | AG20: =ROUND(AF20,0) -> 7835 | AH20: =X19*AE20 -> 146902.54 | AI20: 1 | AJ20: =2*(AA20*AB20+AB20*AC20+AA20*AC20)/1000000 -> 1.26 | AK20: =AE20/AJ20 -> 4663.5726
B21: MES 60.40.21 | C21: 5189 | D21: =C21*0.75 -> 3891.75 | E21: U7521604020 | F21: Корпус UC2 60.40.20 IP66 USOLA | G21: 4816 | H21: 1038500 | I21: AE Шкаф RAL7035, с МП, 380x600x210mm | J21: 81.06 | K21: =J21*$N$1 -> 5882.5242 | L21: 1 | M21: 5,452.04 | N21: 6,742.00 | O21: R5CE0642 | P21: Навесной шкаф CE, 600 x 400 x 200мм, IP65 | Q21: 8403.94 | R21: 0 | S21: 6941.75 | T21: 8994 | U21: R5ST0642 | V21: Корпус сварной навесной серии ST с М/П Размер: 600 x 400 x 200 мм (В х Ш х Г) | W21: 4912.7 | X21: 42 | Y21: 4057.95 | Z21: 5258 | AA21: 600 | AB21: 400 | AC21: 200 | AD21: SE1018 | AE21: =Y21*$AE$1 -> 3855.0525 | AF21: =AE21/0.75 -> 5140.07 | AG21: =ROUND(AF21,0) -> 5140 | AH21: =X20*AE21 -> 7710.105 | AI21: 1 | AJ21: =2*(AA21*AB21+AB21*AC21+AA21*AC21)/1000000 -> 0.88 | AK21: =AE21/AJ21 -> 4380.7415
D22: =C22*0.75 -> 0 | K22: =J22*$N$1 -> 0 | O22: R5CE0652 | P22: Навесной шкаф CE, 600 х 500 х 200мм,IP65 | Q22: 11327.53 | R22: 0 | S22: 9356.67 | T22: 12123 | U22: R5ST0652 | V22: Корпус сварной навесной серии ST с М/П Размер: 600 x 500 x 200 мм (В х Ш х Г) | W22: 6269.62 | X22: 16 | Y22: 5178.78 | Z22: 6710 | AA22: 600 | AB22: 500 | AC22: 200 | AD22: SE1019 | AE22: =Y22*$AE$1 -> 4919.841 | AF22: =AE22/0.75 -> 6559.788 | AG22: =ROUND(AF22,0) -> 6560 | AH22: =X21*AE22 -> 206633.32 | AI22: 1 | AJ22: =2*(AA22*AB22+AB22*AC22+AA22*AC22)/1000000 -> 1.04 | AK22: =AE22/AJ22 -> 4730.6163
B23: MES 60.40.25 | C23: 5847 | D23: =C23*0.75 -> 4385.25 | E23: U7521604025 | F23: Корпус UC2 60.40.25 IP66 USOLA | G23: 5020 | K23: =J23*$N$1 -> 0 | O23: R5CE0649 | P23: Навесной шкаф CE, 600 x 400 x 250мм, IP65 | Q23: 10298.46 | R23: 0 | S23: 8506.66 | T23: 11022 | U23: R5ST0649 | V23: Корпус сварной навесной серии ST с М/П Размер: 600 x 400 x 250 мм (В х Ш х Г) | W23: 5723.51 | X23: 101 | Y23: 4727.68 | Z23: 6125 | AA23: 600 | AB23: 400 | AC23: 250 | AD23: SE1020 | AE23: =Y23*$AE$1 -> 4491.296 | AF23: =AE23/0.75 -> 5988.3947 | AG23: =ROUND(AF23,0) -> 5988 | AH23: =X22*AE23 -> 71860.736 | AI23: 1 | AJ23: =2*(AA23*AB23+AB23*AC23+AA23*AC23)/1000000 -> 0.98 | AK23: =AE23/AJ23 -> 4582.9551 | AL23: 7084.8608
B24: MES 60.60.25 | C24: 7719 | D24: =C24*0.75 -> 5789.25 | E24: U7521606025 | F24: Корпус UC2 60.60.25 IP66 USOLA | G24: 6627 | H24: 1054500 | I24: AE Шкаф RAL7035 с МП, 600x600x250mm | J24: 135.9 | K24: =J24*$N$1 -> 9862.263 | L24: 0 | M24: 9,140.30 | N24: 11,304.00 | O24: R5CE0669 | P24: Навесной шкаф CE, 600 x 600 x 250мм, IP65 | Q24: 11910.4 | R24: 0 | S24: 9838.13 | T24: 12747 | U24: R5ST0669 | V24: Корпус сварной навесной серии ST с М/П Размер: 600 x 600 x 250 мм (В х Ш х Г) | W24: 6879.44 | X24: 26 | Y24: 5682.5 | Z24: 7363 | AA24: 600 | AB24: 600 | AC24: 250 | AD24: SE1021 | AE24: =Y24*$AE$1 -> 5398.375 | AF24: =AE24/0.75 -> 7197.8333 | AG24: =ROUND(AF24,0) -> 7198 | AH24: =X23*AE24 -> 545235.88 | AI24: 1 | AJ24: =2*(AA24*AB24+AB24*AC24+AA24*AC24)/1000000 -> 1.32 | AK24: =AE24/AJ24 -> 4089.678
D25: =C25*0.75 -> 0 | E25: U7521606040 | F25: Корпус UC2 60.60.40 IP66 USOLA | G25: 7729 | K25: =J25*$N$1 -> 0 | O25: R5CE0644 | P25: Навесной шкаф CE, 600 x 400 x 400мм, IP65 | Q25: 14167.6 | R25: 0 | S25: 11702.6 | T25: 15162 | U25: R5ST0644 | V25: Корпус сварной навесной серии ST с М/П Размер: 600 x 400 x 400 мм (В х Ш х Г) | W25: 7692.69 | X25: 4 | Y25: 6354.25 | Z25: 8233 | AA25: 600 | AB25: 400 | AC25: 400 | AD25: SE1022 | AE25: =Y25*$AE$1 -> 6036.5375 | AF25: =AE25/0.75 -> 8048.7167 | AG25: =ROUND(AF25,0) -> 8049 | AH25: =X24*AE25 -> 156949.97 | AI25: 1 | AJ25: =2*(AA25*AB25+AB25*AC25+AA25*AC25)/1000000 -> 1.28 | AK25: =AE25/AJ25 -> 4716.0449
D26: =C26*0.75 -> 0 | E26: U7521606035 | F26: Корпус UC2 60.60.35 IP66 USOLA | G26: 7392 | H26: 1360500 | I26: AE Шкаф RAL7035, с МП, 600x600x350mm | J26: 161.27 | K26: =J26*$N$1 -> 11703.364 | L26: 2 | M26: 10,846.93 | N26: 13,414.00 | O26: R5CE0664 | P26: Навесной шкаф CE, 600 x 600 x 400мм, IP65 | Q26: 18992.75 | R26: 0 | S26: 15688.23 | T26: 20326 | U26: R5ST0664 | V26: Корпус сварной навесной серии ST с М/П Размер: 600 x 600 x 400 мм (В х Ш х Г) | W26: 9708.69 | X26: 4 | Y26: 8019.49 | Z26: 10390 | AA26: 600 | AB26: 600 | AC26: 400 | AD26: SE1023 | AE26: =Y26*$AE$1 -> 7618.5155 | AF26: =AE26/0.75 -> 10158.021 | AG26: =ROUND(AF26,0) -> 10158 | AH26: =X25*AE26 -> 30474.062 | AI26: 1 | AJ26: =2*(AA26*AB26+AB26*AC26+AA26*AC26)/1000000 -> 1.68 | AK26: =AE26/AJ26 -> 4534.8307
B27: MES 70.50.21 | C27: 7262 | D27: =C27*0.75 -> 5446.5 | K27: =J27*$N$1 -> 0 | O27: R5CE0752 | P27: Навесной шкаф CE, 700 x 500 x 200мм, IP65 | Q27: 11934.99 | R27: 0 | S27: 9858.44 | T27: 12773 | U27: R5ST0752 | V27: Корпус сварной навесной серии ST с М/П Размер: 700 x 500 x 200 мм (В х Ш х Г) | W27: 6223.7 | X27: 26 | Y27: 5140.85 | Z27: 6661 | AA27: 700 | AB27: 500 | AC27: 200 | AD27: SE1024 | AE27: =Y27*$AE$1 -> 4883.8075 | AF27: =AE27/0.75 -> 6511.7433 | AG27: =ROUND(AF27,0) -> 6512 | AH27: =X26*AE27 -> 19535.23 | AI27: 1 | AJ27: =2*(AA27*AB27+AB27*AC27+AA27*AC27)/1000000 -> 1.18 | AK27: =AE27/AJ27 -> 4138.8199
B28: MES 70.50.25 | C28: 7744 | D28: =C28*0.75 -> 5808 | E28: U7521705025 | F28: Корпус UC2 70.50.25 IP66 USOLA | G28: 6454 | H28: 1057500 | I28: AE Шкаф RAL7035 с МП, 500x700x250mm | J28: 133.51 | K28: =J28*$N$1 -> 9688.8207 | L28: 1 | M28: 8,067.46 | N28: 11,105.00 | O28: R5CE0759 | P28: Навесной шкаф CE, 700 x 500 x 250мм, IP65 | Q28: 12160.19 | R28: 0 | S28: 10044.46 | T28: 13014 | U28: R5ST0759 | V28: Корпус сварной навесной серии ST с М/П Размер: 700 x 500 x 250 мм (В х Ш х Г) | W28: 6579.09 | X28: 24 | Y28: 5434.41 | Z28: 7041 | AA28: 700 | AB28: 500 | AC28: 250 | AD28: SE1025 | AE28: =Y28*$AE$1 -> 5162.6895 | AF28: =AE28/0.75 -> 6883.586 | AG28: =ROUND(AF28,0) -> 6884 | AH28: =X27*AE28 -> 134229.93 | AI28: 1 | AJ28: =2*(AA28*AB28+AB28*AC28+AA28*AC28)/1000000 -> 1.3 | AK28: =AE28/AJ28 -> 3971.2996
B29: MES 80.60.21 | C29: 8893 | D29: =C29*0.75 -> 6669.75 | K29: =J29*$N$1 -> 0 | O29: R5CE0862 | P29: Навесной шкаф CE, 800 х 600 х 200мм, IP65 | Q29: 12784.27 | R29: 0 | S29: 10559.96 | T29: 13682 | U29: R5ST0862 | V29: Корпус сварной навесной серии ST с М/П Размер: 800 x 600 x 200 мм (В х Ш х Г) | W29: 7830.34 | X29: 10 | Y29: 6467.96 | Z29: 8380 | AA29: 800 | AB29: 600 | AC29: 200 | AD29: SE1026 | AE29: =Y29*$AE$1 -> 6144.562 | AF29: =AE29/0.75 -> 8192.7493 | AG29: =ROUND(AF29,0) -> 8193 | AH29: =X28*AE29 -> 147469.49 | AI29: 1 | AJ29: =2*(AA29*AB29+AB29*AC29+AA29*AC29)/1000000 -> 1.52 | AK29: =AE29/AJ29 -> 4042.475
D30: =C30*0.75 -> 0 | K30: =J30*$N$1 -> 0 | O30: R5CE0882 | P30: Навесной шкаф CE, 800 х 800 х 200мм, IP65 | Q30: 16214.81 | R30: 0 | S30: 13393.63 | T30: 17353 | U30: R5ST0882 | V30: Корпус сварной навесной серии ST с М/П Размер: 800 x 800 x 200 мм (В х Ш х Г) | W30: 10724.15 | X30: 0 | Y30: 8858.27 | Z30: 11477 | AA30: 800 | AB30: 800 | AC30: 200 | AD30: SE1027 | AE30: =Y30*$AE$1 -> 8415.3565 | AF30: =AE30/0.75 -> 11220.475 | AG30: =ROUND(AF30,0) -> 11220 | AH30: =X29*AE30 -> 84153.565 | AI30: 1 | AJ30: =2*(AA30*AB30+AB30*AC30+AA30*AC30)/1000000 -> 1.92 | AK30: =AE30/AJ30 -> 4382.9982
B31: MES 80.60.25 | C31: 9453 | D31: =C31*0.75 -> 7089.75 | E31: U7521806025 | F31: Корпус UC2 80.60.25 IP66 USOLA | G31: 7877 | H31: 1058500 | I31: AE Шкаф RAL7035, с МП, 600x800x250mm | J31: 160.89 | K31: =J31*$N$1 -> 11675.787 | L31: 4 | M31: 10,821.92 | N31: 13,383.00 | O31: R5CE0869 | P31: Навесной шкаф CE, 800 x 600 x 250мм, IP65 | Q31: 13479.89 | R31: 0 | S31: 11134.55 | T31: 14427 | U31: R5ST0869 | V31: Корпус сварной навесной серии ST с М/П Размер: 800 x 600 x 250 мм (В х Ш х Г) | W31: 8026.13 | X31: 21 | Y31: 6629.68 | Z31: 8590 | AA31: 800 | AB31: 600 | AC31: 250 | AD31: SE1028 | AE31: =Y31*$AE$1 -> 6298.196 | AF31: =AE31/0.75 -> 8397.5947 | AG31: =ROUND(AF31,0) -> 8398 | AH31: =X30*AE31 -> 0 | AI31: 1 | AJ31: =2*(AA31*AB31+AB31*AC31+AA31*AC31)/1000000 -> 1.66 | AK31: =AE31/AJ31 -> 3794.094
B32: MES 80.60.30 | C32: 10058 | D32: =C32*0.75 -> 7543.5 | E32: U7521806030 | F32: Корпус UC2 80.60.30 IP66 USOLA | G32: 8382 | K32: =J32*$N$1 -> 0 | O32: R5CE0863 | P32: Навесной шкаф CE, 800 x 600 x 300мм, IP65 | Q32: 13455.55 | R32: 0 | S32: 11114.44 | T32: 14400 | U32: R5ST0863 | V32: Корпус сварной навесной серии ST с М/П Размер: 800 x 600 x 300 мм (В х Ш х Г) | W32: 8354.14 | X32: 39 | Y32: 6900.62 | Z32: 8941 | AA32: 800 | AB32: 600 | AC32: 300 | AD32: SE1029 | AE32: =Y32*$AE$1 -> 6555.589 | AF32: =AE32/0.75 -> 8740.7853 | AG32: =ROUND(AF32,0) -> 8741 | AH32: =X31*AE32 -> 137667.37 | AI32: 1 | AJ32: =2*(AA32*AB32+AB32*AC32+AA32*AC32)/1000000 -> 1.8 | AK32: =AE32/AJ32 -> 3641.9939
B33: MES 80.80.30 | C33: 12212 | D33: =C33*0.75 -> 9159 | K33: =J33*$N$1 -> 0 | O33: R5CE0883 | P33: Навесной шкаф CE, 800 x 800 x 300мм, IP65 | Q33: 17834.95 | R33: 0 | S33: 14731.88 | T33: 19087 | U33: R5ST0883 | V33: Корпус сварной навесной серии ST с М/П Размер: 800 x 800 x 300 мм (В х Ш х Г) | W33: 11973.1 | X33: 0 | Y33: 9889.92 | Z33: 12814 | AA33: 800 | AB33: 800 | AC33: 300 | AD33: SE1030 | AE33: =Y33*$AE$1 -> 9395.424 | AF33: =AE33/0.75 -> 12527.232 | AG33: =ROUND(AF33,0) -> 12527 | AH33: =X32*AE33 -> 366421.54 | AI33: 1 | AJ33: =2*(AA33*AB33+AB33*AC33+AA33*AC33)/1000000 -> 2.24 | AK33: =AE33/AJ33 -> 4194.3857
B34: MES 80.60.40 | C34: 13829 | D34: =C34*0.75 -> 10371.75 | K34: =J34*$N$1 -> 0 | O34: R5CE0864 | P34: Навесной шкаф CE, 800 x 600 x 400мм, IP65 | Q34: 22686.77 | R34: 0 | S34: 18739.54 | T34: 24280 | U34: R5ST0864 | V34: Корпус сварной навесной серии ST с М/П Размер: 800 x 600 x 400 мм (В х Ш х Г) | W34: 12076.86 | X34: 5 | Y34: 9975.63 | Z34: 12925 | AA34: 800 | AB34: 600 | AC34: 400 | AD34: SE1031 | AE34: =Y34*$AE$1 -> 9476.8485 | AF34: =AE34/0.75 -> 12635.798 | AG34: =ROUND(AF34,0) -> 12636 | AH34: =X33*AE34 -> 0 | AI34: 1 | AJ34: =2*(AA34*AB34+AB34*AC34+AA34*AC34)/1000000 -> 2.08 | AK34: =AE34/AJ34 -> 4556.1772
D35: =C35*0.75 -> 0 | E35: U7521808040 | F35: Корпус UC2 80.80.40 IP66 USOLA | G35: 10177 | K35: =J35*$N$1 -> 0 | O35: R5CE0884 | P35: Навесной шкаф CE, 800 x 800 x 400мм, IP65 | Q35: 25314.84 | R35: 0 | S35: 20910.36 | T35: 27093 | U35: R5ST0884 | V35: Корпус сварной навесной серии ST с М/П Размер: 800 x 800 x 400 мм (В х Ш х Г) | W35: 13753.09 | X35: 8 | Y35: 11360.21 | Z35: 14719 | AA35: 800 | AB35: 800 | AC35: 400 | AD35: SE1032 | AE35: =Y35*$AE$1 -> 10792.199 | AF35: =AE35/0.75 -> 14389.599 | AG35: =ROUND(AF35,0) -> 14390 | AH35: =X34*AE35 -> 53960.997 | AI35: 1 | AJ35: =2*(AA35*AB35+AB35*AC35+AA35*AC35)/1000000 -> 2.56 | AK35: =AE35/AJ35 -> 4215.7029
B36: MES 100.60.25 | C36: 10991 | D36: =C36*0.75 -> 8243.25 | E36: U7521106025 | F36: Корпус UC2 100.60.25 IP66 USOLA | G36: 9159 | H36: 1090500 | I36: AE Шкаф RAL7035, с МП, 600x1000x250mm | J36: 183.72 | K36: =J36*$N$1 -> 13332.56 | L36: 3 | M36: 12,357.09 | N36: 15,282.00 | O36: R5CE1069 | P36: Навесной шкаф CE, 1000 x 600 x 250мм, IP65 | Q36: 16232.42 | R36: 0 | S36: 13408.17 | T36: 17372 | U36: R5ST1069 | V36: Корпус сварной навесной серии ST с М/П Размер: 1000 x 600 x250 мм (В х Ш х Г) | W36: 10927.84 | X36: 1 | Y36: 9026.53 | Z36: 11695 | AA36: 1000 | AB36: 600 | AC36: 250 | AD36: SE1033 | AE36: =Y36*$AE$1 -> 8575.2035 | AF36: =AE36/0.75 -> 11433.605 | AG36: =ROUND(AF36,0) -> 11434 | AH36: =X35*AE36 -> 68601.628 | AI36: 1 | AJ36: =2*(AA36*AB36+AB36*AC36+AA36*AC36)/1000000 -> 2 | AK36: =AE36/AJ36 -> 4287.6017
B37: MES 100.60.30 | C37: 11752 | D37: =C37*0.75 -> 8814 | E37: U7521106030 | F37: Корпус UC2 100.60.30 IP66 USOLA | G37: 9794 | K37: =J37*$N$1 -> 0 | O37: R5CE1063 | P37: Навесной шкаф CE, 1000 x 600 x 300мм, IP65 | Q37: 17114.35 | R37: 0 | S37: 14136.66 | T37: 18316 | U37: R5ST1063 | V37: Корпус сварной навесной серии ST с М/П Размер: 1000 x 600 x300 мм (В х Ш х Г) | W37: 11952.9 | X37: 82 | Y37: 9873.24 | Z37: 12792 | AA37: 1000 | AB37: 600 | AC37: 300 | AD37: SE1034 | AE37: =Y37*$AE$1 -> 9379.578 | AF37: =AE37/0.75 -> 12506.104 | AG37: =ROUND(AF37,0) -> 12506 | AH37: =X36*AE37 -> 9379.578 | AI37: 1 | AJ37: =2*(AA37*AB37+AB37*AC37+AA37*AC37)/1000000 -> 2.16 | AK37: =AE37/AJ37 -> 4342.3972
B38: MES 100.80.30 | C38: 13916 | D38: =C38*0.75 -> 10437 | E38: U7521108030 | F38: Корпус UC2 100.80.30 IP66 USOLA | G38: 11597 | H38: 1180500 | I38: AE Шкаф RAL7035, с МП, 800x1000x300mm | J38: 210.95 | K38: =J38*$N$1 -> 15308.641 | L38: 1 | M38: 14,188.72 | N38: 17,547.00 | O38: R5CE1083 | P38: Навесной шкаф CE, 1000 x 800 x 300мм, IP65 | Q38: 20606.88 | R38: 1 | S38: 17021.52 | T38: 22054 | U38: R5ST1083 | V38: Корпус сварной навесной серии ST с М/П Размер: 1000 x 800 x300 мм (В х Ш х Г) | W38: 11866.58 | X38: 32 | Y38: 9801.93 | Z38: 12700 | AA38: 1000 | AB38: 800 | AC38: 300 | AD38: SE1035 | AE38: =Y38*$AE$1 -> 9311.8335 | AF38: =AE38/0.75 -> 12415.778 | AG38: =ROUND(AF38,0) -> 12416 | AH38: =X37*AE38 -> 763570.35 | AI38: 1 | AJ38: =2*(AA38*AB38+AB38*AC38+AA38*AC38)/1000000 -> 2.68 | AK38: =AE38/AJ38 -> 3474.5647
B39: MES 100.60.40 | C39: 16713 | D39: =C39*0.75 -> 12534.75 | E39: U7521106040 | F39: Корпус UC2 100.60.40 IP66 USOLA | G39: 13928 | K39: =J39*$N$1 -> 0 | O39: R5CE1064 | P39: Навесной шкаф CE, 1000 x 600 x 400мм, IP65 | Q39: 23523.85 | R39: 0 | S39: 19430.98 | T39: 25176 | U39: R5ST1064 | V39: Корпус сварной навесной серии ST с М/П Размер: 1000 x 600 x400 мм (В х Ш х Г) | W39: 14347.09 | X39: 7 | Y39: 11850.87 | Z39: 15355 | AA39: 1000 | AB39: 600 | AC39: 400 | AD39: SE1036 | AE39: =Y39*$AE$1 -> 11258.327 | AF39: =AE39/0.75 -> 15011.102 | AG39: =ROUND(AF39,0) -> 15011 | AH39: =X38*AE39 -> 360266.45 | AI39: 1 | AJ39: =2*(AA39*AB39+AB39*AC39+AA39*AC39)/1000000 -> 2.48 | AK39: =AE39/AJ39 -> 4539.6478
D40: =C40*0.75 -> 0 | K40: =J40*$N$1 -> 0 | O40: R5CE1084 | P40: Навесной шкаф CE, 1000 x 800 x 400мм, IP65 | Q40: 24928.39 | R40: 0 | S40: 20591.14 | T40: 26679 | U40: R5ST1084 | V40: Корпус сварной навесной серии ST с М/П Размер: 1000 x 800 x400 мм (В х Ш х Г) | W40: 15038 | X40: 4 | Y40: 12421.57 | Z40: 16094 | AA40: 1000 | AB40: 800 | AC40: 400 | AD40: SE1037 | AE40: =Y40*$AE$1 -> 11800.491 | AF40: =AE40/0.75 -> 15733.989 | AG40: =ROUND(AF40,0) -> 15734 | AH40: =X39*AE40 -> 82603.44 | AI40: 1 | AJ40: =2*(AA40*AB40+AB40*AC40+AA40*AC40)/1000000 -> 3.04 | AK40: =AE40/AJ40 -> 3881.7406
B41: MES 120.60.21 | C41: 12680 | D41: =C41*0.75 -> 9510 | E41: U7521126025 | F41: Корпус UC2 120.60.25 IP66 USOLA | G41: 11534 | K41: =J41*$N$1 -> 0 | U41: R5ST1262 | V41: Корпус сварной навесной серии ST с М/П Размер: 1200 x 600 x200 мм (В х Ш х Г) | W41: 11629.87 | X41: 0 | Y41: 9606.42 | Z41: 12447 | AA41: 1200 | AB41: 600 | AC41: 200 | AD41: SE1038 | AE41: =Y41*$AE$1 -> 9126.099 | AF41: =AE41/0.75 -> 12168.132 | AG41: =ROUND(AF41,0) -> 12168 | AH41: =X40*AE41 -> 36504.396 | AI41: 1 | AJ41: =2*(AA41*AB41+AB41*AC41+AA41*AC41)/1000000 -> 2.16 | AK41: =AE41/AJ41 -> 4225.0458
B42: MES 120.60.30 | C42: 14964 | D42: =C42*0.75 -> 11223 | E42: U7521126030 | F42: Корпус UC2 120.60.30 IP66 USOLA | G42: 12471 | H42: 1260500 | I42: AE Шкаф RAL7035 с МП, 600x1200x300mm | J42: 234.5 | K42: =J42*$N$1 -> 17017.665 | L42: 1 | M42: 15,772.47 | N42: 19,506.00 | O42: R5CE1263 | P42: Навесной шкаф CE, 1200 x 600 x 300мм, IP65 | Q42: 20933.23 | R42: 0 | S42: 17291.09 | T42: 22403 | U42: R5ST1263 | V42: Корпус сварной навесной серии ST с М/П Размер: 1200 x 600 x300 мм (В х Ш х Г) | W42: 13581.47 | X42: 19 | Y42: 11218.45 | Z42: 14535 | AA42: 1200 | AB42: 600 | AC42: 300 | AD42: SE1039 | AE42: =Y42*$AE$1 -> 10657.528 | AF42: =AE42/0.75 -> 14210.037 | AG42: =ROUND(AF42,0) -> 14210 | AH42: =X41*AE42 -> 0 | AI42: 1 | AJ42: =2*(AA42*AB42+AB42*AC42+AA42*AC42)/1000000 -> 2.52 | AK42: =AE42/AJ42 -> 4229.1776
B43: MES 120.80.30 | C43: 17177 | D43: =C43*0.75 -> 12882.75 | E43: U7521128030 | F43: Корпус UC2 120.80.30 IP66 USOLA | G43: 14315 | H43: 1280500 | I43: AE Шкаф RAL7035, с МП, 800x1200x300mm | J43: 268.56 | K43: =J43*$N$1 -> 19489.399 | L43: 0 | M43: 18,064.16 | N43: 22,340.00 | O43: R5CE1283 | P43: Навесной шкаф CE, 1200 x 800 x 300мм, IP65 | Q43: 24027.24 | R43: 0 | S43: 19846.79 | T43: 25715 | U43: R5ST1283 | V43: Корпус сварной навесной серии ST с М/П Размер: 1200 x 800 x300 мм (В х Ш х Г) | W43: 15753.63 | X43: 37 | Y43: 13012.69 | Z43: 16860 | AA43: 1200 | AB43: 800 | AC43: 300 | AD43: SE1040 | AE43: =Y43*$AE$1 -> 12362.056 | AF43: =AE43/0.75 -> 16482.741 | AG43: =ROUND(AF43,0) -> 16483 | AH43: =X42*AE43 -> 234879.05 | AI43: 1 | AJ43: =2*(AA43*AB43+AB43*AC43+AA43*AC43)/1000000 -> 3.12 | AK43: =AE43/AJ43 -> 3962.1973
B44: MES 120.60.40 | C44: 18774 | D44: =C44*0.75 -> 14080.5 | E44: U7521126040 | F44: Корпус UC2 120.60.40 IP66 USOLA | G44: 15647 | K44: =J44*$N$1 -> 0 | U44: R5ST1264 | V44: Корпус сварной навесной серии ST с М/П Размер: 1200 x 600 x400 мм (В х Ш х Г) | W44: 16982.67 | X44: 0 | Y44: 14027.89 | Z44: 18175 | AA44: 1200 | AB44: 600 | AC44: 400 | AD44: SE1041 | AE44: =Y44*$AE$1 -> 13326.495 | AF44: =AE44/0.75 -> 17768.661 | AG44: =ROUND(AF44,0) -> 17769 | AI44: 1 | AJ44: =2*(AA44*AB44+AB44*AC44+AA44*AC44)/1000000 -> 2.88 | AK44: =AE44/AJ44 -> 4627.2554
B45: MES 120.80.40 | C45: 23356 | D45: =C45*0.75 -> 17517 | E45: U7521128040 | F45: Корпус UC2 120.80.40 IP66 USOLA | G45: 19464 | K45: =J45*$N$1 -> 0 | U45: R5ST1284 | V45: Корпус сварной навесной серии ST с М/П Размер: 1200 x 800 x400 мм (В х Ш х Г) | W45: 21354.28 | X45: 4 | Y45: 17638.89 | Z45: 22854 | AA45: 1200 | AB45: 800 | AC45: 400 | AD45: SE1042 | AE45: =Y45*$AE$1 -> 16756.945 | AF45: =AE45/0.75 -> 22342.594 | AG45: =ROUND(AF45,0) -> 22343 | AH45: =X44*AE45 -> 0 | AI45: 1 | AJ45: =2*(AA45*AB45+AB45*AC45+AA45*AC45)/1000000 -> 3.52 | AK45: =AE45/AJ45 -> 4760.4959 | AL45: 10547.243
B46: MES 140.60.40 | C46: 22603 | D46: =C46*0.75 -> 16952.25 | E46: U7521146040 | F46: Корпус UC2 140.60.40 IP66 USOLA | G46: 18837 | K46: =J46*$N$1 -> 0 | O46: R5CE1463 | P46: Навесной шкаф CE, 1400 x 600 x 300мм, IP65 | Q46: 22816.83 | R46: 0 | S46: 18846.97 | T46: 24419 | U46: R5ST1463 | V46: Корпус сварной навесной серии ST с М/П Размер: 1400 x 600 x300 мм (В х Ш х Г) | W46: 18947.97 | X46: 0 | Y46: 15651.25 | Z46: 20279 | AA46: 1400 | AB46: 600 | AC46: 300 | AD46: SE1043 | AE46: =Y46*$AE$1 -> 14868.688 | AF46: =AE46/0.75 -> 19824.917 | AG46: =ROUND(AF46,0) -> 19825 | AH46: =X45*AE46 -> 59474.75 | AI46: 1 | AJ46: =2*(AA46*AB46+AB46*AC46+AA46*AC46)/1000000 -> 2.88 | AK46: =AE46/AJ46 -> 5162.7387
B47: MES 140.80.40 | C47: 27721 | D47: =C47*0.75 -> 20790.75 | E47: U7521148040 | F47: Корпус UC2 140.80.40 IP66 USOLA | G47: 23102 | K47: =J47*$N$1 -> 0 | O47: R5CE1483 | P47: Навесной шкаф CE, 1400 x 800 x 300мм, IP65 | Q47: 28782.64 | R47: 0 | S47: 23774.81 | T47: 30804 | U47: R5ST1483 | V47: Корпус сварной навесной серии ST с М/П Размер: 1400 x 800 x300 мм (В х Ш х Г) | W47: 21399.26 | X47: 6 | Y47: 17676.05 | Z47: 22902 | AA47: 1400 | AB47: 800 | AC47: 300 | AD47: SE1044 | AE47: =Y47*$AE$1 -> 16792.247 | AF47: =AE47/0.75 -> 22389.663 | AG47: =ROUND(AF47,0) -> 22390 | AH47: =X46*AE47 -> 0 | AI47: 1 | AJ47: =2*(AA47*AB47+AB47*AC47+AA47*AC47)/1000000 -> 3.56 | AK47: =AE47/AJ47 -> 4716.9235
H48: 1032500 | I48: AE Шкаф, RAL7035, с МП, 200x300x120mm | J48: 41.22 | K48: =J48*$N$1 -> 2991.3354
H49: 1033500 | I49: AE Шкаф RAL7035, с МП, 300x300x210mm | J49: 60.98 | K49: =J49*$N$1 -> 4425.3186 | AH49: =SUM(AH5:AH53) -> 4411438.3
B50: MES 100.60.21 | C50: 10582 | H50: 1037500 | I50: AE Шкаф RAL7035 с МП, 400x800x300mm | J50: 174.87 | K50: =J50*$N$1 -> 12690.316
H51: 1055500 | I51: AE Шкаф RAL7035 с МП, 800x600x300mm | J51: 211.5 | K51: =J51*$N$1 -> 15348.555
H52: 1060500 | I52: AE Шкаф RAL7035, с МП, 600x600x210mm | J52: 105.72 | K52: =J52*$N$1 -> 7672.1004
B53: MES 160.60.40 | C53: 25948 | E53: U7521166040 | F53: Корпус UC2 160.60.40 IP66 USOLA | G53: 21625 | H53: 1073500 | I53: AE Шкаф RAL7035, с МП, 760x760x300mm | J53: 186.29 | K53: =J53*$N$1 -> 13519.065
H54: 1076500 | I54: AE Шкаф RAL7035, с МП, 600x760x210mm | J54: 134.58 | K54: =J54*$N$1 -> 9766.4706
F55: Корпуса компактные UC2 IP66 | H55: 1077500 | I55: AE Шкаф RAL7035 с МП, 760x760x210mm | J55: 174.9 | K55: =J55*$N$1 -> 12692.493
E56: U7521202015 | F56: Корпус UC2 20.20.15 IP66 USOLA | G56: 2060 | H56: 1100500 | I56: AE Шкаф RAL7035, с МП, 1000x760x210mm | J56: 286.52 | K56: =J56*$N$1 -> 20792.756
E57: U7521202020 | F57: Корпус UC2 20.20.20 IP66 USOLA | G57: 2158 | H57: 1110500 | I57: AE Шкаф RAL7035, с МП, 1000x1000x300mm | J57: 308.45 | K57: =J57*$N$1 -> 22384.216
E58: U7521203015 | F58: Корпус UC2 20.30.15 IP66 USOLA | G58: 2191 | H58: 1114500 | I58: AE Шкаф RAL7035, с МП, 1000x1400x300mm | J58: 454.19 | K58: =J58*$N$1 -> 32960.568
E59: U7521203020 | F59: Корпус UC2 20.30.20 IP66 USOLA | G59: 2202 | H59: 1130500 | I59: AE Шкаф RAL7035 с МП, 1000x760x300mm | J59: 282.96 | K59: =J59*$N$1 -> 20534.407
E60: U7521253015 | F60: Корпус UC2 25.30.15 IP66 USOLA | G60: 2269 | H60: 1213500 | I60: AE Шкаф RAL7035, с МП, 1000x1200x300mm | J60: 377.19 | K60: =J60*$N$1 -> 27372.678
E61: U7521253020 | F61: Корпус UC2 25.30.20 IP66 USOLA | G61: 2315 | H61: 1338500 | I61: AE Шкаф RAL7035, с МП, 380x600x350mm | J61: 137.93 | K61: =J61*$N$1 -> 10009.58
E62: U7521253025 | F62: Корпус UC2 25.30.25 IP66 USOLA | G62: 2379 | H62: 1339500 | I62: AE Шкаф RAL7035, с МП, 600x380x350mm | J62: 143.82 | K62: =J62*$N$1 -> 10437.017
E63: U7521253515 | F63: Корпус UC2 25.35.15 IP66 USOLA | G63: 2367 | H63: 1376500 | I63: AE Шкаф RAL7035, с МП, 600x760x350mm | J63: 190.78 | K63: =J63*$N$1 -> 13844.905
E64: U7521253520 | F64: Корпус UC2 25.35.20 IP66 USOLA | G64: 2423
E65: U7521253525 | F65: Корпус UC2 25.35.25 IP66 USOLA | G65: 2477
E66: U7521254015 | F66: Корпус UC2 25.40.15 IP66 USOLA | G66: 2465
E67: U7521254020 | F67: Корпус UC2 25.40.20 IP66 USOLA | G67: 2536
E68: U7521254025 | F68: Корпус UC2 25.40.25 IP66 USOLA | G68: 2588
E70: U7521302020 | F70: Корпус UC2 30.20.20 IP66 USOLA | G70: 2746
E71: U7521302025 | F71: Корпус UC2 30.20.25 IP66 USOLA | G71: 2841
E73: U7521303020 | F73: Корпус UC2 30.30.20 IP66 USOLA | G73: 2977
E74: U7521303025 | F74: Корпус UC2 30.30.25 IP66 USOLA | G74: 3029
E75: U7521303515 | F75: Корпус UC2 30.35.15 IP66 USOLA | G75: 3041
E76: U7521303520 | F76: Корпус UC2 30.35.20 IP66 USOLA | G76: 3078
E77: U7521303525 | F77: Корпус UC2 30.35.25 IP66 USOLA | G77: 3151
... E141: U7521806040 | F141: Корпус UC2 80.60.40 IP66 USOLA | G141: 11525

Sheet SE1100(черный лист)
H1: 420
G2: Прайсовая цена SE1000 | H2: Прайсовая цена SE1100
B3: SE1101.0231.1035 | C3: 300 | D3: 200 | E3: 150 | F3: IP67 | G3: 2944 | H3: =G3+$H$1 -> 3364
B4: SE1102.0391.1035 | C4: 300 | D4: 250 | E4: 150 | F4: IP67 | G4: 3034 | H4: =G4+$H$1 -> 3454
B5: SE1103.0331.1036 | C5: 300 | D5: 300 | E5: 150 | F5: IP67 | G5: 3223 | H5: =G5+$H$1 -> 3643
B6: SE1104.0341.1030 | C6: 300 | D6: 400 | E6: 150 | F6: IP67 | G6: 3330 | H6: =G6+$H$1 -> 3750
B7: SE1105.0342.1031 | C7: 300 | D7: 400 | E7: 200 | F7: IP67 | G7: 3261 | H7: =G7+$H$1 -> 3681
B8: SE1106.0431.1034 | C8: 400 | D8: 300 | E8: 150 | F8: IP67 | G8: 3438 | H8: =G8+$H$1 -> 3858
B9: SE1107.0432.1034 | C9: 400 | D9: 300 | E9: 200 | F9: IP67 | G9: 3834 | H9: =G9+$H$1 -> 4254
B10: SE1108.0442.1380 | C10: 400 | D10: 400 | E10: 200 | F10: IP67 | G10: 3884 | H10: =G10+$H$1 -> 4304
B11: SE1109.0462.1039 | C11: 400 | D11: 600 | E11: 200 | F11: IP67 | G11: 5601 | H11: =G11+$H$1 -> 6021
B12: SE1110.0531.1045 | C12: 500 | D12: 300 | E12: 150 | F12: IP67 | G12: 4400 | H12: =G12+$H$1 -> 4820
B13: SE1111.0532.1045 | C13: 500 | D13: 300 | E13: 200 | F13: IP67 | G13: 4783 | H13: =G13+$H$1 -> 5203
B14: SE1112.0542.1045 | C14: 500 | D14: 400 | E14: 200 | F14: IP67 | G14: 4861 | H14: =G14+$H$1 -> 5281
... B46: SE1144.1483.1280 | C46: 1400 | D46: 800 | E46: 300 | F46: IP66 | G46: 22390 | H46: =G46+$H$1 -> 22810

Sheet SF1000 и SF1100
H1: 2500
F2: площадь | G2: цена на SE1000 | H2: Прайсовая цена на SF1000 | I2: Цена со скидкой SF100
B3: 300 | C3: 200 | D3: 150 | E3: SF1001.0231.1035 | F3: 0.27 | G3: 2944 | H3: =F3*$H$1+G3 -> 3619 | I3: =H3*0.75 -> 2714.25 | J3: 2208.1895
B4: 300 | C4: 250 | D4: 150 | E4: SF1002.0391.1035 | F4: 0.315 | G4: 3034 | H4: =F4*$H$1+G4 -> 3821.5 | I4: =H4*0.75 -> 2866.125 | J4: 2275.231
B5: 300 | C5: 300 | D5: 150 | E5: SF1003.0331.1036 | F5: 0.36 | G5: 3223 | H5: =F5*$H$1+G5 -> 4123 | I5: =H5*0.75 -> 3092.25 | J5: 2416.9995
B6: 300 | C6: 400 | D6: 150 | E6: SF1004.0341.1030 | F6: 0.45 | G6: 3330 | H6: =F6*$H$1+G6 -> 4455 | I6: =H6*0.75 -> 3341.25 | J6: 2497.607
B7: 300 | C7: 400 | D7: 200 | E7: SF1005.0342.1031 | F7: 0.52 | G7: 3261 | H7: =F7*$H$1+G7 -> 4561 | I7: =H7*0.75 -> 3420.75 | J7: 2445.566
B8: 400 | C8: 300 | D8: 150 | E8: SF1006.0431.1034 | F8: 0.45 | G8: 3438 | H8: =F8*$H$1+G8 -> 4563 | I8: =H8*0.75 -> 3422.25 | J8: 2578.186
B9: 400 | C9: 300 | D9: 200 | E9: SF1007.0432.1034 | F9: 0.52 | G9: 3834 | H9: =F9*$H$1+G9 -> 5134 | I9: =H9*0.75 -> 3850.5 | J9: 2875.859
B10: 400 | C10: 400 | D10: 200 | E10: SF1008.0442.1380 | F10: 0.64 | G10: 3884 | H10: =F10*$H$1+G10 -> 5484 | I10: =H10*0.75 -> 4113 | J10: 2913.2225
B11: 400 | C11: 600 | D11: 200 | E11: SF1009.0462.1039 | F11: 0.88 | G11: 5601 | H11: =F11*$H$1+G11 -> 7801 | I11: =H11*0.75 -> 5850.75 | J11: 4200.767
B12: 500 | C12: 300 | D12: 150 | E12: SF1010.0531.1045 | F12: 0.54 | G12: 4400 | H12: =F12*$H$1+G12 -> 5750 | I12: =H12*0.75 -> 4312.5 | J12: 3299.749
B13: 500 | C13: 300 | D13: 200 | E13: SF1011.0532.1045 | F13: 0.62 | G13: 4783 | H13: =F13*$H$1+G13 -> 6333 | I13: =H13*0.75 -> 4749.75 | J13: 3586.8865
B14: 500 | C14: 400 | D14: 200 | E14: SF1012.0542.1045 | F14: 0.76 | G14: 4861 | H14: =F14*$H$1+G14 -> 6761 | I14: =H14*0.75 -> 5070.75 | J14: 3645.7485
... B46: 1400 | C46: 800 | D46: 300 | E46: SF1044.1483.1280 | F46: 3.56 | G46: 22390 | H46: =F46*$H$1+G46 -> 31290 | I46: =H46*0.75 -> 23467.5 | J46: 16792.247
E47: SF1101.0231.1035 | F47: 0.27 | G47: 3364 | H47: =F47*$H$1+G47 -> 4039
E48: SF1102.0391.1035 | F48: 0.315 | G48: 3454 | H48: =F48*$H$1+G48 -> 4241.5
E49: SF1103.0331.1036 | F49: 0.36 | G49: 3643 | H49: =F49*$H$1+G49 -> 4543
E50: SF1104.0341.1030 | F50: 0.45 | G50: 3750 | H50: =F50*$H$1+G50 -> 4875
E51: SF1105.0342.1031 | F51: 0.52 | G51: 3681 | H51: =F51*$H$1+G51 -> 4981
E52: SF1106.0431.1034 | F52: 0.45 | G52: 3858 | H52: =F52*$H$1+G52 -> 4983
E53: SF1107.0432.1034 | F53: 0.52 | G53: 4254 | H53: =F53*$H$1+G53 -> 5554
E54: SF1108.0442.1380 | F54: 0.64 | G54: 4304 | H54: =F54*$H$1+G54 -> 5904
E55: SF1109.0462.1039 | F55: 0.88 | G55: 6021 | H55: =F55*$H$1+G55 -> 8221
E56: SF1110.0531.1045 | F56: 0.54 | G56: 4820 | H56: =F56*$H$1+G56 -> 6170
E57: SF1111.0532.1045 | F57: 0.62 | G57: 5203 | H57: =F57*$H$1+G57 -> 6753
E58: SF1112.0542.1045 | F58: 0.76 | G58: 5281 | H58: =F58*$H$1+G58 -> 7181
... E90: SF1144.1483.1280 | F90: 3.56 | G90: 22810 | H90: =F90*$H$1+G90 -> 31710

Sheet SE2000 (нерж304)
J1: 1.3 | K1: 0.95 | N1: Провенто
B2: IPEX | H2: Площадь поверхности | I2: Себестоимость | J2: Наша цена с наценкой от себестоимости | K2: Наша цена от провенто | L2: Прайсовая цена | N2: артикул | O2: прайсовая цена | P2: цена провенто со скидкой 25% | Q2: Стоимость м2 | R2: вычисленная стоимостьм2 | S2: Вычисленная цена сос скидкой | T2: УЗОЛА | V2: Rittal | Y2: 72.57 | Z2: Цена ЭТМ со Скидкой | AA2: Цена ЭТМ розница | AD2: DKS | AF2: Цена ЭТМ со Скидкой | AG2: Цена ЭТМ розница
B3: 300 | C3: 200 | D3: 150 | E3: IP67 | F3: 1 | G3: SЕ2001 | H3: =2*(B3*C3+C3*D3+B3*D3)/1000000 -> 0.27 | I3: 5707.0047 | J3: =I3*$J$1 -> 7419.1061 | K3: =S3*$K$1 -> 8269.275 | L3: =K3/0.75 -> 11025.7 | M3: =ROUND(L3,0) -> 11026 | N3: SES 30.20.15 | O3: 11606 | P3: =O3*0.75 -> 8704.5 | Q3: =P3/H3 -> 32238.889 | R3: 32238.889 | S3: =R3*H3 -> 8704.5 | T3: Корпус UC2 30.20.15 из нержавеющей стали IP66 USOLA | U3: 8690 | V3: 1002600 | W3: AE Шкаф, нерж.сталь с МП 200x300x155mm | X3: 172.1 | Y3: =X3*$Y$2 -> 12489.297 | Z3: 11,575.58 | AA3: 14,315.00
B4: 300 | C4: 250 | D4: 150 | E4: IP67 | F4: 1 | G4: SE2002 | H4: =2*(B4*C4+C4*D4+B4*D4)/1000000 -> 0.315 | J4: =I4*$J$1 -> 0 | K4: =S4*$K$1 -> 6594.9559 | L4: =K4/0.75 -> 8793.2746 | M4: =ROUND(L4,0) -> 8793 | P4: =O4*0.75 -> 0 | Q4: =P4/H4 -> 0 | R4: 22038.282 | S4: =R4*H4 -> 6942.0589 | Y4: =X4*$Y$2 -> 0 | AC4: R5CEB03911 | AD4: Навесной шкаф CE из нержавеющей стали (AISI 304), 300 x 250x 150мм, без фланца | AE4: 16614.36 | AF4: 11,630.22 | AG4: 15,069.00
B5: 300 | C5: 300 | D5: 150 | E5: IP67 | F5: 1 | G5: SE2003 | H5: =2*(B5*C5+C5*D5+B5*D5)/1000000 -> 0.36 | J5: =I5*$J$1 -> 0 | K5: =S5*$K$1 -> 6873.0188 | L5: =K5/0.75 -> 9164.025 | M5: =ROUND(L5,0) -> 9164 | P5: =O5*0.75 -> 0 | Q5: =P5/H5 -> 0 | R5: 20096.546 | S5: =R5*H5 -> 7234.7566 | Y5: =X5*$Y$2 -> 0 | AC5: R5CEB03311 | AD5: Навесной шкаф CE из нержавеющей стали (AISI 304), 300 x 300x 150мм, без фланца | AE5: 17311.45 | AF5: 12,118.19 | AG5: 15,701.00
B6: 300 | C6: 400 | D6: 150 | E6: IP67 | F6: 1 | G6: SE2004 | H6: =2*(B6*C6+C6*D6+B6*D6)/1000000 -> 0.45 | J6: =I6*$J$1 -> 0 | K6: =S6*$K$1 -> 9298.125 | L6: =K6/0.75 -> 12397.5 | M6: =ROUND(L6,0) -> 12398 | N6: SES 30.40.15 | O6: 13050 | P6: =O6*0.75 -> 9787.5 | Q6: =P6/H6 -> 21750 | R6: 21750 | S6: =R6*H6 -> 9787.5 | T6: Корпус UC2 30.40.15 из нержавеющей стали IP66 USOLA | U6: 9790 | V6: 1004600 | W6: AE Шкаф, нерж.сталь с МП 380x300x155mm | X6: 199.21 | Y6: =X6*$Y$2 -> 14456.67 | Z6: 13,398.64 | AA6: 16,570.00 | AC6: R5CEB03411 | AD6: Навесной шкаф CE из нержавеющей стали (AISI 304), 300 x 400x 150мм, без фланца | AE6: 18689.83 | AF6: 13,083.07 | AG6: 16,951.00
B7: 300 | C7: 400 | D7: 200 | E7: IP67 | F7: 1 | G7: SE2005 | H7: =2*(B7*C7+C7*D7+B7*D7)/1000000 -> 0.52 | J7: =I7*$J$1 -> 0 | K7: =S7*$K$1 -> 9544.8972 | L7: =K7/0.75 -> 12726.53 | M7: =ROUND(L7,0) -> 12727 | P7: =O7*0.75 -> 0 | Q7: =P7/H7 -> 0 | R7: 19321.654 | S7: =R7*H7 -> 10047.26 | V7: 1011600 | W7: AE Шкаф, нерж.сталь с МП 380x300x210mm | X7: 206.09 | Y7: =X7*$Y$2 -> 14955.951 | Z7: 12,987.07 | AA7: 17,037.00
B8: 400 | C8: 300 | D8: 150 | E8: IP67 | F8: 1 | G8: SE2006 | H8: =2*(B8*C8+C8*D8+B8*D8)/1000000 -> 0.45 | J8: =I8*$J$1 -> 0 | K8: =S8*$K$1 -> 9298.125 | L8: =K8/0.75 -> 12397.5 | M8: =ROUND(L8,0) -> 12398 | N8: SES 40.30.15 | O8: 13197 | P8: =O8*0.75 -> 9897.75 | Q8: =P8/H8 -> 21995 | R8: 21750 | S8: =R8*H8 -> 9787.5 | T8: Корпус UC2 40.30.15 из нержавеющей стали IP66 USOLA | U8: 9900 | Y8: =X8*$Y$2 -> #VALUE! | AC8: R5CEB04311 | AD8: Навесной шкаф CE из нержавеющей стали (AISI 304), 400 x 300x 150мм, без фланца | AE8: 18748.7 | AF8: 13,124.28 | AG8: 17,004.00
B9: 400 | C9: 300 | D9: 200 | E9: IP67 | F9: 1 | G9: SE2007 | H9: =2*(B9*C9+C9*D9+B9*D9)/1000000 -> 0.52 | J9: =I9*$J$1 -> 0 | K9: =S9*$K$1 -> 9544.8972 | L9: =K9/0.75 -> 12726.53 | M9: =ROUND(L9,0) -> 12727 | P9: =O9*0.75 -> 0 | Q9: =P9/H9 -> 0 | R9: 19321.654 | S9: =R9*H9 -> 10047.26 | T9: Корпус UC2 40.30.20 из нержавеющей стали IP66 USOLA | U9: 10230 | V9: 1005600 | W9: AE Шкаф, нерж.сталь с МП 300x380x210mm | X9: 212.2 | Y9: =X9*$Y$2 -> 15399.354 | Z9: 14,273.02 | AA9: 17,651.00 | AC9: R5CEB04321 | AD9: Навесной шкаф CE из нержавеющей стали (AISI 304), 400 x 300x 200мм, без фланца | AE9: 21738.47 | AF9: 15,217.15 | AG9: 19,716.00
B10: 400 | C10: 400 | D10: 200 | E10: IP67 | F10: 1 | G10: SE2008 | H10: =2*(B10*C10+C10*D10+B10*D10)/1000000 -> 0.64 | J10: =I10*$J$1 -> 0 | K10: =S10*$K$1 -> 11198.362 | L10: =K10/0.75 -> 14931.15 | M10: =ROUND(L10,0) -> 14931 | N10: SES 40.40.21 | O10: 15717 | P10: =O10*0.75 -> 11787.75 | Q10: =P10/H10 -> 18418.359 | R10: 18418.359 | S10: =R10*H10 -> 11787.75 | T10: Корпус UC2 40.40.20 из нержавеющей стали IP66 USOLA | U10: 11770 | V10: 1006600 | W10: AE Шкаф, нерж.сталь с МП 380x380x210mm | X10: 233.54 | Y10: =X10*$Y$2 -> 16947.998 | Z10: 15,708.18 | AA10: 19,426.00 | AC10: R5CEB04421 | AD10: Навесной шкаф CE из нержавеющей стали (AISI 304), 400 x 400x 200мм, без фланца | AE10: 24290.12 | AF10: 17,003.33 | AG10: 22,030.00
B11: 400 | C11: 600 | D11: 200 | E11: IP67 | F11: 1 | G11: SE2009 | H11: =2*(B11*C11+C11*D11+B11*D11)/1000000 -> 0.88 | J11: =I11*$J$1 -> 0 | K11: =S11*$K$1 -> 13994.212 | L11: =K11/0.75 -> 18658.95 | M11: =ROUND(L11,0) -> 18659 | P11: =O11*0.75 -> 0 | Q11: =P11/H11 -> 0 | R11: 16739.489 | S11: =R11*H11 -> 14730.75 | T11: Корпус UC2 40.60.20 из нержавеющей стали IP66 USOLA | U11: 12980 | V11: 1009600 | W11: AE Шкаф, нерж.сталь с МП600x380x210mm | X11: 291.74 | Y11: =X11*$Y$2 -> 21171.572 | Z11: 19,622.89 | AA11: 24,267.00 | AC11: R5CEB04621 | AD11: Навесной шкаф CE из нержавеющей стали (AISI 304), 400 x 600x 200мм, без фланца | AE11: 28028.69 | AF11: 19,620.37 | AG11: 25,421.00
B12: 500 | C12: 300 | D12: 150 | E12: IP67 | F12: 2 | G12: SE2010 | H12: =2*(B12*C12+C12*D12+B12*D12)/1000000 -> 0.54 | J12: =I12*$J$1 -> 0 | K12: =S12*$K$1 -> 9728.3574 | L12: =K12/0.75 -> 12971.143 | M12: =ROUND(L12,0) -> 12971 | P12: =O12*0.75 -> 0 | Q12: =P12/H12 -> 0 | R12: 18963.66 | S12: =R12*H12 -> 10240.376 | Y12: =X12*$Y$2 -> 0 | AC12: R5CEB05311 | AD12: Навесной шкаф CE из нержавеющей стали (AISI 304), 500 x 300x 150мм, без фланца | AE12: 20366.02 | AF12: 14,256.42 | AG12: 18,471.00
B13: 500 | C13: 300 | D13: 200 | E13: IP67 | F13: 2 | G13: SE2011 | H13: =2*(B13*C13+C13*D13+B13*D13)/1000000 -> 0.62 | J13: =I13*$J$1 -> 0 | K13: =S13*$K$1 -> 11115.632 | L13: =K13/0.75 -> 14820.843 | M13: =ROUND(L13,0) -> 14821 | P13: =O13*0.75 -> 0 | Q13: =P13/H13 -> 0 | R13: 18872.041 | S13: =R13*H13 -> 11700.666 | Y13: =X13*$Y$2 -> 0 | AC13: R5CEB05321 | AD13: Навесной шкаф CE из нержавеющей стали (AISI 304), 500 x 300x 200мм, без фланца | AE13: 24177.61 | AF13: 16,924.56 | AG13: 21,928.00
B14: 500 | C14: 400 | D14: 200 | E14: IP67 | F14: 2 | G14: SE2012 | H14: =2*(B14*C14+C14*D14+B14*D14)/1000000 -> 0.76 | J14: =I14*$J$1 -> 0 | K14: =S14*$K$1 -> 13095.75 | L14: =K14/0.75 -> 17461 | M14: =ROUND(L14,0) -> 17461 | N14: SES 50.40.21 | O14: 18380 | P14: =O14*0.75 -> 13785 | Q14: =P14/H14 -> 18138.158 | R14: 18138.158 | S14: =R14*H14 -> 13785 | T14: Корпус UC2 50.40.20 из нержавеющей стали IP66 USOLA | U14: 13750 | V14: 1015600 | W14: AE Шкаф, нерж.сталь с МП 400x500x210mm | X14: 277.23 | Y14: =X14*$Y$2 -> 20118.581 | Z14: 18,647.08 | AA14: 23,060.00 | AC14: R5CEB05421 | AD14: Навесной шкаф CE из нержавеющей стали (AISI 304), 500 x 400x 200мм, без фланца | AE14: 26310.67 | AF14: 18,417.74 | AG14: 23,863.00
B15: 500 | C15: 500 | D15: 200 | E15: IP67 | F15: 2 | G15: SE2013 | H15: =2*(B15*C15+C15*D15+B15*D15)/1000000 -> 0.9 | J15: =I15*$J$1 -> 0 | K15: =S15*$K$1 -> 14710.275 | L15: =K15/0.75 -> 19613.7 | M15: =ROUND(L15,0) -> 19614 | N15: SES 50.50.21 | O15: 20646 | P15: =O15*0.75 -> 15484.5 | Q15: =P15/H15 -> 17205 | R15: 17205 | S15: =R15*H15 -> 15484.5 | T15: Корпус UC2 50.50.20 из нержавеющей стали IP66 USOLA | U15: 15510 | V15: 1007600 | W15: AE Шкаф, нерж.сталь с МП 500x500x210mm | X15: 306.78 | Y15: =X15*$Y$2 -> 22263.025 | Z15: 20,635.16 | AA15: 25,519.00 | AC15: R5CEB05521 | AD15: Навесной шкаф CE из нержавеющей стали (AISI 304), 500 x 500x 200мм, без фланца | AE15: 28436.78 | AF15: 19,906.03 | AG15: 25,791.00
B16: 500 | C16: 600 | D16: 200 | E16: IP67 | F16: 2 | G16: SE2014 | H16: =2*(B16*C16+C16*D16+B16*D16)/1000000 -> 1.04 | J16: =I16*$J$1 -> 0 | K16: =S16*$K$1 -> 17550.186 | L16: =K16/0.75 -> 23400.248 | M16: =ROUND(L16,0) -> 23400 | P16: =O16*0.75 -> 0 | Q16: =P16/H16 -> 0 | R16: 17763.347 | S16: =R16*H16 -> 18473.88 | Y16: =X16*$Y$2 -> 0
B17: 500 | C17: 400 | D17: 250 | E17: IP67 | F17: 2 | G17: SE2015 | H17: =2*(B17*C17+C17*D17+B17*D17)/1000000 -> 0.85 | J17: =I17*$J$1 -> 0 | K17: =S17*$K$1 -> 14859.281 | L17: =K17/0.75 -> 19812.374 | M17: =ROUND(L17,0) -> 19812 | P17: =O17*0.75 -> 0 | Q17: =P17/H17 -> 0 | R17: 18401.586 | S17: =R17*H17 -> 15641.348 | Y17: =X17*$Y$2 -> 0 | AC17: R5CEB05491 | AD17: Навесной шкаф CE из нержавеющей стали (AISI 304), 500 x 400x 250мм, без фланца | AE17: 29500.64 | AF17: 20,650.74 | AG17: 26,756.00
B18: 500 | C18: 500 | D18: 300 | E18: IP67 | F18: 2 | G18: SE2016 | H18: =2*(B18*C18+C18*D18+B18*D18)/1000000 -> 1.1 | J18: =I18*$J$1 -> 0 | K18: =S18*$K$1 -> 18599.178 | L18: =K18/0.75 -> 24798.905 | M18: =ROUND(L18,0) -> 24799 | P18: =O18*0.75 -> 0 | Q18: =P18/H18 -> 0 | R18: 17798.257 | S18: =R18*H18 -> 19578.083 | V18: 1013600 | W18: AE Шкаф, нерж.сталь с МП 500x500x300mm | X18: 360.72 | Y18: =X18*$Y$2 -> 26177.45 | Z18: 24,263.41 | AA18: 30,006.00
B19: 500 | C19: 600 | D19: 300 | E19: IP67 | F19: 2 | G19: SE2017 | H19: =2*(B19*C19+C19*D19+B19*D19)/1000000 -> 1.26 | J19: =I19*$J$1 -> 0 | K19: =S19*$K$1 -> 20917.879 | L19: =K19/0.75 -> 27890.505 | M19: =ROUND(L19,0) -> 27891 | P19: =O19*0.75 -> 0 | Q19: =P19/H19 -> 0 | R19: 17475.254 | S19: =R19*H19 -> 22018.82 | Y19: =X19*$Y$2 -> 0
B20: 600 | C20: 400 | D20: 200 | E20: IP67 | F20: 2 | G20: SE2018 | H20: =2*(B20*C20+C20*D20+B20*D20)/1000000 -> 0.88 | J20: =I20*$J$1 -> 0 | K20: =S20*$K$1 -> 13994.212 | L20: =K20/0.75 -> 18658.95 | M20: =ROUND(L20,0) -> 18659 | N20: SES 60.40.21 | O20: 19641 | P20: =O20*0.75 -> 14730.75 | Q20: =P20/H20 -> 16739.489 | R20: 16739.489 | S20: =R20*H20 -> 14730.75 | T20: Корпус UC2 60.40.20 из нержавеющей стали IP66 USOLA | U20: 14740 | V20: 1008600 | W20: AE Шкаф, нерж.сталь с МП 380x600x210mm | X20: 292.62 | Y20: =X20*$Y$2 -> 21235.433 | Z20: 19,682.19 | AA20: 24,341.00 | AC20: R5CEB06421 | AD20: Навесной шкаф CE из нержавеющей стали (AISI 304), 600 x 400x 200мм, без фланца | AE20: 28225.02 | AF20: 19,757.80 | AG20: 25,599.00
B21: 600 | C21: 500 | D21: 200 | E21: IP67 | F21: 2 | G21: SE2019 | H21: =2*(B21*C21+C21*D21+B21*D21)/1000000 -> 1.04 | J21: =I21*$J$1 -> 0 | K21: =S21*$K$1 -> 17550.186 | L21: =K21/0.75 -> 23400.248 | M21: =ROUND(L21,0) -> 23400 | P21: =O21*0.75 -> 0 | Q21: =P21/H21 -> 0 | R21: 17763.347 | S21: =R21*H21 -> 18473.88 | Y21: =X21*$Y$2 -> 0
B22: 600 | C22: 400 | D22: 250 | E22: IP67 | F22: 2 | G22: SE2020 | H22: =2*(B22*C22+C22*D22+B22*D22)/1000000 -> 0.98 | I22: 20028.054 | J22: =I22*$J$1 -> 26036.471 | K22: =S22*$K$1 -> 16783.814 | L22: =K22/0.75 -> 22378.418 | M22: =ROUND(L22,0) -> 22378 | P22: =O22*0.75 -> 0 | Q22: =P22/H22 -> 0 | R22: 18027.727 | S22: =R22*H22 -> 17667.172 | Y22: =X22*$Y$2 -> 0 | AC22: R5CEB06491 | AD22: Навесной шкаф CE из нержавеющей стали (AISI 304), 600 x 400x 250мм, без фланца | AE22: 31496.47 | AF22: 22,047.84 | AG22: 28,566.00
B23: 600 | C23: 600 | D23: 250 | E23: IP67 | F23: 2 | G23: SE2021 | H23: =2*(B23*C23+C23*D23+B23*D23)/1000000 -> 1.32 | J23: =I23*$J$1 -> 0 | K23: =S23*$K$1 -> 19860.938 | L23: =K23/0.75 -> 26481.25 | M23: =ROUND(L23,0) -> 26481 | N23: SES 60.60.25 | O23: 27875 | P23: =O23*0.75 -> 20906.25 | Q23: =P23/H23 -> 15838.068 | R23: 15838.068 | S23: =R23*H23 -> 20906.25 | T23: Корпус UC2 60.60.25 из нержавеющей стали IP66 USOLA | U23: 20900 | V23: 1010600 | W23: AE Шкаф, нерж.сталь с МП 600x600x210mm | X23: 375.24 | Y23: =X23*$Y$2 -> 27231.167 | Z23: 25,239.94 | AA23: 31,214.00 | AC23: R5CEB06691 | AD23: Навесной шкаф CE из нержавеющей стали (AISI 304), 600 x 600x 250мм, без фланца | AE23: 36638.32 | AF23: 25,647.18 | AG23: 33,230.00
B24: 600 | C24: 400 | D24: 400 | E24: IP67 | F24: 2 | G24: SE2022 | H24: =2*(B24*C24+C24*D24+B24*D24)/1000000 -> 1.28 | J24: =I24*$J$1 -> 0 | K24: =S24*$K$1 -> 21004.23 | L24: =K24/0.75 -> 28005.64 | M24: =ROUND(L24,0) -> 28006 | P24: =O24*0.75 -> 0 | Q24: =P24/H24 -> 0 | R24: 17273.215 | S24: =R24*H24 -> 22109.716 | Y24: =X24*$Y$2 -> 0 | AC24: R5CEB06441 | AD24: Навесной шкаф CE из нержавеющей стали (AISI 304), 600 x 400x 400мм, без фланца | AE24: 52433.47 | AF24: 36,703.95 | AG24: 47,556.00
B25: 600 | C25: 600 | D25: 400 | E25: IP67 | F25: 2 | G25: SE2023 | H25: =2*(B25*C25+C25*D25+B25*D25)/1000000 -> 1.68 | J25: =I25*$J$1 -> 0 | K25: =S25*$K$1 -> 26223.733 | L25: =K25/0.75 -> 34964.977 | M25: =ROUND(L25,0) -> 34965 | P25: =O25*0.75 -> 0 | Q25: =P25/H25 -> 0 | R25: 16430.91 | S25: =R25*H25 -> 27603.929 | Y25: =X25*$Y$2 -> 0 | AC25: R5CEB06641 | AD25: Навесной шкаф CE из нержавеющей стали (AISI 304), 600 x 600x 400мм, без фланца | AE25: 53373.94 | AF25: 37,362.29 | AG25: 48,408.00
B26: 700 | C26: 500 | D26: 200 | E26: IP67 | F26: 2 | G26: SE2024 | H26: =2*(B26*C26+C26*D26+B26*D26)/1000000 -> 1.18 | J26: =I26*$J$1 -> 0 | K26: =S26*$K$1 -> 19698.77 | L26: =K26/0.75 -> 26265.027 | M26: =ROUND(L26,0) -> 26265 | P26: =O26*0.75 -> 0 | Q26: =P26/H26 -> 0 | R26: 17572.498 | S26: =R26*H26 -> 20735.548 | Y26: =X26*$Y$2 -> 0 | AC26: R5CEB07521 | AD26: Навесной шкаф CE из нержавеющей стали (AISI 304), 700 x 500x 200мм, без фланца | AE26: 34129.82 | AF26: 23,891.22 | AG26: 30,955.00
B27: 700 | C27: 500 | D27: 250 | E27: IP67 | F27: 2 | G27: SE2025 | H27: =2*(B27*C27+C27*D27+B27*D27)/1000000 -> 1.3 | J27: =I27*$J$1 -> 0 | K27: =S27*$K$1 -> 19488.3 | L27: =K27/0.75 -> 25984.4 | M27: =ROUND(L27,0) -> 25984 | N27: SES 70.50.25 | O27: 27352 | P27: =O27*0.75 -> 20514 | Q27: =P27/H27 -> 15780 | R27: 15780 | S27: =R27*H27 -> 20514 | T27: Корпус UC2 70.50.25 из нержавеющей стали IP66 USOLA | U27: 20570 | Y27: =X27*$Y$2 -> 0 | AC27: R5CEB07591 | AD27: Навесной шкаф CE из нержавеющей стали (AISI 304), 700 x 500x 250мм, без фланца | AE27: 37672.09 | AF27: 26,370.84 | AG27: 34,167.00
B28: 800 | C28: 600 | D28: 200 | E28: IP67 | F28: 2 | G28: SE2026 | H28: =2*(B28*C28+C28*D28+B28*D28)/1000000 -> 1.52 | J28: =I28*$J$1 -> 0 | K28: =S28*$K$1 -> 24282.009 | L28: =K28/0.75 -> 32376.012 | M28: =ROUND(L28,0) -> 32376 | P28: =O28*0.75 -> 0 | Q28: =P28/H28 -> 0 | R28: 16815.795 | S28: =R28*H28 -> 25560.009 | V28: 1012600 | W28: AE Шкаф, нерж.сталь с МП 600x760x210mm | X28: 435.11 | Y28: =X28*$Y$2 -> 31575.933 | Z28: 29,267.54 | AA28: 36,195.00
B29: 800 | C29: 800 | D29: 200 | E29: IP67 | F29: 2 | G29: SE2027 | H29: =2*(B29*C29+C29*D29+B29*D29)/1000000 -> 1.92 | J29: =I29*$J$1 -> 0 | K29: =S29*$K$1 -> 29019.526 | L29: =K29/0.75 -> 38692.702 | M29: =ROUND(L29,0) -> 38693 | P29: =O29*0.75 -> 0 | Q29: =P29/H29 -> 0 | R29: 15909.828 | S29: =R29*H29 -> 30546.87 | Y29: =X29*$Y$2 -> 0
B30: 800 | C30: 600 | D30: 250 | E30: IP67 | F30: 2 | G30: SE2028 | H30: =2*(B30*C30+C30*D30+B30*D30)/1000000 -> 1.66 | J30: =I30*$J$1 -> 0 | K30: =S30*$K$1 -> 26004.606 | L30: =K30/0.75 -> 34672.808 | M30: =ROUND(L30,0) -> 34673 | P30: =O30*0.75 -> 0 | Q30: =P30/H30 -> 0 | R30: 16489.921 | S30: =R30*H30 -> 27373.269 | Y30: =X30*$Y$2 -> 0 | AC30: R5CEB08691 | AD30: Навесной шкаф CE из нержавеющей стали (AISI 304), 800 x 600x 250мм, без фланца | AE30: 43740.62 | AF30: 30,618.86 | AG30: 39,671.00
B31: 800 | C31: 600 | D31: 300 | E31: IP67 | F31: 2 | G31: SE2029 | H31: =2*(B31*C31+C31*D31+B31*D31)/1000000 -> 1.8 | J31: =I31*$J$1 -> 0 | K31: =S31*$K$1 -> 24984.525 | L31: =K31/0.75 -> 33312.7 | M31: =ROUND(L31,0) -> 33313 | N31: SES 80.60.30 | O31: 35066 | P31: =O31*0.75 -> 26299.5 | Q31: =P31/H31 -> 14610.833 | R31: 14610.833 | S31: =R31*H31 -> 26299.5 | T31: Корпус UC2 80.60.30 из нержавеющей стали IP66 USOLA | U31: 26400 | Y31: =X31*$Y$2 -> 0 | AC31: R5CEB08631 | AD31: Навесной шкаф CE из нержавеющей стали (AISI 304), 800 x 600x 300мм, без фланца | AE31: 47769.53 | AF31: 33,439.15 | AG31: 43,325.00
B32: 800 | C32: 800 | D32: 300 | E32: IP67 | F32: 2 | G32: SE2030 | H32: =2*(B32*C32+C32*D32+B32*D32)/1000000 -> 2.24 | J32: =I32*$J$1 -> 0 | K32: =S32*$K$1 -> 32228.003 | L32: =K32/0.75 -> 42970.67 | M32: =ROUND(L32,0) -> 42971 | P32: =O32*0.75 -> 0 | Q32: =P32/H32 -> 0 | R32: 15144.738 | S32: =R32*H32 -> 33924.213 | V32: 1014600 | W32: AE Шкаф, нерж.сталь с МП 760x760x300mm | X32: 620.19 | Y32: =X32*$Y$2 -> 45007.188 | Z32: 41,717.48 | AA32: 51,591.00 | AC32: R5CEB08831 | AD32: Навесной шкаф CE из нержавеющей стали (AISI 304), 800 x 800x 300мм, без фланца | AE32: 55054.74 | AF32: 38,538.87 | AG32: 49,933.00
B33: 800 | C33: 600 | D33: 400 | E33: IP67 | F33: 2 | G33: SE2031 | H33: =2*(B33*C33+C33*D33+B33*D33)/1000000 -> 2.08 | J33: =I33*$J$1 -> 0 | K33: =S33*$K$1 -> 30644.502 | L33: =K33/0.75 -> 40859.336 | M33: =ROUND(L33,0) -> 40859 | P33: =O33*0.75 -> 0 | Q33: =P33/H33 -> 0 | R33: 15508.351 | S33: =R33*H33 -> 32257.371 | T33: Корпус UC2 80.80.40 из нержавеющей стали IP66 USOLA | U33: 33000 | Y33: =X33*$Y$2 -> 0 | AC33: R5CEB08641 | AD33: Навесной шкаф CE из нержавеющей стали (AISI 304), 800 x 600x 400мм, без фланца | AE33: 67920.48 | AF33: 47,545.02 | AG33: 61,602.00
B34: 800 | C34: 800 | D34: 400 | E34: IP67 | F34: 2 | G34: SE2032 | H34: =2*(B34*C34+C34*D34+B34*D34)/1000000 -> 2.56 | J34: =I34*$J$1 -> 0 | K34: =S34*$K$1 -> 34984.066 | L34: =K34/0.75 -> 46645.421 | M34: =ROUND(L34,0) -> 46645 | P34: =O34*0.75 -> 0 | Q34: =P34/H34 -> 0 | R34: 14384.895 | S34: =R34*H34 -> 36825.332 | Y34: =X34*$Y$2 -> 0 | AC34: R5CEB08841 | AD34: Навесной шкаф CE из нержавеющей стали (AISI 304), 800 x 800x 400мм, без фланца | AE34: 77630.89 | AF34: 54,342.40 | AG34: 70,409.00
B35: 1000 | C35: 600 | D35: 250 | E35: IP66 | F35: 2 | G35: SE2033 | H35: =2*(B35*C35+C35*D35+B35*D35)/1000000 -> 2 | J35: =I35*$J$1 -> 0 | K35: =S35*$K$1 -> 29823.832 | L35: =K35/0.75 -> 39765.109 | M35: =ROUND(L35,0) -> 39765 | P35: =O35*0.75 -> 0 | Q35: =P35/H35 -> 0 | R35: 15696.754 | S35: =R35*H35 -> 31393.507 | Y35: =X35*$Y$2 -> 0 | AC35: R5CEB10691 | AD35: Навесной шкаф CE из нержавеющей стали (AISI 304), 1000 x 600 x 250мм, без фланца | AE35: 49511.53 | AF35: 34,658.56 | AG35: 44,905.00
B36: 1000 | C36: 600 | D36: 300 | E36: IP66 | F36: 2 | G36: SE2034 | H36: =2*(B36*C36+C36*D36+B36*D36)/1000000 -> 2.16 | J36: =I36*$J$1 -> 0 | K36: =S36*$K$1 -> 31439.358 | L36: =K36/0.75 -> 41919.144 | M36: =ROUND(L36,0) -> 41919 | P36: =O36*0.75 -> 0 | Q36: =P36/H36 -> 0 | R36: 15321.325 | S36: =R36*H36 -> 33094.061 | T36: Корпус UC2 100.60.30 из нержавеющей стали IP66 USOLA | U36: 33000 | Y36: =X36*$Y$2 -> 0 | AC36: R5CEB10631 | AD36: Навесной шкаф CE из нержавеющей стали (AISI 304), 1000 x 600 x 300мм, без фланца | AE36: 53679.97 | AF36: 37,576.51 | AG36: 48,686.00
B37: 1000 | C37: 800 | D37: 300 | E37: IP66 | F37: 2 | G37: SE2035 | H37: =2*(B37*C37+C37*D37+B37*D37)/1000000 -> 2.68 | J37: =I37*$J$1 -> 0 | K37: =S37*$K$1 -> 33845.175 | L37: =K37/0.75 -> 45126.9 | M37: =ROUND(L37,0) -> 45127 | N37: SES 100.80.30 | O37: 47502 | P37: =O37*0.75 -> 35626.5 | Q37: =P37/H37 -> 13293.47 | R37: 13293.47 | S37: =R37*H37 -> 35626.5 | T37: Корпус UC2 100.80.30 из нержавеющей стали IP66 USOLA | U37: 35750 | V37: 1016600 | W37: AE Шкаф,нерж.сталь с МП 800x1000x300mm | X37: 704.6 | Y37: =X37*$Y$2 -> 51132.822 | Z37: 47,394.55 | AA37: 58,612.00 | AC37: R5CEB10831 | AD37: Навесной шкаф CE из нержавеющей стали (AISI 304), 1000 x 800 x 300мм, без фланца | AE37: 66091.39 | AF37: 46,264.64 | AG37: 59,943.00
B38: 1000 | C38: 600 | D38: 400 | E38: IP66 | F38: 2 | G38: SE2036 | H38: =2*(B38*C38+C38*D38+B38*D38)/1000000 -> 2.48 | J38: =I38*$J$1 -> 0 | K38: =S38*$K$1 -> 34386.097 | L38: =K38/0.75 -> 45848.129 | M38: =ROUND(L38,0) -> 45848 | P38: =O38*0.75 -> 0 | Q38: =P38/H38 -> 0 | R38: 14595.118 | S38: =R38*H38 -> 36195.892 | Y38: =X38*$Y$2 -> 0 | AC38: R5CEB10641 | AD38: Навесной шкаф CE из нержавеющей стали (AISI 304), 1000 x 600 x 400мм, без фланца | AE38: 75363.41 | AF38: 52,755.15 | AG38: 68,352.00
B39: 1000 | C39: 800 | D39: 400 | E39: IP66 | F39: 2 | G39: SE2037 | H39: =2*(B39*C39+C39*D39+B39*D39)/1000000 -> 3.04 | J39: =I39*$J$1 -> 0 | K39: =S39*$K$1 -> 38456.402 | L39: =K39/0.75 -> 51275.203 | M39: =ROUND(L39,0) -> 51275 | P39: =O39*0.75 -> 0 | Q39: =P39/H39 -> 0 | R39: 13315.929 | S39: =R39*H39 -> 40480.423 | Y39: =X39*$Y$2 -> 0 | AC39: R5CEB10841 | AD39: Навесной шкаф CE из нержавеющей стали (AISI 304), 1000 x 800 x 400мм, без фланца | AE39: 86497.47 | AF39: 60,549.09 | AG39: 78,451.00
B40: 1200 | C40: 600 | D40: 200 | E40: IP66 | F40: 2 | G40: SE2038 | H40: =2*(B40*C40+C40*D40+B40*D40)/1000000 -> 2.16 | J40: =I40*$J$1 -> 0 | K40: =S40*$K$1 -> 31439.358 | L40: =K40/0.75 -> 41919.144 | M40: =ROUND(L40,0) -> 41919 | P40: =O40*0.75 -> 0 | Q40: =P40/H40 -> 0 | R40: 15321.325 | S40: =R40*H40 -> 33094.061 | Y40: =X40*$Y$2 -> 0
B41: 1200 | C41: 600 | D41: 300 | E41: IP66 | F41: 2 | G41: SE2039 | H41: =2*(B41*C41+C41*D41+B41*D41)/1000000 -> 2.52 | J41: =I41*$J$1 -> 0 | K41: =S41*$K$1 -> 34716.194 | L41: =K41/0.75 -> 46288.259 | M41: =ROUND(L41,0) -> 46288 | P41: =O41*0.75 -> 0 | Q41: =P41/H41 -> 0 | R41: 14501.334 | S41: =R41*H41 -> 36543.362 | Y41: =X41*$Y$2 -> 0 | AC41: R5CEB12631 | AD41: Навесной шкаф CE из нержавеющей стали (AISI 304), 1200 x 600 x 300мм, без фланца | AE41: 60414.27 | AF41: 42,290.59 | AG41: 54,794.00
B42: 1200 | C42: 800 | D42: 300 | E42: IP66 | F42: 2 | G42: SE2040 | H42: =2*(B42*C42+C42*D42+B42*D42)/1000000 -> 3.12 | J42: =I42*$J$1 -> 0 | K42: =S42*$K$1 -> 38898.938 | L42: =K42/0.75 -> 51865.25 | M42: =ROUND(L42,0) -> 51865 | N42: SES 120.80.30 | O42: 54595 | P42: =O42*0.75 -> 40946.25 | Q42: =P42/H42 -> 13123.798 | R42: 13123.798 | S42: =R42*H42 -> 40946.25 | T42: Корпус UC2 120.80.30 из нержавеющей стали IP66 USOLA | U42: 41030 | Y42: =X42*$Y$2 -> 0 | AC42: R5CEB12831 | AD42: Навесной шкаф CE из нержавеющей стали (AISI 304), 1200 x 800 x 300мм, без фланца | AE42: 70508.87 | AF42: 49,356.91 | AG42: 63,949.00
B43: 1200 | C43: 600 | D43: 400 | E43: IP66 | F43: 2 | G43: SE2041 | H43: =2*(B43*C43+C43*D43+B43*D43)/1000000 -> 2.88 | J43: =I43*$J$1 -> 0 | K43: =S43*$K$1 -> 37395.234 | L43: =K43/0.75 -> 49860.312 | M43: =ROUND(L43,0) -> 49860 | P43: =O43*0.75 -> 0 | Q43: =P43/H43 -> 0 | R43: 13667.849 | S43: =R43*H43 -> 39363.405 | Y43: =X43*$Y$2 -> 0
B44: 1200 | C44: 800 | D44: 400 | E44: IP66 | F44: 2 | G44: SE2042 | H44: =2*(B44*C44+C44*D44+B44*D44)/1000000 -> 3.52 | I44: 38047.849 | J44: =I44*$J$1 -> 49462.204 | K44: =S44*$K$1 -> 40765.164 | L44: =K44/0.75 -> 54353.552 | M44: =ROUND(L44,0) -> 54354 | P44: =O44*0.75 -> 0 | Q44: =P44/H44 -> 0 | R44: 12190.539 | S44: =R44*H44 -> 42910.699 | Y44: =X44*$Y$2 -> 0
B45: 1400 | C45: 600 | D45: 300 | E45: IP66 | F45: 2 | G45: SE2043 | H45: =2*(B45*C45+C45*D45+B45*D45)/1000000 -> 2.88 | J45: =I45*$J$1 -> 0 | K45: =S45*$K$1 -> 37395.234 | L45: =K45/0.75 -> 49860.312 | M45: =ROUND(L45,0) -> 49860 | P45: =O45*0.75 -> 0 | Q45: =P45/H45 -> 0 | R45: 13667.849 | S45: =R45*H45 -> 39363.405 | V45: 1017600 | W45: AE Шкаф,нерж.сталь с МП 800x1200x300mm | X45: 823.26 | Y45: =X45*$Y$2 -> 59743.978 | Z45: 55,376.15 | AA45: 68,483.00 | AC45: R5CEB14631 | AD45: Навесной шкаф CE из нержавеющей стали (AISI 304), 1400 x 600 x 300мм, без фланца | AE45: 76645.45 | AF45: 53,652.58 | AG45: 69,515.00
B46: 1400 | C46: 800 | D46: 300 | E46: IP66 | F46: 2 | G46: SE2044 | H46: =2*(B46*C46+C46*D46+B46*D46)/1000000 -> 3.56 | J46: =I46*$J$1 -> 0 | K46: =S46*$K$1 -> 40935.169 | L46: =K46/0.75 -> 54580.225 | M46: =ROUND(L46,0) -> 54580 | P46: =O46*0.75 -> 0 | Q46: =P46/H46 -> 0 | R46: 12103.835 | S46: =R46*H46 -> 43089.651 | Y46: =X46*$Y$2 -> 0 | AC46: R5CEB14831 | AD46: Навесной шкаф CE из нержавеющей стали (AISI 304), 1400 x 800 x 300мм, без фланца | AE46: 90281.12 | AF46: 63,197.68 | AG46: 81,882.00
Y47: =X47*$Y$2 -> 0
V48: 1001600 | W48: AE Шкаф, нерж.сталь с МП 200x300x120mm | X48: 150.52 | Y48: =X48*$Y$2 -> 10923.236 | AC48: R5CEB06831 | AD48: Навесной шкаф CE из нержавеющей стали (AISI 304), двухдверный, 600 x 800 x 300мм, без фланца | AE48: 56055.9
V49: 1002500 | W49: AE Шкаф, нерж.сталь с МП 200x300x155mm | X49: 277.65 | Y49: =X49*$Y$2 -> 20149.06 | AC49: R5CEB08121 | AD49: Навесной шкаф CE из нержавеющей стали (AISI 304), двухдверный, 800 x 1000 x 200мм, без фланца | AE49: 64999.83
V50: 1003600 | W50: AE Шкаф, нерж.сталь с МП 300x300x210mm | X50: 187.38 | Y50: =X50*$Y$2 -> 13598.167 | AC50: R5CEB08131 | AD50: Навесной шкаф CE из нержавеющей стали (AISI 304), двухдверный, 800 x 1000 x 300мм, без фланца | AE50: 75311.28
V51: 1005500 | W51: AE Шкаф, нерж.сталь с МП 300x380x210mm | X51: 368.71 | Y51: =X51*$Y$2 -> 26757.285 | AC51: R5CEB10131 | AD51: Навесной шкаф CE из нержавеющей стали (AISI 304), двухдверный, 1000 x 1000 x 300мм, без фланца | AE51: 86296.81
V52: 1006500 | W52: AE Шкаф, нерж.сталь с МП 380x380x210mm | X52: 377.42 | Y52: =X52*$Y$2 -> 27389.369 | AC52: R5CEB121231 | AD52: Навесной шкаф CE из нержавеющей стали (AISI 304), двухдверный, 1200 x 1200 x 300мм, без фланца | AE52: 119180.57
V53: 1010500 | W53: AE Шкаф, нерж.сталь с МП 600x600x210mm | X53: 637.35 | Y53: =X53*$Y$2 -> 46252.489 | AC53: R5CEB12131 | AD53: Навесной шкаф CE из нержавеющей стали (AISI 304), двухдверный, 1200 x 1000 x 300мм, без фланца | AE53: 98546.04
V54: 1018600 | W54: AE Шкаф,нерж.сталь с МП1000x1000x300mm | X54: 927.77 | Y54: =X54*$Y$2 -> 67328.269 | AC54: R5CEB14131 | AD54: Навесной шкаф CE из нержавеющей стали (AISI 304), двухдверный, 1400 x 1000 x 300мм, без фланца | AE54: 107260.48
V55: 1019500 | W55: AE Шкаф,нерж.сталь с МП1000x1200x300mm | X55: 1617.46 | Y55: =X55*$Y$2 -> 117379.07
V56: 1019600 | W56: AE Шкаф,нерж.сталь с МП1000x1200x300mm | X56: 1003.19 | Y56: =X56*$Y$2 -> 72801.498

Sheet SE2100(нерж304)
I1: 514
B2: IPEX
B3: 300 | C3: 200 | D3: 150 | E3: IP67 | F3: 1 | G3: SЕ2101 | H3: ='SE2000 (нерж304)'!M3 -> 11026 | I3: =H3+$I$1 -> 11540
B4: 300 | C4: 250 | D4: 150 | E4: IP67 | F4: 1 | G4: SE2102 | H4: ='SE2000 (нерж304)'!M4 -> 8793 | I4: =H4+$I$1 -> 9307
B5: 300 | C5: 300 | D5: 150 | E5: IP67 | F5: 1 | G5: SE2103 | H5: ='SE2000 (нерж304)'!M5 -> 9164 | I5: =H5+$I$1 -> 9678
B6: 300 | C6: 400 | D6: 150 | E6: IP67 | F6: 1 | G6: SE2104 | H6: ='SE2000 (нерж304)'!M6 -> 12398 | I6: =H6+$I$1 -> 12912
B7: 300 | C7: 400 | D7: 200 | E7: IP67 | F7: 1 | G7: SE2105 | H7: ='SE2000 (нерж304)'!M7 -> 12727 | I7: =H7+$I$1 -> 13241
B8: 400 | C8: 300 | D8: 150 | E8: IP67 | F8: 1 | G8: SE2106 | H8: ='SE2000 (нерж304)'!M8 -> 12398 | I8: =H8+$I$1 -> 12912
B9: 400 | C9: 300 | D9: 200 | E9: IP67 | F9: 1 | G9: SE2107 | H9: ='SE2000 (нерж304)'!M9 -> 12727 | I9: =H9+$I$1 -> 13241
B10: 400 | C10: 400 | D10: 200 | E10: IP67 | F10: 1 | G10: SE2108 | H10: ='SE2000 (нерж304)'!M10 -> 14931 | I10: =H10+$I$1 -> 15445
B11: 400 | C11: 600 | D11: 200 | E11: IP67 | F11: 1 | G11: SE2109 | H11: ='SE2000 (нерж304)'!M11 -> 18659 | I11: =H11+$I$1 -> 19173
B12: 500 | C12: 300 | D12: 150 | E12: IP67 | F12: 2 | G12: SE2110 | H12: ='SE2000 (нерж304)'!M12 -> 12971 | I12: =H12+$I$1 -> 13485
B13: 500 | C13: 300 | D13: 200 | E13: IP67 | F13: 2 | G13: SE2111 | H13: ='SE2000 (нерж304)'!M13 -> 14821 | I13: =H13+$I$1 -> 15335
B14: 500 | C14: 400 | D14: 200 | E14: IP67 | F14: 2 | G14: SE2112 | H14: ='SE2000 (нерж304)'!M14 -> 17461 | I14: =H14+$I$1 -> 17975
... B46: 1400 | C46: 800 | D46: 300 | E46: IP66 | F46: 2 | G46: SE2144 | H46: ='SE2000 (нерж304)'!M46 -> 54580 | I46: =H46+$I$1 -> 55094

Sheet Напольные корпуса линейных шкаф
B1: IPEX | F1: Провенто | I1: УЗОЛА
B2: высота | C2: Ширина шкафа, мм. | D2: Глубина шкафа, мм. | E2: Артикул
B3: 1200 | C3: 300 | D3: 400 | E3: FE 1001
B4: 1200 | C4: 300 | D4: 500 | E4: FE 1002
B5: 1200 | C5: 300 | D5: 600 | E5: FE 1003
B6: 1200 | C6: 300 | D6: 800 | E6: FE 1004
B7: 1200 | C7: 300 | D7: 1000 | E7: FE 1005
B8: 1200 | C8: 400 | D8: 300 | E8: FE 1001
B9: 1200 | C9: 400 | D9: 400 | E9: FE 1006
B10: 1200 | C10: 400 | D10: 500 | E10: FE 1007
B11: 1200 | C11: 400 | D11: 600 | E11: FE 1008
B12: 1200 | C12: 400 | D12: 800 | E12: FE 1009
B13: 1200 | C13: 400 | D13: 1000 | E13: FE 1010
B14: 1200 | C14: 600 | D14: 300 | E14: FE 1003
B15: 1200 | C15: 600 | D15: 400 | E15: FE 1008
B16: 1200 | C16: 600 | D16: 500 | E16: FE 1011 | I16: U7705126050 | J16: Корпус LC2 120.60.50 IP55 USOLA | K16: 25145
B17: 1200 | C17: 600 | D17: 600 | E17: FE 1012
B18: 1200 | C18: 600 | D18: 800 | E18: FE 1013
B19: 1200 | C19: 600 | D19: 1000 | E19: FE 1014
B20: 1200 | C20: 800 | D20: 300 | E20: FE 1004
B21: 1200 | C21: 800 | D21: 400 | E21: FE 1009
B22: 1200 | C22: 800 | D22: 500 | E22: FE 1015 | I22: U7705128050 | J22: Корпус LC2 120.80.50 IP55 USOLA | K22: 27351
B23: 1200 | C23: 600 | D23: 600 | E23: FE 1012
B24: 1200 | C24: 800 | D24: 800 | E24: FE 1016
B25: 1200 | C25: 800 | D25: 1000 | E25: FE 1017
B26: 1200 | C26: 1000 | D26: 300 | E26: FE 1005
B27: 1200 | C27: 1000 | D27: 400 | E27: FE 1010
B28: 1200 | C28: 1000 | D28: 500 | E28: FE 1018
B29: 1200 | C29: 1000 | D29: 600 | E29: FE 1014
B30: 1200 | C30: 1000 | D30: 800 | E30: FE 1017
B31: 1200 | C31: 1000 | D31: 1000 | E31: FE 1019
B32: 1400 | C32: 300 | D32: 400 | E32: FE 1020
B33: 1400 | C33: 300 | D33: 500 | E33: FE 1021
B34: 1400 | C34: 300 | D34: 600 | E34: FE 1022
... B44: 1400 | C44: 600 | D44: 400 | E44: FE 1027
B45: 1400 | C45: 600 | D45: 500 | E45: FE 1030 | I45: U7705146050 | J45: Корпус LC2 140.60.50 IP55 USOLA | K45: 25805
B46: 1400 | C46: 600 | D46: 600 | E46: FE 1031
B47: 1400 | C47: 600 | D47: 800 | E47: FE 1032
B48: 1400 | C48: 600 | D48: 1000 | E48: FE 1033
B49: 1400 | C49: 800 | D49: 300 | E49: FE 1023
B50: 1400 | C50: 800 | D50: 400 | E50: FE 1028
B51: 1400 | C51: 800 | D51: 500 | E51: FE 1034 | I51: U7705148050 | J51: Корпус LC2 140.80.50 IP55 USOLA | K51: 27932
B52: 1400 | C52: 600 | D52: 600 | E52: FE 1031
B53: 1400 | C53: 800 | D53: 800 | E53: FE 1035
B54: 1400 | C54: 800 | D54: 1000 | E54: FE 1036
B55: 1400 | C55: 1000 | D55: 300 | E55: FE 1024
B56: 1400 | C56: 1000 | D56: 400 | E56: FE 1029
B57: 1400 | C57: 1000 | D57: 500 | E57: FE 1037
B58: 1400 | C58: 1000 | D58: 600 | E58: FE 1033
B59: 1400 | C59: 1000 | D59: 800 | E59: FE 1036
B60: 1400 | C60: 1000 | D60: 1000 | E60: FE 1038
B61: 1600 | C61: 300 | D61: 400 | E61: FE 1039
B62: 1600 | C62: 300 | D62: 500 | E62: FE 1040
B63: 1600 | C63: 300 | D63: 600 | E63: FE 1041
... B73: 1600 | C73: 600 | D73: 400 | E73: FE 1046
B74: 1600 | C74: 600 | D74: 500 | E74: FE 1049 | I74: U7705166050 | J74: Корпус LC2 160.60.50 IP55 USOLA | K74: 26897
B75: 1600 | C75: 600 | D75: 600 | E75: FE 1050
B76: 1600 | C76: 600 | D76: 800 | E76: FE 1051
B77: 1600 | C77: 600 | D77: 1000 | E77: FE 1052
B78: 1600 | C78: 800 | D78: 300 | E78: FE 1042
B79: 1600 | C79: 800 | D79: 400 | E79: FE 1047 | I79: U7705168040 | J79: Корпус LC2 160.80.40 IP55 USOLA | K79: 26400
B80: 1600 | C80: 800 | D80: 500 | E80: FE 1053 | I80: U7705168050 | J80: Корпус LC2 160.80.50 IP55 USOLA | K80: 29023
B81: 1600 | C81: 600 | D81: 600 | E81: FE 1050
B82: 1600 | C82: 800 | D82: 800 | E82: FE 1054
B83: 1600 | C83: 800 | D83: 1000 | E83: FE 1055
B84: 1600 | C84: 1000 | D84: 300 | E84: FE 1043
B85: 1600 | C85: 1000 | D85: 400 | E85: FE 1048
B86: 1600 | C86: 1000 | D86: 500 | E86: FE 1056 | I86: U7702161050 | J86: Корпус LC2 160.100.50 IP55 USOLA | K86: 42985
B87: 1600 | C87: 1000 | D87: 600 | E87: FE 1052
B88: 1600 | C88: 1000 | D88: 800 | E88: FE 1055
B89: 1600 | C89: 1000 | D89: 1000 | E89: FE 1057
B90: 1800 | C90: 300 | D90: 400 | E90: FE 1058
B91: 1800 | C91: 300 | D91: 500 | E91: FE 1059
B92: 1800 | C92: 300 | D92: 600 | E92: FE 1060
B93: 1800 | C93: 300 | D93: 800 | E93: FE 1061
B94: 1800 | C94: 300 | D94: 1000 | E94: FE 1062
B95: 1800 | C95: 400 | D95: 300 | E95: FE 1058
B96: 1800 | C96: 400 | D96: 400 | E96: FE 1063
B97: 1800 | C97: 400 | D97: 500 | E97: FE 1064
B98: 1800 | C98: 400 | D98: 600 | E98: FE 1065
... B101: 1800 | C101: 600 | D101: 300 | E101: FE 1060
B102: 1800 | C102: 600 | D102: 400 | E102: FE 1065 | I102: U7705186040 | J102: Корпус LC2 180.60.40 IP55 USOLA | K102: 24381
B103: 1800 | C103: 600 | D103: 500 | E103: FE 1068 | F103: Шкаф индивидуальной сборки | G103: MPS 180.60.50 1056-0 | H103: 30102 | I103: U7705186050 | J103: Корпус LC2 180.60.50 IP55 USOLA | K103: 27498
B104: 1800 | C104: 600 | D104: 600 | E104: FE 1069 | F104: Шкаф индивидуальной сборки | G104: MPS 180.60.60 1057-0 | H104: 39175 | I104: U7705186060 | J104: Корпус LC2 180.60.60 IP55 USOLA | K104: 29195
B105: 1800 | C105: 600 | D105: 800 | E105: FE 1070
B106: 1800 | C106: 600 | D106: 1000 | E106: FE 1071
B107: 1800 | C107: 800 | D107: 300 | E107: FE 1061
B108: 1800 | C108: 800 | D108: 400 | E108: FE 1066 | I108: U7705188040 | J108: Корпус LC2 180.80.40 IP55 USOLA | K108: 27499
B109: 1800 | C109: 800 | D109: 500 | E109: FE 1072 | F109: Шкаф индивидуальной сборки | G109: MPS 180.80.50 1056-0 | H109: 32444 | I109: U7705188050 | J109: Корпус LC2 180.80.50 IP55 USOLA | K109: 30198
B110: 1800 | C110: 600 | D110: 600 | E110: FE 1069
B111: 1800 | C111: 800 | D111: 800 | E111: FE 1073 | I111: U7705188080 | J111: Корпус LC2 180.80.80 IP55 USOLA | K111: 34430
B112: 1800 | C112: 800 | D112: 1000 | E112: FE 1074
B113: 1800 | C113: 1000 | D113: 300 | E113: FE 1062
B114: 1800 | C114: 1000 | D114: 400 | E114: FE 1067 | I114: U7702181040 | J114: Корпус LC2 180.100.40 IP55 USOLA | K114: 44085
B115: 1800 | C115: 1000 | D115: 500 | E115: FE 1075
B116: 1800 | C116: 1000 | D116: 600 | E116: FE 1071
B117: 1800 | C117: 1000 | D117: 800 | E117: FE 1074
B118: 1800 | C118: 1000 | D118: 1000 | E118: FE 1076
B119: 2000 | C119: 300 | D119: 400 | E119: FE 1077
B120: 2000 | C120: 300 | D120: 500 | E120: FE 1078
...

Sheet коробки соеденительные CS
B1: IPEX | J1: Провенто | L1: УЗОЛА | O1: Rittal | R1: 72.57
B2: А, мм. | C2: В, мм. | D2: С, мм. | E2: H, мм. | F2: К, мм. | G2: Степень защиты | H2: Кол-во клемм | I2: Артикул | O2: 1545500 | P2: EB Электрошкафчик 150x300x80mm RAL7035 | Q2: 43.09 | R2: =Q2*$R$1 -> 3127.0413
B3: 230 | C3: 150 | D3: 135 | E3: 153 | F3: 185 | G3: IP67 | H3: 1х26, 2хРЕ | I3: СS1001 | L3: U7521202015 | M3: Корпус UC2 20.20.15 IP66 USOLA | N3: 2060 | O3: 1546500 | P3: EB Электрошкафчик 200x200x80mm RAL7035 | Q3: 40.38 | R3: =Q3*$R$1 -> 2930.3766
B4: 260 | C4: 260 | D4: 150 | E4: 183 | F4: 295 | G4: IP67 | H4: 1х30 | I4: СS1002 | J4: MES 20.20.12 | K4: 2381 | L4: U7521203015 | M4: Корпус UC2 20.30.15 IP66 USOLA | N4: 2191 | O4: 1547500 | P4: EB Электрошкафчик 200x400x80mm RAL7035 | Q4: 52.58 | R4: =Q4*$R$1 -> 3815.7306
B5: 310 | C5: 310 | D5: 200 | E5: 233 | F5: 345 | G5: IP67 | H5: 1х32, 4хРЕ | I5: СS1003 | J5: MES 30.30.15 | K5: 3433 | L5: U7521303020 | M5: Корпус UC2 30.30.20 IP66 USOLA | N5: 2977 | O5: 1548500 | P5: EB Электрошкафчик 150x300x120mm RAL7035 | Q5: 43.06 | R5: =Q5*$R$1 -> 3124.8642
B6: 480 | C6: 480 | D6: 200 | E6: 403 | F6: 515 | G6: IP67 | H6: 1х66, 1х59, 5хРЕ | I6: СS1004 | J6: MES 50.50.21 | K6: 5625 | L6: U7521505020 | M6: Корпус UC2 50.50.20 IP66 USOLA | N6: 4829 | O6: 1549500 | P6: EB Электрошкафчик 200x200x120mm RAL7035 | Q6: 37.76 | R6: =Q6*$R$1 -> 2740.2432
O7: 1550500 | P7: EB Электрошкафчик 200x400x120mm RAL7035 | Q7: 51.14 | R7: =Q7*$R$1 -> 3711.2298
B8: 230 | C8: 150 | D8: 135 | E8: 153 | F8: 185 | G8: IP67 | H8: 1х26, 2хРЕ | I8: СS2001 | O8: 1551500 | P8: EB Электрошкафчик 150x150x80mm RAL7035 | Q8: 38.83 | R8: =Q8*$R$1 -> 2817.8931
B9: 260 | C9: 260 | D9: 150 | E9: 183 | F9: 295 | G9: IP67 | H9: 1х30 | I9: СS2002 | J9: SES 30.20.15 | K9: 10847 | L9: U7582302015 | M9: Корпус UC2 30.20.15 из нержавеющей стали IP66 USOLA | N9: 8690 | O9: 1552500 | P9: EB Электрошкафчик 200x300x80mm RAL7035 | Q9: 47.7 | R9: =Q9*$R$1 -> 3461.589
B10: 310 | C10: 310 | D10: 200 | E10: 233 | F10: 345 | G10: IP67 | H10: 1х32, 4хРЕ | I10: СS2003 | J10: SES 30.40.15 | K10: 12197 | L10: U7582304015 | M10: Корпус UC2 30.40.15 из нержавеющей стали IP66 USOLA | N10: 9790 | O10: 1553500 | P10: EB Электрошкафчик150x150x120мм RАL7035 | Q10: 39.96 | R10: =Q10*$R$1 -> 2899.8972
B11: 480 | C11: 480 | D11: 200 | E11: 403 | F11: 515 | G11: IP67 | H11: 1х66, 1х59, 5хРЕ | I11: СS2004 | J11: SES 50.50.21 | K11: 19296 | L11: U7582505020 | M11: Корпус UC2 50.50.20 из нержавеющей стали IP66 USOLA | N11: 15510 | O11: 1554500 | P11: EB Электрошкафчик 200x300x120mm RAL7035 | Q11: 42.96 | R11: =Q11*$R$1 -> 3117.6072
O12: 1555500 | P12: EB Электрошкафчик 300x300x120mm RAL7035 | Q12: 47.83 | R12: =Q12*$R$1 -> 3471.0231
B13: 120 | C13: 120 | D13: 80 | E13: - | F13: 155 | G13: IP67 | H13: 1х11 | I13: СS1101 | J13: MBS 12.12.06 | K13: 1140 | L13: U7541121206 | M13: Клеммная коробкаТВ 12.12.06 IP66 USOLA | N13: 924 | O13: 1556500 | P13: EB Электрошкафчик 300x400x120mm RAL7035 | Q13: 59.21 | R13: =Q13*$R$1 -> 4296.8697
B14: 150 | C14: 150 | D14: 90 | E14: 73 | F14: 185 | G14: IP67 | H14: 1х14 | I14: СS1102 | J14: MBS 15.15.08 | K14: 1385 | L14: U7541151512 | M14: Клеммная коробка ТВ 15.15.12 IP66 USOLA | N14: 1447 | O14: 1557500 | P14: EB Электрошкафчик 200x500x120mm RAL7035 | Q14: 59.6 | R14: =Q14*$R$1 -> 4325.172
B15: 190 | C15: 190 | D15: 100 | E15: 113 | F15: 225 | G15: IP67 | H15: 1х18, 2хРЕ | I15: СS1103 | J15: MBS 20.20.08 | K15: 1603 | L15: U7541202012 | M15: Клеммная коробка ТВ 20.20.12 IP66 USOLA | N15: 1703 | O15: 1577500 | P15: EB Электрошкафчик 300x400x155 RAL7035 | Q15: 63.4 | R15: =Q15*$R$1 -> 4600.938
B16: 230 | C16: 150 | D16: 135 | E16: 153 | F16: 185 | G16: IP67 | H16: 1х26, 2хРЕ | I16: СS1104 | O16: 1578500 | P16: EB Электрошкафчик 300x600x155mm RAL7035 | Q16: 80.22 | R16: =Q16*$R$1 -> 5821.5654
B17: 250 | C17: 250 | D17: 120 | E17: 173 | F17: 285 | G17: IP67 | H17: 1х22 | I17: СS1105 | O17: 1579500 | P17: EB Электрошкафчик 300x800x155mm RAL7035 | Q17: 109.15 | R17: =Q17*$R$1 -> 7921.0155
B18: 260 | C18: 260 | D18: 150 | E18: 183 | F18: 295 | G18: IP67 | H18: 1х30 | I18: СS1106
B19: 310 | C19: 310 | D19: 200 | E19: 233 | F19: 345 | G19: IP67 | H19: 1х32, 4хРЕ | I19: СS1107 | J19: MBS 30.30.12 | K19: 2817 | L19: U7541303012 | M19: Клеммная коробка ТВ 30.30.12 IP66 USOLA | N19: 2310
B20: 480 | C20: 480 | D20: 200 | E20: 403 | F20: 515 | G20: IP67 | H20: 1х66, 1х59, 5хРЕ | I20: СS1108 | J20: MBS 40.40.12 | K20: 4277
B22: 120 | C22: 120 | D22: 80 | E22: - | F22: 155 | G22: IP67 | H22: 1х11 | I22: СS2101 | J22: SBS 12.12.06 | K22: 4813
B23: 150 | C23: 150 | D23: 90 | E23: 73 | F23: 185 | G23: IP67 | H23: 1х14 | I23: СS2102 | J23: SBS 15.15.08 | K23: 5438 | L23: U7592151508 | M23: Клеммная коробка ТВ 15.15.08 из нержавеющей стали IP 66 USOLA | N23: 4565
B24: 190 | C24: 190 | D24: 100 | E24: 113 | F24: 225 | G24: IP67 | H24: 1х18, 2хРЕ | I24: СS2103 | J24: SBS 20.20.08 | K24: 6475 | L24: U7592202008 | M24: Клеммная коробка ТВ 20.20.08 из нержавеющей стали IP 66 USOLA | N24: 5555
B25: 230 | C25: 150 | D25: 135 | E25: 153 | F25: 185 | G25: IP67 | H25: 1х26, 2хРЕ | I25: СS2104
B26: 250 | C26: 250 | D26: 120 | E26: 173 | F26: 285 | G26: IP67 | H26: 1х22 | I26: СS2105
B27: 260 | C27: 260 | D27: 150 | E27: 183 | F27: 295 | G27: IP67 | H27: 1х30 | I27: СS2106
B28: 310 | C28: 310 | D28: 200 | E28: 233 | F28: 345 | G28: IP67 | H28: 1х32, 4хРЕ | I28: СS2107 | J28: SBS 30.30.12 | K28: 9508
B29: 480 | C29: 480 | D29: 200 | E29: 403 | F29: 515 | G29: IP67 | H29: 1х66, 1х59, 5хРЕ | I29: СS2108
J31: MES 20.20.08 | K31: 2445 | L31: U7521202020 | M31: Корпус UC2 20.20.20 IP66 USOLA | N31: 2158
J33: MES 30.20.12 | K33: 2596 | L33: U7521203020 | M33: Корпус UC2 20.30.20 IP66 USOLA | N33: 2202
J34: MES 30.20.15 | K34: 3055 | L34: U7521253015 | M34: Корпус UC2 25.30.15 IP66 USOLA | N34: 2269
J35: MES 30.30.12 | K35: 2892 | L35: U7521253020 | M35: Корпус UC2 25.30.20 IP66 USOLA | N35: 2315
L36: U7521253025 | M36: Корпус UC2 25.30.25 IP66 USOLA | N36: 2379
J37: MES 30.40.15 | K37: 3487 | L37: U7521253515 | M37: Корпус UC2 25.35.15 IP66 USOLA | N37: 2367
J38: MES 40.30.12 | K38: 3588 | L38: U7521253520 | M38: Корпус UC2 25.35.20 IP66 USOLA | N38: 2423
J39: MES 40.30.15 | K39: 3552 | L39: U7521253525 | M39: Корпус UC2 25.35.25 IP66 USOLA | N39: 2477
J40: MES 40.30.21 | K40: 4028 | L40: U7521254015 | M40: Корпус UC2 25.40.15 IP66 USOLA | N40: 2465
J41: MES 40.40.21 | K41: 4417 | L41: U7521254020 | M41: Корпус UC2 25.40.20 IP66 USOLA | N41: 2536
J42: MES 40.60.21 | K42: 5296 | L42: U7521254025 | M42: Корпус UC2 25.40.25 IP66 USOLA | N42: 2588
J43: MES 50.30.21 | K43: 4782 | L43: U7521302015 | M43: Корпус UC2 30.20.15 IP66 USOLA | N43: 2644
J44: MES 50.40.21 | K44: 5078 | L44: U7521302020 | M44: Корпус UC2 30.20.20 IP66 USOLA | N44: 2746
J45: MES 50.40.25 | K45: 5543 | L45: U7521302025 | M45: Корпус UC2 30.20.25 IP66 USOLA | N45: 2841
L46: U7521303015 | M46: Корпус UC2 30.30.15 IP66 USOLA | N46: 2970
J47: MBS 10.10.06 | K47: 1035
J48: MBS 10.15.06 | K48: 1129 | L48: U7521303025 | M48: Корпус UC2 30.30.25 IP66 USOLA | N48: 3029
L49: U7521303515 | M49: Корпус UC2 30.35.15 IP66 USOLA | N49: 3041
J50: MBS 15.15.06 | K50: 1210 | L50: U7521303520 | M50: Корпус UC2 30.35.20 IP66 USOLA | N50: 3078
L51: U7521303525 | M51: Корпус UC2 30.35.25 IP66 USOLA | N51: 3151
J52: MBS 15.15.12 | K52: 1782 | L52: U7521304015 | M52: Корпус UC2 30.40.15 IP66 USOLA | N52: 3264
J53: MBS 15.20.08 | K53: 1583 | L53: U7521304020 | M53: Корпус UC2 30.40.20 IP66 USOLA | N53: 3078
J54: MBS 15.20.12 | K54: 1958 | L54: U7521304025 | M54: Корпус UC2 30.40.25 IP66 USOLA | N54: 3103
J55: MBS 15.30.08 | K55: 1814 | L55: U7521403015 | M55: Корпус UC2 40.30.15 IP66 USOLA | N55: 3049
J56: MBS 15.30.12 | K56: 2306 | L56: U7521403020 | M56: Корпус UC2 40.30.20 IP66 USOLA | N56: 3457
L57: U7521403025 | M57: Корпус UC2 40.30.25 IP66 USOLA | N57: 3491
J58: MBS 20.20.12 | K58: 2049 | L58: U7521403515 | M58: Корпус UC2 40.35.15 IP66 USOLA | N58: 3459
J59: MBS 20.30.08 | K59: 1738 | L59: U7521403520 | M59: Корпус UC2 40.35.20 IP66 USOLA | N59: 3565
J60: MBS 20.30.12 | K60: 2306 | L60: U7521403525 | M60: Корпус UC2 40.35.25 IP66 USOLA | N60: 3641
J61: MBS 20.40.08 | K61: 2231 | L61: U7521404015 | M61: Корпус UC2 40.40.15 IP66 USOLA | N61: 3517
J62: MBS 20.40.12 | K62: 2632 | L62: U7521404020 | M62: Корпус UC2 40.40.20 IP66 USOLA | N62: 3791
J63: MBS 30.30.08 | K63: 2022 | L63: U7521404025 | M63: Корпус UC2 40.40.25 IP66 USOLA | N63: 3957
L64: U7521406015 | M64: Корпус UC2 40.60.15 IP66 USOLA | N64: 4444
J65: MBS 30.40.08 | K65: 2417 | L65: U7521406020 | M65: Корпус UC2 40.60.20 IP66 USOLA | N65: 4547
J66: MBS 30.40.12 | K66: 3191 | L66: U7521406025 | M66: Корпус UC2 40.60.25 IP66 USOLA | N66: 4616
J67: MBS 30.60.08 | K67: 2971 | L67: U7521453015 | M67: Корпус UC2 45.30.15 IP66 USOLA | N67: 3565
J68: MBS 30.60.12 | K68: 4510 | L68: U7521453020 | M68: Корпус UC2 45.30.20 IP66 USOLA | N68: 3780
L69: U7521453025 | M69: Корпус UC2 45.30.25 IP66 USOLA | N69: 3994
J70: MBS 40.60.12 | K70: 5272 | L70: U7521453515 | M70: Корпус UC2 45.35.15 IP66 USOLA | N70: 3753
J71: MBS 40.80.12 | K71: 6239 | L71: U7521453520 | M71: Корпус UC2 45.35.20 IP66 USOLA | N71: 3820
L72: U7521453525 | M72: Корпус UC2 45.35.25 IP66 USOLA | N72: 3901
J73: SES 100.80.30 | K73: 44395 | L73: U7521454015 | M73: Корпус UC2 45.40.15 IP66 USOLA | N73: 3927
J74: SES 120.80.30 | K74: 51024 | L74: U7521454020 | M74: Корпус UC2 45.40.20 IP66 USOLA | N74: 4039
L75: U7521454025 | M75: Корпус UC2 45.40.25 IP66 USOLA | N75: 4148
L76: U7521503015 | M76: Корпус UC2 50.30.15 IP66 USOLA | N76: 4074
J77: SES 40.30.15 | K77: 12334 | L77: U7521503020 | M77: Корпус UC2 50.30.20 IP66 USOLA | N77: 4106
J78: SES 40.40.21 | K78: 14689 | L78: U7521503025 | M78: Корпус UC2 50.30.25 IP66 USOLA | N78: 4149
J79: SES 50.40.21 | K79: 17178 | L79: U7521503515 | M79: Корпус UC2 50.35.15 IP66 USOLA | N79: 4215
L80: U7521503520 | M80: Корпус UC2 50.35.20 IP66 USOLA | N80: 4292
J81: SES 60.40.21 | K81: 18357 | L81: U7521503525 | M81: Корпус UC2 50.35.25 IP66 USOLA | N81: 4335
J82: SES 60.60.25 | K82: 26052 | L82: U7521504015 | M82: Корпус UC2 50.40.15 IP66 USOLA | N82: 4261
J83: SES 70.50.25 | K83: 25563 | L83: U7521504020 | M83: Корпус UC2 50.40.20 IP66 USOLA | N83: 4360
J84: SES 80.60.30 | K84: 32772 | L84: U7521504025 | M84: Корпус UC2 50.40.25 IP66 USOLA | N84: 4759
L85: U7521504040 | M85: Корпус UC2 50.40.40 IP66 USOLA | N85: 5129
J86: SBS 15.30.08 | K86: 6556 | L86: U7521505015 | M86: Корпус UC2 50.50.15 IP66 USOLA | N86: 4769
J88: SBS 20.30.08 | K88: 7405 | L88: U7521505025 | M88: Корпус UC2 50.50.25 IP66 USOLA | N88: 5022
J90: SBS 30.40.12 | K90: 12059 | L90: U7541101006 | M90: Клеммная коробка ТВ 10.10.06 IP66 USOLA | N90: 835
L91: U7541101506 | M91: Клеммная коробка ТВ 10.15.06 IP66 USOLA | N91: 928
L93: U7541151506 | M93: Клеммная коробка ТВ 15.15.06 IP66 USOLA | N93: 1012
L94: U7541151508 | M94: Клеммная коробка ТВ 15.15.08 IP66 USOLA | N94: 1117
L96: U7541152008 | M96: Клеммная коробка ТВ 15.20.08 IP66 USOLA | N96: 1308
L97: U7541152012 | M97: Клеммная коробка ТВ 15.20.12 IP66 USOLA | N97: 1639
L98: U7541152508 | M98: Клеммная коробка ТВ 15.25.08 IP66 USOLA | N98: 1430
L99: U7541153008 | M99: Клеммная коробка ТВ 15.30.08 IP66 USOLA | N99: 1485
L100: U7541153012 | M100: Клеммная коробка ТВ 15.30.12 IP66 USOLA | N100: 1925
L101: U7541154012 | M101: Клеммная коробка ТВ 15.40.12 IP66 USOLA | N101: 2151
L102: U7541202008 | M102: Клеммная коробка ТВ 20.20.08 IP66 USOLA | N102: 1293
L104: U7541203008 | M104: Клеммная коробка ТВ 20.30.08 IP66 USOLA | N104: 1414
L105: U7541203012 | M105: Клеммная коробка ТВ 20.30.12 IP66 USOLA | N105: 1918
... L121: U7541408012 | M121: Клеммная коробка ТВ 40.80.12 IP66 USOLA | N121: 4923
M123: Шкафы UC2 из нержавеющей стали
L124: U7582106030 | M124: Корпус UC2 100.60.30 из нержавеющей стали IP66 USOLA | N124: 33000
...

Sheet Лист2
B2: AE Щит с монтажной панелью ЩМП 600x600x210 мм IP66 (1060500) | D2: 1060500 | E2: RITTAL/AE | F2: 6+ | G2: В течение 2 дн. | H2: 7,110.80 | I2: 8,794.00 | N2: Е1001
B3: AE Щит с монтажной панелью ЩМП 380x380x210 мм IP66 (1380500) | D3: 1380500 | E3: RITTAL/AE | F3: 5+ | G3: В течение 2 дн. | H3: 4,444.07 | I3: 5,496.00 | N3: 300 | O3: 250 | P3: 150 | Q3: 235 | R3: 186 | S3: 239 | T3: 210 | U3: 189 | V3: 160 | W3: IP67 | X3: 1 | Y3: SE1002
N4: 300 | O4: 300 | P4: 150 | Q4: 235 | R4: 236 | S4: 239 | T4: 210 | U4: 239 | V4: 210 | W4: IP67 | X4: 1 | Y4: SE1003
B5: AE Щит с монтажной панелью ЩМП 300x400x210 мм IP66 (1034500) | D5: 1034500 | E5: RITTAL/AE | F5: 4 | G5: В течение 2 дн. | H5: 4,462.64 | I5: 5,519.00 | N5: 300 | O5: 400 | P5: 150 | Q5: 235 | R5: 336 | S5: 239 | T5: 210 | U5: 339 | V5: 310 | W5: IP67 | X5: 1 | Y5: SE1004
N6: 300 | O6: 400 | P6: 200 | Q6: 235 | R6: 336 | S6: 239 | T6: 210 | U6: 339 | V6: 310 | W6: IP67 | X6: 1 | Y6: SE1005
B7: AE Щит с монтажной панелью ЩМП 600x800x250 мм IP66 (1058500) | D7: 1058500 | E7: RITTAL/AE | F7: 4+ | G7: В течение 2 дн. | H7: 10,821.92 | I7: 13,383.00 | N7: 400 | O7: 300 | P7: 150 | Q7: 335 | R7: 236 | S7: 339 | T7: 310 | U7: 239 | V7: 210 | W7: IP67 | X7: 1 | Y7: SE1006
N8: 400 | O8: 300 | P8: 200 | Q8: 335 | R8: 236 | S8: 339 | T8: 310 | U8: 239 | V8: 210 | W8: IP67 | X8: 1 | Y8: SE1007
B9: AE Щит с монтажной панелью ЩМП 600x1000x250 мм IP66 (1090500) | D9: 1090500 | E9: RITTAL/AE | F9: 3+ | G9: В течение 2 дн. | H9: 12,357.09 | I9: 15,282.00 | N9: 400 | O9: 400 | P9: 200 | Q9: 335 | R9: 336 | S9: 339 | T9: 310 | U9: 339 | V9: 310 | W9: IP67 | X9: 1 | Y9: SE1008
N10: 400 | O10: 600 | P10: 200 | Q10: 335 | R10: 536 | S10: 339 | T10: 310 | U10: 539 | V10: 510 | W10: IP67 | X10: 1 | Y10: SE1009
B11: AE Щит с монтажной панелью ЩМП 400x500x210 мм IP66 (1045500) | D11: 1045500 | E11: RITTAL/AE | F11: 2+ | G11: В течение 2 дн. | H11: 5,138.43 | I11: 6,355.00 | N11: 500 | O11: 300 | P11: 150 | Q11: 435 | R11: 236 | S11: 439 | T11: 410 | U11: 239 | V11: 210 | W11: IP67 | X11: 2 | Y11: SE1010
N12: 500 | O12: 300 | P12: 200 | Q12: 435 | R12: 236 | S12: 439 | T12: 410 | U12: 239 | V12: 210 | W12: IP67 | X12: 2 | Y12: SE1011
B13: AE Щит с монтажной панелью ЩМП 600x600x350 мм IP66 (1360500) | D13: 1360500 | E13: RITTAL/AE | F13: 2+ | G13: В течение 2 дн. | H13: 10,846.93 | I13: 13,414.00 | N13: 500 | O13: 400 | P13: 200 | Q13: 435 | R13: 336 | S13: 439 | T13: 410 | U13: 339 | V13: 310 | W13: IP67 | X13: 2 | Y13: SE1012
N14: 500 | O14: 500 | P14: 200 | Q14: 435 | R14: 436 | S14: 439 | T14: 410 | U14: 439 | V14: 410 | W14: IP67 | X14: 2 | Y14: SE1013
B15: AE Щит с монтажной панелью ЩМП 800x1000x300 мм IP66 (1180500) | D15: 1180500 | E15: RITTAL/AE | F15: 1+ | G15: В течение 2 дн. | H15: 14,188.72 | I15: 17,547.00 | N15: 500 | O15: 600 | P15: 200 | Q15: 435 | R15: 536 | S15: 439 | T15: 410 | U15: 539 | V15: 510 | W15: IP67 | X15: 2 | Y15: SE1014
N16: 500 | O16: 400 | P16: 250 | Q16: 435 | R16: 336 | S16: 439 | T16: 410 | U16: 339 | V16: 310 | W16: IP67 | X16: 2 | Y16: SE1015
B17: AE Щит с монтажной панелью ЩМП 500х700х250мм IP66 (1057500) | D17: 1057500 | E17: RITTAL/AE | F17: 1+ | G17: В течение 2 дн. | H17: 8,067.46 | I17: 11,105.00 | N17: 500 | O17: 500 | P17: 300 | Q17: 435 | R17: 436 | S17: 439 | T17: 410 | U17: 439 | V17: 410 | W17: IP67 | X17: 2 | Y17: SE1016
N18: 500 | O18: 600 | P18: 300 | Q18: 435 | R18: 536 | S18: 439 | T18: 410 | U18: 539 | V18: 510 | W18: IP67 | X18: 2 | Y18: SE1017
B19: AE Щит с монтажной панелью ЩМП 500х700х250мм IP66 (1057500) | D19: 1057500 | E19: RITTAL/AE | F19: 1+ | G19: В течение 2 дн. | H19: 8,979.58 | I19: 11,105.00 | N19: 600 | O19: 400 | P19: 200 | Q19: 535 | R19: 336 | S19: 539 | T19: 510 | U19: 339 | V19: 310 | W19: IP67 | X19: 2 | Y19: SE1018
N20: 600 | O20: 500 | P20: 200 | Q20: 535 | R20: 436 | S20: 539 | T20: 510 | U20: 439 | V20: 410 | W20: IP67 | X20: 2 | Y20: SE1019
B21: AE Щит с монтажной панелью ЩМП 380x600x210 мм IP66 (1038500) | D21: 1038500 | E21: RITTAL/AE | F21: 1 | G21: В течение 2 дн. | H21: 5,452.04 | I21: 6,742.00 | N21: 600 | O21: 400 | P21: 250 | Q21: 535 | R21: 336 | S21: 539 | T21: 510 | U21: 339 | V21: 310 | W21: IP67 | X21: 2 | Y21: SE1020
N22: 600 | O22: 600 | P22: 250 | Q22: 535 | R22: 536 | S22: 539 | T22: 510 | U22: 539 | V22: 510 | W22: IP67 | X22: 2 | Y22: SE1021
B23: AE Шкаф однодверный 600x1200x300мм RAL7035 (1260500) | D23: 1260500 | E23: RITTAL/AE | F23: 1+ | G23: В течение 2 дн. | H23: 15,772.47 | I23: 19,506.00 | N23: 600 | O23: 400 | P23: 400 | Q23: 535 | R23: 336 | S23: 539 | T23: 510 | U23: 339 | V23: 310 | W23: IP67 | X23: 2 | Y23: SE1022
N24: 600 | O24: 600 | P24: 400 | Q24: 535 | R24: 536 | S24: 539 | T24: 510 | U24: 539 | V24: 510 | W24: IP67 | X24: 2 | Y24: SE1023
B25: AE Шкаф 600x380x210мм с монтажной платой RAL7035 (1039500) | D25: 1039500 | E25: RITTAL/AE | F25: 1+ | G25: В течение 2 дн. | H25: 5,870.65 | I25: 7,260.00 | N25: 700 | O25: 500 | P25: 200 | Q25: 635 | R25: 436 | S25: 639 | T25: 610 | U25: 439 | V25: 410 | W25: IP67 | X25: 2 | Y25: SE1024
N26: 700 | O26: 500 | P26: 250 | Q26: 635 | R26: 436 | S26: 639 | T26: 610 | U26: 439 | V26: 410 | W26: IP67 | X26: 2 | Y26: SE1025
B27: Шарнир двери 180град д/AE 2шт (2449000) | D27: 2449000 | E27: RITTAL/AE | F27: 1+ | G27: В течение 2 дн. | H27: 1,116.55 | I27: 1,381.00 | N27: 800 | O27: 600 | P27: 200 | Q27: 735 | R27: 536 | S27: 739 | T27: 710 | U27: 539 | V27: 510 | W27: IP67 | X27: 2 | Y27: SE1026
N28: 800 | O28: 800 | P28: 200 | Q28: 735 | R28: 736 | S28: 739 | T28: 710 | U28: 739 | V28: 710 | W28: IP67 | X28: 2 | Y28: SE1027
B29: AE Шкаф 1000x1200x300мм с монтажной платой нержавеющая сталь (1019600) | D29: 1019600 | E29: RITTAL/AE | F29: 1 | G29: В течение 2 дн. | H29: 60,625.26 | I29: 83,451.00 | N29: 800 | O29: 600 | P29: 250 | Q29: 735 | R29: 536 | S29: 739 | T29: 710 | U29: 539 | V29: 510 | W29: IP67 | X29: 2 | Y29: SE1028
N30: 800 | O30: 600 | P30: 300 | Q30: 735 | R30: 536 | S30: 739 | T30: 710 | U30: 539 | V30: 510 | W30: IP67 | X30: 2 | Y30: SE1029
B31: AE Шкаф 1000x1200x300мм с монтажной платой нержавеющая сталь (1019600) | D31: 1019600 | E31: RITTAL/AE | F31: 1 | G31: В течение 2 дн. | H31: 67,479.62 | I31: 83,451.00 | N31: 800 | O31: 800 | P31: 300 | Q31: 735 | R31: 736 | S31: 739 | T31: 710 | U31: 739 | V31: 710 | W31: IP67 | X31: 2 | Y31: SE1030
N32: 800 | O32: 600 | P32: 400 | Q32: 735 | R32: 536 | S32: 739 | T32: 710 | U32: 539 | V32: 510 | W32: IP67 | X32: 2 | Y32: SE1031
B33: AE Щит с монтажной панелью ЩМП 200х300х155 мм IP66 (1035500) | D33: 1035500 | E33: RITTAL/AE | F33: Уточнить | G33: Уточнить | H33: 3,126.06 | I33: 3,866.00 | N33: 800 | O33: 800 | P33: 400 | Q33: 735 | R33: 736 | S33: 739 | T33: 710 | U33: 739 | V33: 710 | W33: IP67 | X33: 2 | Y33: SE1032
N34: 1000 | O34: 600 | P34: 250 | Q34: 935 | R34: 536 | S34: 939 | T34: 910 | U34: 539 | V34: 510 | W34: IP66 | X34: 2 | Y34: SE1033
B35: AE Шкаф 500x500x300мм с монтажной платой RAL7035 (1350500) | D35: 1350500 | E35: RITTAL/AE | F35: Уточнить | G35: Уточнить | H35: 8,645.97 | I35: 10,692.00 | N35: 1000 | O35: 600 | P35: 300 | Q35: 935 | R35: 536 | S35: 939 | T35: 910 | U35: 539 | V35: 510 | W35: IP66 | X35: 2 | Y35: SE1034
N36: 1000 | O36: 800 | P36: 300 | Q36: 935 | R36: 736 | S36: 939 | T36: 910 | U36: 739 | V36: 710 | W36: IP66 | X36: 2 | Y36: SE1035
B37: CM Компактн распред.шкаф 1000x1400x400mm (5122500) | D37: 5122500 | E37: RITTAL/CM | F37: Уточнить | G37: Уточнить | H37: 39,931.58 | I37: 49,383.00 | N37: 1000 | O37: 600 | P37: 400 | Q37: 935 | R37: 536 | S37: 939 | T37: 910 | U37: 539 | V37: 510 | W37: IP66 | X37: 2 | Y37: SE1036
N38: 1000 | O38: 800 | P38: 400 | Q38: 935 | R38: 736 | S38: 939 | T38: 910 | U38: 739 | V38: 710 | W38: IP66 | X38: 2 | Y38: SE1037
B39: AE Шкаф 300x300x210мм с монтажной платой RAL7035 (1033500) | D39: 1033500 | E39: RITTAL/AE | F39: Уточнить | G39: Уточнить | H39: 4,100.46 | I39: 5,071.00 | N39: 1200 | O39: 600 | P39: 200 | Q39: 1135 | R39: 536 | S39: 1139 | T39: 1110 | U39: 539 | V39: 510 | W39: IP66 | X39: 2 | Y39: SE1038
N40: 1200 | O40: 600 | P40: 300 | Q40: 1135 | R40: 536 | S40: 1139 | T40: 1110 | U40: 539 | V40: 510 | W40: IP66 | X40: 2 | Y40: SE1039
B41: AE Шкаф 380x600x350мм с монтажной платой RAL7035 (1338500) | D41: 1338500 | E41: RITTAL/AE | F41: Уточнить | G41: Уточнить | H41: 9,276.75 | I41: 11,472.00 | N41: 1200 | O41: 800 | P41: 300 | Q41: 1135 | R41: 736 | S41: 1139 | T41: 1110 | U41: 739 | V41: 710 | W41: IP66 | X41: 2 | Y41: SE1040
N42: 1200 | O42: 600 | P42: 400 | Q42: 1135 | R42: 536 | S42: 1139 | T42: 1110 | U42: 539 | V42: 510 | W42: IP66 | X42: 2 | Y42: SE1041
B43: AE Шкаф однодверный 500x500x210мм RAL7035 (1050500) | D43: 1050500 | E43: RITTAL/AE | F43: Уточнить | G43: Уточнить | H43: 6,244.97 | I43: 7,723.00 | N43: 1200 | O43: 800 | P43: 400 | Q43: 1135 | R43: 736 | S43: 1139 | T43: 1110 | U43: 739 | V43: 710 | W43: IP66 | X43: 2 | Y43: SE1042
N44: 1400 | O44: 600 | P44: 300 | Q44: 1335 | R44: 536 | S44: 1339 | T44: 1310 | U44: 539 | V44: 510 | W44: IP66 | X44: 2 | Y44: SE1043
B45: AE Шкаф 600x760x210мм с монтажной платой RAL7035 (1076500) | D45: 1076500 | E45: RITTAL/AE | F45: Уточнить | G45: Уточнить | H45: 9,051.72 | I45: 11,194.00 | N45: 1400 | O45: 800 | P45: 300 | Q45: 1335 | R45: 736 | S45: 1339 | T45: 1310 | U45: 739 | V45: 710 | W45: IP66 | X45: 2 | Y45: SE1044
B47: AE Шкаф распределительный 400x800x300мм RAL7035 (1037500) | D47: 1037500 | E47: RITTAL/AE | F47: Уточнить | G47: Уточнить | H47: 11,762.74 | I47: 14,547.00
B49: AE Щит с монтажной панелью ЩМП 800x1200x300 мм IP66 (1280500) | D49: 1280500 | E49: RITTAL/AE | F49: Уточнить | G49: Уточнить | H49: 18,064.16 | I49: 22,340.00
B51: AE Щит с монтажной панелью ЩМП 300x300x155мм IP66 (1036500) | D51: 1036500 | E51: RITTAL/AE | F51: Уточнить | G51: Уточнить | H51: 3,983.30 | I51: 4,926.00
B53: AE Шкаф 200x300x120мм с монтажной платой нержавеющая сталь (1001600) | D53: 1001600 | E53: RITTAL/AE | F53: Уточнить | G53: Уточнить | H53: 10,123.99 | I53: 12,520.00
B55: AE Шкаф 380x300x210мм с монтажной платой нержавеющая сталь (1011600) | D55: 1011600 | E55: RITTAL/AE | F55: Уточнить | G55: Уточнить | H55: 13,862.26 | I55: 17,143.00
B57: CM Компактн распред.шкаф 1200x1200x400mm (5123500) | D57: 5123500 | E57: RITTAL/CM | F57: Уточнить | G57: Уточнить | H57: 35,171.76 | I57: 43,496.00
B59: AE Шкаф 600x760x350мм с монтажной платой RAL7035 (1376500) | D59: 1376500 | E59: RITTAL/AE | F59: Уточнить | G59: Уточнить | H59: 12,832.15 | I59: 15,869.00
B61: AE Шкаф 760x760x300мм с монтажной платой RAL7035 (1073500) | D61: 1073500 | E61: RITTAL/AE | F61: Уточнить | G61: Уточнить | H61: 12,529.97 | I61: 15,496.00
B63: CM Шкаф распределительный компактный 800x1200x400 мм (5117500) | D63: 5117500 | E63: RITTAL/CM | F63: Уточнить | G63: Уточнить | H63: 26,379.36 | I63: 32,623.00
B65: AE Шкаф распределительный 600x600x250мм RAL7035 (1054500) | D65: 1054500 | E65: RITTAL/AE | F65: Уточнить | G65: Уточнить | H65: 9,140.30 | I65: 11,304.00
B67: AE Шкаф 760x760x300мм с монтажной платой нержавеющая сталь (1014600) | D67: 1014600 | E67: RITTAL/AE | F67: Уточнить | G67: Уточнить | H67: 41,717.48 | I67: 51,591.00
B69: AE Шкаф 800x1000x300мм с монтажной платой нержавеющая сталь (1016600) | D69: 1016600 | E69: RITTAL/AE | F69: Уточнить | G69: Уточнить | H69: 47,394.55 | I69: 58,612.00
... B111: AE Шкаф 380x380x210мм RAL7035 без монтажной платы (1380510) | D111: 1380510 | E111: RITTAL/AE | F111: Уточнить | G111: Уточнить | H111: 4,120.47 | I111: 5,096.00
B113: AE Шкаф EMV 600x380x210мм RAL7035 с монтажной платой (1039750) | D113: 1039750 | E113: RITTAL/AE | F113: Уточнить | G113: Уточнить | H113: н/д
B115: AE Шкаф распределительный окрашенный 600x600x210мм (1060502) | D115: 1060502 | E115: RITTAL/AE | F115: Уточнить | G115: Уточнить | H115: 6,305.70 | I115: 7,798.00
B117: CM Компактный распред.шкаф 600x800x400mm (5110800) | D117: 5110800 | E117: RITTAL/CM | F117: Уточнить | G117: Уточнить | H117: 15,543.87 | I117: 19,223.00
B118: CM Компактн распред.шкаф 1000x1200x300mm (5119500) | D118: 5119500 | E118: RITTAL/CM | F118: Уточнить | G118: Уточнить | H118: 27,000.13 | I118: 33,391.00
B120: CM Компактн распред.шкаф 1200x1200x400mm (5123800) | D120: 5123800 | E120: RITTAL/CM | F120: Уточнить | G120: Уточнить | H120: 34,668.13 | I120: 42,873.00
B121: AE Шкаф распределительный 800x1200x300мм без монтажной платы (1280510) | D121: 1280510 | E121: RITTAL/AE | F121: Уточнить | G121: Уточнить | H121: 16,413.25 | I121: 20,298.00
B123: AE Шкаф распределительный грунтованный 300x300x210мм (1033800) | D123: 1033800 | E123: RITTAL/AE | F123: Уточнить | G123: Уточнить | H123: 4,054.03 | I123: 5,014.00
B125: AE Шкаф распределительный грунтованный 380x300x210мм (1031800) | D125: 1031800 | E125: RITTAL/AE | F125: Уточнить | G125: Уточнить | H125: 4,144.75 | I125: 5,126.00
B127: AE Шкаф распределительный 1000x760x300мм без монтажной платы (1130510) | D127: 1130510 | E127: RITTAL/AE | F127: Уточнить | G127: Уточнить | H127: 17,634.82 | I127: 21,809.00
B129: AE Шкаф распределительный грунтованный 1000x1000x300мм (1110800) | D129: 1110800 | E129: RITTAL/AE | F129: Уточнить | G129: Уточнить | H129: 19,877.22 | I129: 24,582.00
B131: AE Шкаф распределительный окрашенный 800x1000x300мм (1180502) | D131: 1180502 | E131: RITTAL/AE | F131: Уточнить | G131: Уточнить | H131: 13,760.10 | I131: 17,017.00
B133: AE Шкаф распределительный грунтованный 600x1200x300мм (1260800) | D133: 1260800 | E133: RITTAL/AE | F133: Уточнить | G133: Уточнить | H133: 15,110.25 | I133: 18,687.00
B135: AE Шкаф распределительный 400x500x210мм без монтажной платы (1045510) | D135: 1045510 | E135: RITTAL/AE | F135: Уточнить | G135: Уточнить | H135: 4,769.10 | I135: 5,898.00
B137: AE Шкаф распределительный окрашенный 380x300x155мм (1030502) | D137: 1030502 | E137: RITTAL/AE | F137: Уточнить | G137: Уточнить | H137: 3,474.68 | I137: 4,297.00
B139: HD Системный шкаф 400х1800х500мм нерж.сталь 1.4301 1шт (4000485) | D139: 4000485 | E139: RITTAL/HD | F139: Уточнить | G139: Уточнить | H139: н/д
B140: AE Шкаф распределительный 500x700x250мм без монтажной платы (1057510) | D140: 1057510 | E140: RITTAL/AE | F140: Уточнить | G140: Уточнить | H140: 8,459.51 | I140: 10,462.00
B142: AE Шкаф распределительный грунтованный 800x1000x300мм (1180800) | D142: 1180800 | E142: RITTAL/AE | F142: Уточнить | G142: Уточнить | H142: 14,007.28 | I142: 17,323.00
B144: AE Шкаф 600x380x210мм без монтажной платы нержавеющая сталь (1009010) | D144: 1009010 | E144: RITTAL/AE | F144: Уточнить | G144: Уточнить | H144: н/д
B146: AE Шкаф распределительный грунтованный 600x380x350мм (1339800) | D146: 1339800 | E146: RITTAL/AE | F146: Уточнить | G146: Уточнить | H146: 9,337.47 | I146: 11,547.00
B148: HD Шкаф д/огнетушителя 400х1120х300 нерж.сталь 1.4301 1шт (4000074) | D148: 4000074 | E148: RITTAL/HD | F148: Уточнить | G148: Уточнить | H148: 74,763.84 | I148: 92,459.00
B149: AE Шкаф распределительный грунтованный 1000x1400x300мм (1114800) | D149: 1114800 | E149: RITTAL/AE | F149: Уточнить | G149: Уточнить | H149: 29,330.41 | I149: 36,272.00
B151: AE Шкаф распределительный окрашенный 500x500x300мм (1350502) | D151: 1350502 | E151: RITTAL/AE | F151: Уточнить | G151: Уточнить | H151: 8,428.80 | I151: 10,424.00
B153: AE Шкаф распределительный 760x760x300мм без монтажной платы (1073510) | D153: 1073510 | E153: RITTAL/AE | F153: Уточнить | G153: Уточнить | H153: 11,727.74 | I153: 14,503.00
B155: AE Шкаф 380x600x210мм без монтажной платы нержавеющая сталь (1008010) | D155: 1008010 | E155: RITTAL/AE | F155: Уточнить | G155: Уточнить | H155: н/д
B157: AE Шкаф распределительный 1000x1000x300мм без монтажной платы (1110510) | D157: 1110510 | E157: RITTAL/AE | F157: Уточнить | G157: Уточнить | H157: 18,792.81 | I157: 23,241.00
B159: AE Шкаф распределительный 600x600x350мм без монтажной платы (1360310) | D159: 1360310 | E159: RITTAL/AE | F159: Уточнить | G159: Уточнить | H159: 11,682.73 | I159: 14,448.00
B161: AE Шкаф распределительный 600x1000x250мм без монтажной платы (1090510) | D161: 1090510 | E161: RITTAL/AE | F161: Уточнить | G161: Уточнить | H161: 11,199.10 | I161: 13,850.00
B163: AE Шкаф 760x760x300мм без монтажной платы нержавеющая сталь (1014010) | D163: 1014010 | E163: RITTAL/AE | F163: Уточнить | G163: Уточнить | H163: н/д
B165: CM Компактн. распред.шкаф 800x1000x300mm (5114500) | D165: 5114500 | E165: RITTAL/CM | F165: Уточнить | G165: Уточнить | H165: 19,150.00 | I165: 23,682.00
B167: CM Компактн распред.шкаф 1000x1000x300mm (5118800) | D167: 5118800 | E167: RITTAL/CM | F167: Уточнить | G167: Уточнить | H167: 24,240.55 | I167: 29,978.00
B168: AE Шкаф распределительный 600x380x210мм без монтажной платы (1039512) | D168: 1039512 | E168: RITTAL/AE | F168: Уточнить | G168: Уточнить | H168: 5,259.15 | I168: 6,504.00
B170: CM Компактн. распред.шкаф 600x1000x400mm (5111800) | D170: 5111800 | E170: RITTAL/CM | F170: Уточнить | G170: Уточнить | H170: 18,812.81 | I170: 23,265.00
B171: AE Шкаф распределительный окрашенный 500x500x210мм (1050502) | D171: 1050502 | E171: RITTAL/AE | F171: Уточнить | G171: Уточнить | H171: 5,837.08 | I171: 7,219.00
B173: AE Шкаф распределительный окрашенный 200x300x155мм (1035502) | D173: 1035502 | E173: RITTAL/AE | F173: Уточнить | G173: Уточнить | H173: 3,038.21 | I173: 3,757.00
B175: AE Шкаф распределительный грунтованный 600x760x350мм (1376800) | D175: 1376800 | E175: RITTAL/AE | F175: Уточнить | G175: Уточнить | H175: 12,291.38 | I175: 15,201.00
B177: AE Шкаф распределительный 500x500x210мм без монтажной платы (1050510) | D177: 1050510 | E177: RITTAL/AE | F177: Уточнить | G177: Уточнить | H177: 5,797.79 | I177: 7,170.00
B179: AE Шкаф распределительный 380x300x155мм без монтажной платы (1030312) | D179: 1030312 | E179: RITTAL/AE | F179: Уточнить | G179: Уточнить | H179: 3,113.91 | I179: 3,851.00
B181: AE Шкаф распределительный грунтованный 200x300x120мм (1032800) | D181: 1032800 | E181: RITTAL/AE | F181: Уточнить | G181: Уточнить | H181: 2,743.89 | I181: 3,393.00
B183: AE Шкаф распределительный 600x760x350мм без монтажной платы (1376510) | D183: 1376510 | E183: RITTAL/AE | F183: Уточнить | G183: Уточнить | H183: 11,689.15 | I183: 14,456.00
B185: HD Системный шкаф 1200х1800х500мм нерж.сталь 1.4301 1шт (4000285) | D185: 4000285 | E185: RITTAL/HD | F185: Уточнить | G185: Уточнить | H185: Свяжитесь с нами | I185: 381,032.00
B186: AE Шкаф распределительный грунтованный 380x600x350мм (1338800) | D186: 1338800 | E186: RITTAL/AE | F186: Уточнить | G186: Уточнить | H186: 8,923.84 | I186: 11,036.00
B188: Ключи с замком VW-E1 (2532002) | D188: 2532002 | E188: RITTAL | F188: Не поставляется | G188: Не поставляется | I188: 1,350.00
B189: Холодильный агрегат арт.3329500 c обработкой для химических сред (3329509 (3329509/11747798/10) | D189: 3329509/11747798/10 | E189: RITTAL | F189: Не поставляется | G189: Не поставляется | I189: 291,656.00
...

Sheet SE3000(нерж316)
J1: Rittal | M1: 72.55
B2: IPEX | H2: Площадь поверхности | I2: себестоимость | N2: Цена в Электрокомплект на 11.07.18 | Q2: ДКС | W2: стоимость м2 | X2: Расчитанная стоимость м2 | Y2: Вычисленная цена | Z2: цена со скидкой | AA2: Прайсовая цена
B3: 300 | C3: 200 | D3: 150 | E3: IP67 | F3: 1 | G3: SЕ2001 | H3: =2*(B3*C3+C3*D3+B3*D3)/1000000 -> 0.27 | I3: 6459.237 | J3: 1002500 | K3: AE Шкаф, нерж.сталь с МП 200x300x155mm | L3: 277.65 | M3: =L3*$M$1 -> 20143.507 | N3: 18 102.04 | O3: 18,675.65 | P3: 23,096.00 | W3: =T3/H3 -> 0 | X3: 35948.292 | Y3: =X3*H3 -> 9706.0387 | Z3: =Y3*0.95 -> 9220.7368 | AA3: =ROUND(Z3,0) -> 9221
B4: 300 | C4: 250 | D4: 150 | E4: IP67 | F4: 1 | G4: SE2002 | H4: =2*(B4*C4+C4*D4+B4*D4)/1000000 -> 0.315 | M4: =L4*$M$1 -> 0 | Q4: R5CEB03912 | R4: Навесной шкаф CE из нержавеющей стали (AISI 316), 300 x 250x 150мм, без фланца | S4: 20632.7 | T4: 14442.51 | U4: 14,443.09 | V4: 18,713.00 | W4: =T4/H4 -> 45849.238 | X4: 45849.238 | Y4: =X4*H4 -> 14442.51 | Z4: =Y4*0.95 -> 13720.385 | AA4: =ROUND(Z4,0) -> 13720
B5: 300 | C5: 300 | D5: 150 | E5: IP67 | F5: 1 | G5: SE2003 | H5: =2*(B5*C5+C5*D5+B5*D5)/1000000 -> 0.36 | M5: =L5*$M$1 -> 0 | Q5: R5CEB03312 | R5: Навесной шкаф CE из нержавеющей стали (AISI 316), 300 x 300x 150мм, без фланца | S5: 21684.53 | T5: 15178.77 | U5: 15,179.39 | V5: 19,667.00 | W5: =T5/H5 -> 42163.25 | X5: 42163.25 | Y5: =X5*H5 -> 15178.77 | Z5: =Y5*0.95 -> 14419.831 | AA5: =ROUND(Z5,0) -> 14420
B6: 300 | C6: 400 | D6: 150 | E6: IP67 | F6: 1 | G6: SE2004 | H6: =2*(B6*C6+C6*D6+B6*D6)/1000000 -> 0.45 | M6: =L6*$M$1 -> 0 | Q6: R5CEB03412 | R6: Навесной шкаф CE из нержавеющей стали (AISI 316), 300 x 400x 150мм, без фланца | S6: 23771.11 | T6: 16639.35 | W6: =T6/H6 -> 36976.333 | X6: 36976.333 | Y6: =X6*H6 -> 16639.35 | Z6: =Y6*0.95 -> 15807.382 | AA6: =ROUND(Z6,0) -> 15807
B7: 300 | C7: 400 | D7: 200 | E7: IP67 | F7: 1 | G7: SE2005 | H7: =2*(B7*C7+C7*D7+B7*D7)/1000000 -> 0.52 | M7: =L7*$M$1 -> 0 | W7: =T7/H7 -> 0 | X7: 37600.808 | Y7: =X7*H7 -> 19552.42 | Z7: =Y7*0.95 -> 18574.799 | AA7: =ROUND(Z7,0) -> 18575
B8: 400 | C8: 300 | D8: 150 | E8: IP67 | F8: 1 | G8: SE2006 | H8: =2*(B8*C8+C8*D8+B8*D8)/1000000 -> 0.45 | M8: =L8*$M$1 -> 0 | Q8: R5CEB04312 | R8: Навесной шкаф CE из нержавеющей стали (AISI 316), 400 x 300x 150мм, без фланца | S8: 23835.21 | T8: 16684.21 | W8: =T8/H8 -> 37076.022 | X8: 36976.333 | Y8: =X8*H8 -> 16639.35 | Z8: =Y8*0.95 -> 15807.382 | AA8: =ROUND(Z8,0) -> 15807
B9: 400 | C9: 300 | D9: 200 | E9: IP67 | F9: 1 | G9: SE2007 | H9: =2*(B9*C9+C9*D9+B9*D9)/1000000 -> 0.52 | J9: 1005500 | K9: AE Шкаф, нерж.сталь с МП 300x380x210mm | L9: 368.71 | M9: =L9*$M$1 -> 26749.91 | N9: 24 038.67 | O9: 24,800.61 | P9: 30,670.00 | Q9: R5CEB04322 | R9: Навесной шкаф CE из нержавеющей стали (AISI 316), 400 x 300x 200мм, без фланца | S9: 27932.76 | T9: 19552.42 | W9: =T9/H9 -> 37600.808 | X9: 37600.808 | Y9: =X9*H9 -> 19552.42 | Z9: =Y9*0.95 -> 18574.799 | AA9: =ROUND(Z9,0) -> 18575
B10: 400 | C10: 400 | D10: 200 | E10: IP67 | F10: 1 | G10: SE2008 | H10: =2*(B10*C10+C10*D10+B10*D10)/1000000 -> 0.64 | J10: 1006500 | K10: AE Шкаф, нерж.сталь с МП 380x380x210mm | L10: 377.42 | M10: =L10*$M$1 -> 27381.821 | N10: 24 606.82 | O10: 25,387.11 | P10: 31,396.00 | Q10: R5CEB04422 | R10: Навесной шкаф CE из нержавеющей стали (AISI 316), 400 x 400x 200мм, без фланца | S10: 31491.77 | T10: 22043.66 | W10: =T10/H10 -> 34443.219 | X10: 34443.219 | Y10: =X10*H10 -> 22043.66 | Z10: =Y10*0.95 -> 20941.477 | AA10: =ROUND(Z10,0) -> 20941
B11: 400 | C11: 600 | D11: 200 | E11: IP67 | F11: 1 | G11: SE2009 | H11: =2*(B11*C11+C11*D11+B11*D11)/1000000 -> 0.88 | M11: =L11*$M$1 -> 0 | Q11: R5CEB04622 | R11: Навесной шкаф CE из нержавеющей стали (AISI 316), 400 x 600x 200мм, без фланца | S11: 37124.4 | T11: 25986.41 | W11: =T11/H11 -> 29530.011 | X11: 29530.011 | Y11: =X11*H11 -> 25986.41 | Z11: =Y11*0.95 -> 24687.089 | AA11: =ROUND(Z11,0) -> 24687
B12: 500 | C12: 300 | D12: 150 | E12: IP67 | F12: 2 | G12: SE2010 | H12: =2*(B12*C12+C12*D12+B12*D12)/1000000 -> 0.54 | M12: =L12*$M$1 -> 0 | Q12: R5CEB05312 | R12: Навесной шкаф CE из нержавеющей стали (AISI 316), 500 x 300x 150мм, без фланца | S12: 26181.97 | T12: 18326.9 | U12: 18,327.64 | V12: 23,746.00 | W12: =T12/H12 -> 33938.704 | X12: 33938.704 | Y12: =X12*H12 -> 18326.9 | Z12: =Y12*0.95 -> 17410.555 | AA12: =ROUND(Z12,0) -> 17411
B13: 500 | C13: 300 | D13: 200 | E13: IP67 | F13: 2 | G13: SE2011 | H13: =2*(B13*C13+C13*D13+B13*D13)/1000000 -> 0.62 | M13: =L13*$M$1 -> 0 | Q13: R5CEB05322 | R13: Навесной шкаф CE из нержавеющей стали (AISI 316), 500 x 300x 200мм, без фланца | S13: 31233.88 | T13: 21863.14 | W13: =T13/H13 -> 35263.129 | X13: 35263.129 | Y13: =X13*H13 -> 21863.14 | Z13: =Y13*0.95 -> 20769.983 | AA13: =ROUND(Z13,0) -> 20770
B14: 500 | C14: 400 | D14: 200 | E14: IP67 | F14: 2 | G14: SE2012 | H14: =2*(B14*C14+C14*D14+B14*D14)/1000000 -> 0.76 | M14: =L14*$M$1 -> 0 | Q14: R5CEB05422 | R14: Навесной шкаф CE из нержавеющей стали (AISI 316), 500 x 400x 200мм, без фланца | S14: 34472.77 | T14: 24130.31 | W14: =T14/H14 -> 31750.408 | X14: 31750.408 | Y14: =X14*H14 -> 24130.31 | Z14: =Y14*0.95 -> 22923.794 | AA14: =ROUND(Z14,0) -> 22924
B15: 500 | C15: 500 | D15: 200 | E15: IP67 | F15: 2 | G15: SE2013 | H15: =2*(B15*C15+C15*D15+B15*D15)/1000000 -> 0.9 | M15: =L15*$M$1 -> 0 | Q15: R5CEB05522 | R15: Навесной шкаф CE из нержавеющей стали (AISI 316), 500 x 500x 200мм, без фланца | S15: 37703.77 | T15: 26391.95 | W15: =T15/H15 -> 29324.389 | X15: 29324.389 | Y15: =X15*H15 -> 26391.95 | Z15: =Y15*0.95 -> 25072.353 | AA15: =ROUND(Z15,0) -> 25072
B16: 500 | C16: 600 | D16: 200 | E16: IP67 | F16: 2 | G16: SE2014 | H16: =2*(B16*C16+C16*D16+B16*D16)/1000000 -> 1.04 | M16: =L16*$M$1 -> 0 | W16: =T16/H16 -> 0 | X16: 31710.959 | Y16: =X16*H16 -> 32979.397 | Z16: =Y16*0.95 -> 31330.428 | AA16: =ROUND(Z16,0) -> 31330
B17: 500 | C17: 400 | D17: 250 | E17: IP67 | F17: 2 | G17: SE2015 | H17: =2*(B17*C17+C17*D17+B17*D17)/1000000 -> 0.85 | M17: =L17*$M$1 -> 0 | Q17: R5CEB05492 | R17: Навесной шкаф CE из нержавеющей стали (AISI 316), 500 x 400x 250мм, без фланца | S17: 39029.01 | T17: 27319.59 | W17: =T17/H17 -> 32140.694 | X17: 32140.694 | Y17: =X17*H17 -> 27319.59 | Z17: =Y17*0.95 -> 25953.61 | AA17: =ROUND(Z17,0) -> 25954
B18: 500 | C18: 500 | D18: 300 | E18: IP67 | F18: 2 | G18: SE2016 | H18: =2*(B18*C18+C18*D18+B18*D18)/1000000 -> 1.1 | M18: =L18*$M$1 -> 0 | W18: =T18/H18 -> 0 | X18: 31341.426 | Y18: =X18*H18 -> 34475.569 | Z18: =Y18*0.95 -> 32751.791 | AA18: =ROUND(Z18,0) -> 32752
B19: 500 | C19: 600 | D19: 300 | E19: IP67 | F19: 2 | G19: SE2017 | H19: =2*(B19*C19+C19*D19+B19*D19)/1000000 -> 1.26 | M19: =L19*$M$1 -> 0 | W19: =T19/H19 -> 0 | X19: 30634.881 | Y19: =X19*H19 -> 38599.95 | Z19: =Y19*0.95 -> 36669.953 | AA19: =ROUND(Z19,0) -> 36670
B20: 600 | C20: 400 | D20: 200 | E20: IP67 | F20: 2 | G20: SE2018 | H20: =2*(B20*C20+C20*D20+B20*D20)/1000000 -> 0.88 | M20: =L20*$M$1 -> 0 | Q20: R5CEB06422 | R20: Навесной шкаф CE из нержавеющей стали (AISI 316), 600 x 400x 200мм, без фланца | S20: 37338.23 | T20: 26136.08 | W20: =T20/H20 -> 29700.091 | X20: 29530.011 | Y20: =X20*H20 -> 25986.41 | Z20: =Y20*0.95 -> 24687.089 | AA20: =ROUND(Z20,0) -> 24687
B21: 600 | C21: 500 | D21: 200 | E21: IP67 | F21: 2 | G21: SE2019 | H21: =2*(B21*C21+C21*D21+B21*D21)/1000000 -> 1.04 | M21: =L21*$M$1 -> 0 | W21: =T21/H21 -> 0 | X21: 31710.959 | Y21: =X21*H21 -> 32979.397 | Z21: =Y21*0.95 -> 31330.428 | AA21: =ROUND(Z21,0) -> 31330
B22: 600 | C22: 400 | D22: 250 | E22: IP67 | F22: 2 | G22: SE2020 | H22: =2*(B22*C22+C22*D22+B22*D22)/1000000 -> 0.98 | I22: 25294.494 | M22: =L22*$M$1 -> 0 | Q22: R5CEB06492 | R22: Навесной шкаф CE из нержавеющей стали (AISI 316), 600 x 400x 250мм, без фланца | S22: 42043.42 | T22: 29429.64 | W22: =T22/H22 -> 30030.245 | X22: 30030.245 | Y22: =X22*H22 -> 29429.64 | Z22: =Y22*0.95 -> 27958.158 | AA22: =ROUND(Z22,0) -> 27958
B23: 600 | C23: 600 | D23: 250 | E23: IP67 | F23: 2 | G23: SE2021 | H23: =2*(B23*C23+C23*D23+B23*D23)/1000000 -> 1.32 | J23: 1010500 | K23: AE Шкаф, нерж.сталь с МП 600x600x210mm | L23: 637.35 | M23: =L23*$M$1 -> 46239.743 | N23: 41 553.59 | O23: 42,871.18 | P23: 53,018.00 | Q23: R5CEB06692 | R23: Навесной шкаф CE из нержавеющей стали (AISI 316), 600 x 600x 250мм, без фланца | S23: 49864.89 | T23: 34904.51 | W23: =T23/H23 -> 26442.811 | X23: 26442.811 | Y23: =X23*H23 -> 34904.51 | Z23: =Y23*0.95 -> 33159.285 | AA23: =ROUND(Z23,0) -> 33159
B24: 600 | C24: 400 | D24: 400 | E24: IP67 | F24: 2 | G24: SE2022 | H24: =2*(B24*C24+C24*D24+B24*D24)/1000000 -> 1.28 | M24: =L24*$M$1 -> 0 | Q24: R5CEB06442 | R24: Навесной шкаф CE из нержавеющей стали (AISI 316), 600 x 400x 400мм, без фланца | S24: 71967.74 | T24: 50376.1 | W24: =T24/H24 -> 39356.328 | X24: 39356.328 | Y24: =X24*H24 -> 50376.1 | Z24: =Y24*0.95 -> 47857.295 | AA24: =ROUND(Z24,0) -> 47857
B25: 600 | C25: 600 | D25: 400 | E25: IP67 | F25: 2 | G25: SE2023 | H25: =2*(B25*C25+C25*D25+B25*D25)/1000000 -> 1.68 | M25: =L25*$M$1 -> 0 | Q25: R5CEB06642 | R25: Навесной шкаф CE из нержавеющей стали (AISI 316), 600 x 600x 400мм, без фланца | S25: 73272.55 | T25: 51289.45 | W25: =T25/H25 -> 30529.435 | X25: 30529.435 | Y25: =X25*H25 -> 51289.45 | Z25: =Y25*0.95 -> 48724.977 | AA25: =ROUND(Z25,0) -> 48725
B26: 700 | C26: 500 | D26: 200 | E26: IP67 | F26: 2 | G26: SE2024 | H26: =2*(B26*C26+C26*D26+B26*D26)/1000000 -> 1.18 | M26: =L26*$M$1 -> 0 | Q26: R5CEB07522 | R26: Навесной шкаф CE из нержавеющей стали (AISI 316), 700 x 500x 200мм, без фланца | S26: 46390.2 | T26: 32472.29 | W26: =T26/H26 -> 27518.89 | X26: 27518.89 | Y26: =X26*H26 -> 32472.29 | Z26: =Y26*0.95 -> 30848.676 | AA26: =ROUND(Z26,0) -> 30849
B27: 700 | C27: 500 | D27: 250 | E27: IP67 | F27: 2 | G27: SE2025 | H27: =2*(B27*C27+C27*D27+B27*D27)/1000000 -> 1.3 | M27: =L27*$M$1 -> 0 | Q27: R5CEB07592 | R27: Навесной шкаф CE из нержавеющей стали (AISI 316), 700 x 500x 250мм, без фланца | S27: 51510.69 | T27: 36056.54 | W27: =T27/H27 -> 27735.8 | X27: 27735.8 | Y27: =X27*H27 -> 36056.54 | Z27: =Y27*0.95 -> 34253.713 | AA27: =ROUND(Z27,0) -> 34254
B28: 800 | C28: 600 | D28: 200 | E28: IP67 | F28: 2 | G28: SE2026 | H28: =2*(B28*C28+C28*D28+B28*D28)/1000000 -> 1.52 | M28: =L28*$M$1 -> 0 | W28: =T28/H28 -> 0 | X28: 29552.4 | Y28: =X28*H28 -> 44919.649 | Z28: =Y28*0.95 -> 42673.666 | AA28: =ROUND(Z28,0) -> 42674
B29: 800 | C29: 800 | D29: 200 | E29: IP67 | F29: 2 | G29: SE2027 | H29: =2*(B29*C29+C29*D29+B29*D29)/1000000 -> 1.92 | M29: =L29*$M$1 -> 0 | W29: =T29/H29 -> 0 | X29: 28383.352 | Y29: =X29*H29 -> 54496.035 | Z29: =Y29*0.95 -> 51771.234 | AA29: =ROUND(Z29,0) -> 51771
B30: 800 | C30: 600 | D30: 250 | E30: IP67 | F30: 2 | G30: SE2028 | H30: =2*(B30*C30+C30*D30+B30*D30)/1000000 -> 1.66 | M30: =L30*$M$1 -> 0 | Q30: R5CEB08692 | R30: Навесной шкаф CE из нержавеющей стали (AISI 316), 800 x 600x 250мм, без фланца | S30: 60719.74 | T30: 42502.72 | W30: =T30/H30 -> 25604.048 | X30: 25604.048 | Y30: =X30*H30 -> 42502.72 | Z30: =Y30*0.95 -> 40377.584 | AA30: =ROUND(Z30,0) -> 40378
B31: 800 | C31: 600 | D31: 300 | E31: IP67 | F31: 2 | G31: SE2029 | H31: =2*(B31*C31+C31*D31+B31*D31)/1000000 -> 1.8 | M31: =L31*$M$1 -> 0 | Q31: R5CEB08632 | R31: Навесной шкаф CE из нержавеющей стали (AISI 316), 800 x 600x 300мм, без фланца | S31: 66610.8 | T31: 46626.35 | W31: =T31/H31 -> 25903.528 | X31: 25903.528 | Y31: =X31*H31 -> 46626.35 | Z31: =Y31*0.95 -> 44295.032 | AA31: =ROUND(Z31,0) -> 44295
B32: 800 | C32: 800 | D32: 300 | E32: IP67 | F32: 2 | G32: SE2030 | H32: =2*(B32*C32+C32*D32+B32*D32)/1000000 -> 2.24 | M32: =L32*$M$1 -> 0 | Q32: R5CEB08832 | R32: Навесной шкаф CE из нержавеющей стали (AISI 316), 800 x 800x 300мм, без фланца | S32: 77726.42 | T32: 54407.08 | W32: =T32/H32 -> 24288.875 | X32: 24288.875 | Y32: =X32*H32 -> 54407.08 | Z32: =Y32*0.95 -> 51686.726 | AA32: =ROUND(Z32,0) -> 51687
B33: 800 | C33: 600 | D33: 400 | E33: IP67 | F33: 2 | G33: SE2031 | H33: =2*(B33*C33+C33*D33+B33*D33)/1000000 -> 2.08 | M33: =L33*$M$1 -> 0 | Q33: R5CEB08642 | R33: Навесной шкаф CE из нержавеющей стали (AISI 316), 800 x 600x 400мм, без фланца | S33: 95290.27 | T33: 66701.45 | W33: =T33/H33 -> 32068.005 | X33: 32068.005 | Y33: =X33*H33 -> 66701.45 | Z33: =Y33*0.95 -> 63366.377 | AA33: =ROUND(Z33,0) -> 63366
B34: 800 | C34: 800 | D34: 400 | E34: IP67 | F34: 2 | G34: SE2032 | H34: =2*(B34*C34+C34*D34+B34*D34)/1000000 -> 2.56 | M34: =L34*$M$1 -> 0 | Q34: R5CEB08842 | R34: Навесной шкаф CE из нержавеющей стали (AISI 316), 800 x 800x 400мм, без фланца | S34: 109768.3 | T34: 76835.81 | W34: =T34/H34 -> 30013.988 | X34: 30013.988 | Y34: =X34*H34 -> 76835.81 | Z34: =Y34*0.95 -> 72994.019 | AA34: =ROUND(Z34,0) -> 72994
B35: 1000 | C35: 600 | D35: 250 | E35: IP66 | F35: 2 | G35: SE2033 | H35: =2*(B35*C35+C35*D35+B35*D35)/1000000 -> 2 | M35: =L35*$M$1 -> 0 | Q35: R5CEB10692 | R35: Навесной шкаф CE из нержавеющей стали (AISI 316), 1000 x 600 x 250мм, без фланца | S35: 69450.71 | T35: 48614.22 | W35: =T35/H35 -> 24307.11 | X35: 24307.11 | Y35: =X35*H35 -> 48614.22 | Z35: =Y35*0.95 -> 46183.509 | AA35: =ROUND(Z35,0) -> 46184
B36: 1000 | C36: 600 | D36: 300 | E36: IP66 | F36: 2 | G36: SE2034 | H36: =2*(B36*C36+C36*D36+B36*D36)/1000000 -> 2.16 | M36: =L36*$M$1 -> 0 | Q36: R5CEB10632 | R36: Навесной шкаф CE из нержавеющей стали (AISI 316), 1000 x 600 x 300мм, без фланца | S36: 75614.18 | T36: 52928.55 | W36: =T36/H36 -> 24503.958 | X36: 24503.958 | Y36: =X36*H36 -> 52928.55 | Z36: =Y36*0.95 -> 50282.122 | AA36: =ROUND(Z36,0) -> 50282
B37: 1000 | C37: 800 | D37: 300 | E37: IP66 | F37: 2 | G37: SE2035 | H37: =2*(B37*C37+C37*D37+B37*D37)/1000000 -> 2.68 | M37: =L37*$M$1 -> 0 | Q37: R5CEB10832 | R37: Навесной шкаф CE из нержавеющей стали (AISI 316), 1000 x 800 x 300мм, без фланца | S37: 92924.67 | T37: 65045.57 | W37: =T37/H37 -> 24270.735 | X37: 24270.735 | Y37: =X37*H37 -> 65045.57 | Z37: =Y37*0.95 -> 61793.291 | AA37: =ROUND(Z37,0) -> 61793
B38: 1000 | C38: 600 | D38: 400 | E38: IP66 | F38: 2 | G38: SE2036 | H38: =2*(B38*C38+C38*D38+B38*D38)/1000000 -> 2.48 | M38: =L38*$M$1 -> 0 | Q38: R5CEB10642 | R38: Навесной шкаф CE из нержавеющей стали (AISI 316), 1000 x 600 x 400мм, без фланца | S38: 106624.36 | T38: 74635.12 | W38: =T38/H38 -> 30094.806 | X38: 30094.806 | Y38: =X38*H38 -> 74635.12 | Z38: =Y38*0.95 -> 70903.364 | AA38: =ROUND(Z38,0) -> 70903
B39: 1000 | C39: 800 | D39: 400 | E39: IP66 | F39: 2 | G39: SE2037 | H39: =2*(B39*C39+C39*D39+B39*D39)/1000000 -> 3.04 | M39: =L39*$M$1 -> 0 | Q39: R5CEB10842 | R39: Навесной шкаф CE из нержавеющей стали (AISI 316), 1000 x 800 x 400мм, без фланца | S39: 123327.9 | T39: 86327.29 | W39: =T39/H39 -> 28397.135 | X39: 28397.135 | Y39: =X39*H39 -> 86327.29 | Z39: =Y39*0.95 -> 82010.925 | AA39: =ROUND(Z39,0) -> 82011
B40: 1200 | C40: 600 | D40: 200 | E40: IP66 | F40: 2 | G40: SE2038 | H40: =2*(B40*C40+C40*D40+B40*D40)/1000000 -> 2.16 | M40: =L40*$M$1 -> 0 | W40: =T40/H40 -> 0 | X40: 24503.958 | Y40: =X40*H40 -> 52928.55 | Z40: =Y40*0.95 -> 50282.122 | AA40: =ROUND(Z40,0) -> 50282
B41: 1200 | C41: 600 | D41: 300 | E41: IP66 | F41: 2 | G41: SE2039 | H41: =2*(B41*C41+C41*D41+B41*D41)/1000000 -> 2.52 | M41: =L41*$M$1 -> 0 | Q41: R5CEB12632 | R41: Навесной шкаф CE из нержавеющей стали (AISI 316), 1200 x 600 x 300мм, без фланца | S41: 85514.32 | T41: 59858.46 | W41: =T41/H41 -> 23753.357 | X41: 23753.357 | Y41: =X41*H41 -> 59858.46 | Z41: =Y41*0.95 -> 56865.537 | AA41: =ROUND(Z41,0) -> 56866
B42: 1200 | C42: 800 | D42: 300 | E42: IP66 | F42: 2 | G42: SE2040 | H42: =2*(B42*C42+C42*D42+B42*D42)/1000000 -> 3.12 | M42: =L42*$M$1 -> 0 | Q42: R5CEB12832 | R42: Навесной шкаф CE из нержавеющей стали (AISI 316), 1200 x 800 x 300мм, без фланца | S42: 100919.3 | T42: 70641.67 | W42: =T42/H42 -> 22641.561 | X42: 22641.561 | Y42: =X42*H42 -> 70641.67 | Z42: =Y42*0.95 -> 67109.586 | AA42: =ROUND(Z42,0) -> 67110
B43: 1200 | C43: 600 | D43: 400 | E43: IP66 | F43: 2 | G43: SE2041 | H43: =2*(B43*C43+C43*D43+B43*D43)/1000000 -> 2.88 | M43: =L43*$M$1 -> 0 | W43: =T43/H43 -> 0 | X43: 26581.188 | Y43: =X43*H43 -> 76553.82 | Z43: =Y43*0.95 -> 72726.129 | AA43: =ROUND(Z43,0) -> 72726
B44: 1200 | C44: 800 | D44: 400 | E44: IP66 | F44: 2 | G44: SE2042 | H44: =2*(B44*C44+C44*D44+B44*D44)/1000000 -> 3.52 | I44: 44850.6 | M44: =L44*$M$1 -> 0 | W44: =T44/H44 -> 0 | X44: 23709.193 | Y44: =X44*H44 -> 83456.359 | Z44: =Y44*0.95 -> 79283.541 | AA44: =ROUND(Z44,0) -> 79284
B45: 1400 | C45: 600 | D45: 300 | E45: IP66 | F45: 2 | G45: SE2043 | H45: =2*(B45*C45+C45*D45+B45*D45)/1000000 -> 2.88 | M45: =L45*$M$1 -> 0 | Q45: R5CEB14632 | R45: Навесной шкаф CE из нержавеющей стали (AISI 316), 1400 x 600 x 300мм, без фланца | S45: 109365.44 | T45: 76553.82 | W45: =T45/H45 -> 26581.188 | X45: 26581.188 | Y45: =X45*H45 -> 76553.82 | Z45: =Y45*0.95 -> 72726.129 | AA45: =ROUND(Z45,0) -> 72726
B46: 1400 | C46: 800 | D46: 300 | E46: IP66 | F46: 2 | G46: SE2044 | H46: =2*(B46*C46+C46*D46+B46*D46)/1000000 -> 3.56 | M46: =L46*$M$1 -> 0 | Q46: R5CEB14832 | R46: Навесной шкаф CE из нержавеющей стали (AISI 316), 1400 x 800 x 300мм, без фланца | S46: 129842.7 | T46: 90887.52 | W46: =T46/H46 -> 25530.202 | X46: 25530.202 | Y46: =X46*H46 -> 90887.52 | Z46: =Y46*0.95 -> 86343.144 | AA46: =ROUND(Z46,0) -> 86343
M47: =L47*$M$1 -> 0
J48: 1019500 | K48: AE Шкаф,нерж.сталь с МП1000x1200x300mm | L48: 1617.46 | M48: =L48*$M$1 -> 117346.72 | N48: 105 454.68 | O48: 108,799.21 | P48: 134,550.00

Sheet Лист1

Sheet Лист3
B2: Артикул | C2: Себестоимость | D2: Цена (продажная) | E2: Наценка %
B3: SE1020 | C3: 2774.3849 | D3: 4254.912 | E3: =(D3/C3-1)*100 -> 53.364157
B4: SE1001 | C4: 978.75 | D4: 2091.969 | E4: =(D4/C4-1)*100 -> 113.73885

Sheet Лист4
E1: 0.27 | F1: 32238.889 | H1: 0.27 | I1: =VLOOKUP(H1,$E$1:$F$44,2,FALSE) -> 32238.889 | L1: 32238.889
E2: 0.45 | F2: 21750 | H2: 0.315 | I2: =VLOOKUP(H2,$E$1:$F$44,2,FALSE) -> 22038.282 | L2: 22038.282
E3: 0.45 | F3: 21995 | H3: 0.36 | I3: =VLOOKUP(H3,$E$1:$F$44,2,FALSE) -> 20096.546 | L3: 20096.546
E4: 0.64 | F4: 18418.359 | H4: 0.45 | I4: =VLOOKUP(H4,$E$1:$F$44,2,FALSE) -> 21750 | L4: 21750
E5: 0.76 | F5: 18138.158 | H5: 0.52 | I5: =VLOOKUP(H5,$E$1:$F$44,2,FALSE) -> 19321.654 | L5: 19321.654
E6: 0.88 | F6: 16739.489 | H6: 0.45 | I6: =VLOOKUP(H6,$E$1:$F$44,2,FALSE) -> 21750 | L6: 21750
E7: 0.9 | F7: 17205 | H7: 0.52 | I7: =VLOOKUP(H7,$E$1:$F$44,2,FALSE) -> 19321.654 | L7: 19321.654
E8: 1.3 | F8: 15780 | H8: 0.64 | I8: =VLOOKUP(H8,$E$1:$F$44,2,FALSE) -> 18418.359 | L8: 18418.359
E9: 1.32 | F9: 15838.068 | H9: 0.88 | I9: =VLOOKUP(H9,$E$1:$F$44,2,FALSE) -> 16739.489 | L9: 16739.489
E10: 1.8 | F10: 14610.833 | H10: 0.54 | I10: =VLOOKUP(H10,$E$1:$F$44,2,FALSE) -> 18963.66 | L10: 18963.66
E11: 2.68 | F11: 13293.47 | H11: 0.62 | I11: =VLOOKUP(H11,$E$1:$F$44,2,FALSE) -> 18872.041 | L11: 18872.041
E12: 3.12 | F12: 13123.798 | H12: 0.76 | I12: =VLOOKUP(H12,$E$1:$F$44,2,FALSE) -> 18138.158 | L12: 18138.158
E13: 0.315 | F13: =_xlfn.FORECAST.LINEAR(E13,F1:F12,E1:E12) -> 22038.282 | H13: 0.9 | I13: =VLOOKUP(H13,$E$1:$F$44,2,FALSE) -> 17205 | L13: 17205
E14: 0.36 | F14: =_xlfn.FORECAST.LINEAR(E14,F2:F13,E2:E13) -> 20096.546 | H14: 1.04 | I14: =VLOOKUP(H14,$E$1:$F$44,2,FALSE) -> 17763.347 | L14: 17763.347
E15: 0.52 | F15: =_xlfn.FORECAST.LINEAR(E15,F3:F14,E3:E14) -> 19321.654 | H15: 0.85 | I15: =VLOOKUP(H15,$E$1:$F$44,2,FALSE) -> 18401.586 | L15: 18401.586
E16: 0.52 | F16: =_xlfn.FORECAST.LINEAR(E16,F4:F15,E4:E15) -> 18968.53 | H16: 1.1 | I16: =VLOOKUP(H16,$E$1:$F$44,2,FALSE) -> 17798.257 | L16: 17798.257
E17: 0.88 | F17: =_xlfn.FORECAST.LINEAR(E17,F5:F16,E5:E16) -> 17999.475 | H17: 1.26 | I17: =VLOOKUP(H17,$E$1:$F$44,2,FALSE) -> 17475.254 | L17: 17475.254
E18: 0.54 | F18: =_xlfn.FORECAST.LINEAR(E18,F6:F17,E6:E17) -> 18963.66 | H18: 0.88 | I18: =VLOOKUP(H18,$E$1:$F$44,2,FALSE) -> 16739.489 | L18: 16739.489
E19: 0.62 | F19: =_xlfn.FORECAST.LINEAR(E19,F7:F18,E7:E18) -> 18872.041 | H19: 1.04 | I19: =VLOOKUP(H19,$E$1:$F$44,2,FALSE) -> 17763.347 | L19: 17763.347
E20: 1.04 | F20: =_xlfn.FORECAST.LINEAR(E20,F8:F19,E8:E19) -> 17763.347 | H20: 0.98 | I20: =VLOOKUP(H20,$E$1:$F$44,2,FALSE) -> 18027.727 | L20: 18027.727
E21: 0.85 | F21: =_xlfn.FORECAST.LINEAR(E21,F9:F20,E9:E20) -> 18401.586 | H21: 1.32 | I21: =VLOOKUP(H21,$E$1:$F$44,2,FALSE) -> 15838.068 | L21: 15838.068
E22: 1.1 | F22: =_xlfn.FORECAST.LINEAR(E22,F10:F21,E10:E21) -> 17798.257 | H22: 1.28 | I22: =VLOOKUP(H22,$E$1:$F$44,2,FALSE) -> 17273.215 | L22: 17273.215
E23: 1.26 | F23: =_xlfn.FORECAST.LINEAR(E23,F11:F22,E11:E22) -> 17475.254 | H23: 1.68 | I23: =VLOOKUP(H23,$E$1:$F$44,2,FALSE) -> 16430.91 | L23: 16430.91
E24: 1.04 | F24: =_xlfn.FORECAST.LINEAR(E24,F12:F23,E12:E23) -> 18108.935 | H24: 1.18 | I24: =VLOOKUP(H24,$E$1:$F$44,2,FALSE) -> 17572.498 | L24: 17572.498
... E44: 3.56 | F44: =_xlfn.FORECAST.LINEAR(E44,F32:F43,E32:E43) -> 12103.835 | H44: 3.56 | I44: =VLOOKUP(H44,$E$1:$F$44,2,FALSE) -> 12103.835 | L44: 12103.835

Sheet Лист5
B2: R5CEB03312 | C2: Навесной шкаф CE из нержавеющей стали (AISI 316), 300 x 300x 150мм, без фланца | D2: 21684.53
B3: R5CEB03412 | C3: Навесной шкаф CE из нержавеющей стали (AISI 316), 300 x 400x 150мм, без фланца | D3: 23771.11
B4: R5CEB03912 | C4: Навесной шкаф CE из нержавеющей стали (AISI 316), 300 x 250x 150мм, без фланца | D4: 20632.7
B5: R5CEB04312 | C5: Навесной шкаф CE из нержавеющей стали (AISI 316), 400 x 300x 150мм, без фланца | D5: 23835.21
B6: R5CEB04322 | C6: Навесной шкаф CE из нержавеющей стали (AISI 316), 400 x 300x 200мм, без фланца | D6: 27932.76
B7: R5CEB04422 | C7: Навесной шкаф CE из нержавеющей стали (AISI 316), 400 x 400x 200мм, без фланца | D7: 31491.77
B8: R5CEB04622 | C8: Навесной шкаф CE из нержавеющей стали (AISI 316), 400 x 600x 200мм, без фланца | D8: 37124.4
B9: R5CEB05312 | C9: Навесной шкаф CE из нержавеющей стали (AISI 316), 500 x 300x 150мм, без фланца | D9: 26181.97
B10: R5CEB05322 | C10: Навесной шкаф CE из нержавеющей стали (AISI 316), 500 x 300x 200мм, без фланца | D10: 31233.88
B11: R5CEB05422 | C11: Навесной шкаф CE из нержавеющей стали (AISI 316), 500 x 400x 200мм, без фланца | D11: 34472.77
B12: R5CEB05492 | C12: Навесной шкаф CE из нержавеющей стали (AISI 316), 500 x 400x 250мм, без фланца | D12: 39029.01
B13: R5CEB05522 | C13: Навесной шкаф CE из нержавеющей стали (AISI 316), 500 x 500x 200мм, без фланца | D13: 37703.77
... B34: R5CEB14832 | C34: Навесной шкаф CE из нержавеющей стали (AISI 316), 1400 x 800 x 300мм, без фланца | D34: 129842.7

Sheet Лист6
C3: 300 | D3: 0.27 | E3: =_xlfn.FORECAST.LINEAR(D3,E4:E6,D4:D6) -> 48442.696 | T3: 0.27 | U3: =VLOOKUP(T3,$P$4:$Q$46,2,FALSE) -> 35948.292 | W3: 35948.292
D4: 0.315 | E4: 45849.238 | P4: 0.315 | Q4: 45849.238 | T4: 0.315 | U4: =VLOOKUP(T4,$P$4:$Q$46,2,FALSE) -> 45849.238 | W4: 45849.238
D5: 0.36 | E5: 42163.25 | P5: 0.36 | Q5: 42163.25 | T5: 0.36 | U5: =VLOOKUP(T5,$P$4:$Q$46,2,FALSE) -> 42163.25 | W5: 42163.25
D6: 0.45 | E6: 36976.333 | P6: 0.45 | Q6: 36976.333 | T6: 0.45 | U6: =VLOOKUP(T6,$P$4:$Q$46,2,FALSE) -> 36976.333 | W6: 36976.333
D7: 0.52 | E7: =_xlfn.FORECAST.LINEAR(D7,E3:E6,D3:D6) -> 32300.42 | P7: 0.45 | Q7: 37076.022 | T7: 0.52 | U7: =VLOOKUP(T7,$P$4:$Q$46,2,FALSE) -> 37600.808 | W7: 37600.808
C8: 400 | D8: 0.45 | E8: 37076.022 | P8: 0.52 | Q8: 37600.808 | T8: 0.45 | U8: =VLOOKUP(T8,$P$4:$Q$46,2,FALSE) -> 36976.333 | W8: 36976.333
D9: 0.52 | E9: 37600.808 | P9: 0.54 | Q9: 33938.704 | T9: 0.52 | U9: =VLOOKUP(T9,$P$4:$Q$46,2,FALSE) -> 37600.808 | W9: 37600.808
D10: 0.64 | E10: 34443.219 | P10: 0.62 | Q10: 35263.129 | T10: 0.64 | U10: =VLOOKUP(T10,$P$4:$Q$46,2,FALSE) -> 34443.219 | W10: 34443.219
D11: 0.88 | E11: 29530.011 | P11: 0.64 | Q11: 34443.219 | T11: 0.88 | U11: =VLOOKUP(T11,$P$4:$Q$46,2,FALSE) -> 29530.011 | W11: 29530.011
C12: 500 | D12: 0.54 | E12: 33938.704 | P12: 0.76 | Q12: 31750.408 | T12: 0.54 | U12: =VLOOKUP(T12,$P$4:$Q$46,2,FALSE) -> 33938.704 | W12: 33938.704
D13: 0.62 | E13: 35263.129 | P13: 0.85 | Q13: 32140.694 | T13: 0.62 | U13: =VLOOKUP(T13,$P$4:$Q$46,2,FALSE) -> 35263.129 | W13: 35263.129
D14: 0.76 | E14: 31750.408 | P14: 0.88 | Q14: 29530.011 | T14: 0.76 | U14: =VLOOKUP(T14,$P$4:$Q$46,2,FALSE) -> 31750.408 | W14: 31750.408
D15: 0.9 | E15: 29324.389 | P15: 0.88 | Q15: 29700.091 | T15: 0.9 | U15: =VLOOKUP(T15,$P$4:$Q$46,2,FALSE) -> 29324.389 | W15: 29324.389
D16: 1.04 | E16: =_xlfn.FORECAST.LINEAR(D16,E12:E15,D12:D15) -> 27543.164 | P16: 0.9 | Q16: 29324.389 | T16: 1.04 | U16: =VLOOKUP(T16,$P$4:$Q$46,2,FALSE) -> 31707.528 | W16: 31710.959
D17: 0.85 | E17: 32140.694 | P17: 0.98 | Q17: 30030.245 | T17: 0.85 | U17: =VLOOKUP(T17,$P$4:$Q$46,2,FALSE) -> 32140.694 | W17: 32140.694
D18: 1.1 | E18: =_xlfn.FORECAST.LINEAR(D18,E12:E17,D12:D17) -> 27144.122 | P18: 1.18 | Q18: 27518.89 | T18: 1.1 | U18: =VLOOKUP(T18,$P$4:$Q$46,2,FALSE) -> 31160.418 | W18: 31341.426
D19: 1.26 | E19: =_xlfn.FORECAST.LINEAR(D19,E13:E18,D13:D18) -> 24042.984 | P19: 1.28 | Q19: 39356.328 | T19: 1.26 | U19: =VLOOKUP(T19,$P$4:$Q$46,2,FALSE) -> 30430.77 | W19: 30634.881
C20: 600 | D20: 0.88 | E20: 29700.091 | P20: 1.3 | Q20: 27735.8 | T20: 0.88 | U20: =VLOOKUP(T20,$P$4:$Q$46,2,FALSE) -> 29530.011 | W20: 29530.011
D21: 1.04 | E21: =_xlfn.FORECAST.LINEAR(D21,E22:E25,D22:D25) -> 31770.451 | P21: 1.32 | Q21: 26442.811 | T21: 1.04 | U21: =VLOOKUP(T21,$P$4:$Q$46,2,FALSE) -> 31707.528 | W21: 31710.959
D22: 0.98 | E22: 30030.245 | P22: 1.66 | Q22: 25604.048 | T22: 0.98 | U22: =VLOOKUP(T22,$P$4:$Q$46,2,FALSE) -> 30030.245 | W22: 30030.245
D23: 1.32 | E23: 26442.811 | P23: 1.68 | Q23: 30529.435 | T23: 1.32 | U23: =VLOOKUP(T23,$P$4:$Q$46,2,FALSE) -> 26442.811 | W23: 26442.811
D24: 1.28 | E24: 39356.328 | P24: 1.8 | Q24: 25903.528 | T24: 1.28 | U24: =VLOOKUP(T24,$P$4:$Q$46,2,FALSE) -> 39356.328 | W24: 39356.328
D25: 1.68 | E25: 30529.435 | P25: 2 | Q25: 24307.11 | T25: 1.68 | U25: =VLOOKUP(T25,$P$4:$Q$46,2,FALSE) -> 30529.435 | W25: 30529.435
C26: 700 | D26: 1.18 | E26: 27518.89 | P26: 2.08 | Q26: 32068.005 | T26: 1.18 | U26: =VLOOKUP(T26,$P$4:$Q$46,2,FALSE) -> 27518.89 | W26: 27518.89
D27: 1.3 | E27: 27735.8 | P27: 2.16 | Q27: 24503.958 | T27: 1.3 | U27: =VLOOKUP(T27,$P$4:$Q$46,2,FALSE) -> 27735.8 | W27: 27735.8
C28: 800 | D28: 1.52 | E28: =_xlfn.FORECAST.LINEAR(D28,E29:E34,D29:D34) -> 25490.62 | P28: 2.24 | Q28: 24288.875 | T28: 1.52 | U28: =VLOOKUP(T28,$P$4:$Q$46,2,FALSE) -> 29578.482 | W28: 29552.4
D29: 1.92 | E29: =_xlfn.FORECAST.LINEAR(D29,E30:E34,D30:D34) -> 27012.568 | P29: 2.48 | Q29: 30094.806 | T29: 1.92 | U29: =VLOOKUP(T29,$P$4:$Q$46,2,FALSE) -> 28304.258 | W29: 28383.352
D30: 1.66 | E30: 25604.048 | P30: 2.52 | Q30: 23753.357 | T30: 1.66 | U30: =VLOOKUP(T30,$P$4:$Q$46,2,FALSE) -> 25604.048 | W30: 25604.048
D31: 1.8 | E31: 25903.528 | P31: 2.56 | Q31: 30013.988 | T31: 1.8 | U31: =VLOOKUP(T31,$P$4:$Q$46,2,FALSE) -> 25903.528 | W31: 25903.528
D32: 2.24 | E32: 24288.875 | P32: 2.68 | Q32: 24270.735 | T32: 2.24 | U32: =VLOOKUP(T32,$P$4:$Q$46,2,FALSE) -> 24288.875 | W32: 24288.875
D33: 2.08 | E33: 32068.005 | P33: 2.88 | Q33: 26581.188 | T33: 2.08 | U33: =VLOOKUP(T33,$P$4:$Q$46,2,FALSE) -> 32068.005 | W33: 32068.005
D34: 2.56 | E34: 30013.988 | P34: 3.04 | Q34: 28397.135 | T34: 2.56 | U34: =VLOOKUP(T34,$P$4:$Q$46,2,FALSE) -> 30013.988 | W34: 30013.988
C35: 1000 | D35: 2 | E35: 24307.11 | P35: 3.12 | Q35: 22641.561 | T35: 2 | U35: =VLOOKUP(T35,$P$4:$Q$46,2,FALSE) -> 24307.11 | W35: 24307.11
D36: 2.16 | E36: 24503.958 | P36: 3.56 | Q36: 25530.202 | T36: 2.16 | U36: =VLOOKUP(T36,$P$4:$Q$46,2,FALSE) -> 24503.958 | W36: 24503.958
D37: 2.68 | E37: 24270.735 | P37: 0.27 | Q37: =_xlfn.FORECAST.LINEAR(P37,Q4:Q36,P4:P36) -> 35948.292 | T37: 2.68 | U37: =VLOOKUP(T37,$P$4:$Q$46,2,FALSE) -> 24270.735 | W37: 24270.735
D38: 2.48 | E38: 30094.806 | P38: 0.52 | Q38: =_xlfn.FORECAST.LINEAR(P38,Q5:Q36,P5:P36) -> 34047.925 | T38: 2.48 | U38: =VLOOKUP(T38,$P$4:$Q$46,2,FALSE) -> 30094.806 | W38: 30094.806
D39: 3.04 | E39: 28397.135 | P39: 1.04 | Q39: =_xlfn.FORECAST.LINEAR(P39,Q6:Q38,P6:P38) -> 31707.528 | T39: 3.04 | U39: =VLOOKUP(T39,$P$4:$Q$46,2,FALSE) -> 28397.135 | W39: 28397.135
C40: 1200 | D40: 2.16 | E40: =_xlfn.FORECAST.LINEAR(D40,E41:E42,D41:D42) -> 24420.435 | P40: 1.04 | Q40: =_xlfn.FORECAST.LINEAR(P40,Q7:Q39,P7:P39) -> 31545.095 | T40: 2.16 | U40: =VLOOKUP(T40,$P$4:$Q$46,2,FALSE) -> 24503.958 | W40: 24503.958
D41: 2.52 | E41: 23753.357 | P41: 1.1 | Q41: =_xlfn.FORECAST.LINEAR(P41,Q8:Q40,P8:P40) -> 31160.418 | T41: 2.52 | U41: =VLOOKUP(T41,$P$4:$Q$46,2,FALSE) -> 23753.357 | W41: 23753.357
D42: 3.12 | E42: 22641.561 | P42: 1.26 | Q42: =_xlfn.FORECAST.LINEAR(P42,Q9:Q41,P9:P41) -> 30430.77 | T42: 3.12 | U42: =VLOOKUP(T42,$P$4:$Q$46,2,FALSE) -> 22641.561 | W42: 22641.561
D43: 2.88 | E43: =_xlfn.FORECAST.LINEAR(D43,E40:E42,D40:D42) -> 23086.279 | P43: 1.52 | Q43: =_xlfn.FORECAST.LINEAR(P43,Q10:Q42,P10:P42) -> 29578.482 | T43: 2.88 | U43: =VLOOKUP(T43,$P$4:$Q$46,2,FALSE) -> 26581.188 | W43: 26581.188
D44: 3.52 | E44: =_xlfn.FORECAST.LINEAR(D44,E40:E43,D40:D43) -> 21900.363 | P44: 1.92 | Q44: =_xlfn.FORECAST.LINEAR(P44,Q11:Q43,P11:P43) -> 28304.258 | T44: 3.52 | U44: =VLOOKUP(T44,$P$4:$Q$47,2,FALSE) -> 23810.972 | W44: 23709.193
C45: 1400 | D45: 2.88 | E45: 26581.188 | P45: 2.16 | Q45: =_xlfn.FORECAST.LINEAR(P45,Q12:Q44,P12:P44) -> 27583.854 | T45: 2.88 | U45: =VLOOKUP(T45,$P$4:$Q$46,2,FALSE) -> 26581.188 | W45: 26581.188
D46: 3.56 | E46: 25530.202 | P46: 2.88 | Q46: =_xlfn.FORECAST.LINEAR(P46,Q13:Q45,P13:P45) -> 25564.754 | T46: 3.56 | U46: =VLOOKUP(T46,$P$4:$Q$46,2,FALSE) -> 25530.202 | W46: 25530.202
P47: 3.52 | Q47: =_xlfn.FORECAST.LINEAR(P47,Q14:Q46,P14:P46) -> 23810.972
